Workbook

Sheet README
A1: Unit 11 - Individual Project: Executive Summary (Quantitative Risk Model)
A3: Purpose: estimate the probability and cost of quality, supply and continuity risks for the international, digitalised business.
A4: Method: Factor Analysis of Information Risk (FAIR) structure with Monte Carlo simulation; inputs are calibrated PERT (min, most likely, max) estimates.
A7: How to use:
A8: 1. Edit only the BLUE cells on the 'Inputs' sheet. Everything else recalculates.
A9: 2. 'Model' shows the deterministic results (expected values and closed-form probabilities).
A10: 3. 'Simulation' runs a live Monte Carlo (press F9 / recalc to reshuffle) and returns the mean and 90th/95th percentile loss.
A12: Colour code:
A13: Blue text = editable input (your assumption).
A14: Black text = formula / calculation.
A15: Green text = link to another sheet.
A16: Grey text = notes.
... A32: Results vary slightly each recalculation because the draws are random; more iterations give a smoother estimate.

Sheet Inputs
A1: Inputs (edit blue cells only)
A2: All blue cells are your assumptions. Sources go in the notes column.
A4: BUSINESS BASE (target scale)
A5: Assumption | B5: Low | C5: Most likely | D5: High | E5: Unit | L5: Source / notes
A6: Revenue | B6: 3000000 | C6: 7000000 | D6: 15000000 | E6: £ | L6: Modelled scale-up from ONS (2023), IBISWorld (2025), Pet Gazette (2025) anchors
A7: Gross margin | B7: 0.35 | C7: 0.45 | D7: 0.55 | E7: % | L7: Pet retail ~40% (trade sources); premium own-made higher
A8: Online share of revenue | B8: 0.25 | C8: 0.4 | D8: 0.6 | E8: % | L8: Sector e-commerce shift
A10: QUALITY RISKS (magnitude as % of revenue)
A11: Risk | B11: F low | C11: F ml | D11: F high | E11: V low | F11: V ml | G11: V high | H11: Mag% low | I11: Mag% ml | J11: Mag% high | L11: Evidence basis
A12: R1 Cold-chain excursion | B12: 1 | C12: 3 | D12: 8 | E12: 0.15 | F12: 0.3 | G12: 0.55 | H12: 0.001 | I12: 0.003 | J12: 0.01 | L12: R1, R2, R4: calibrated expert judgement - no firm-specific public data (weak/moderate knowledge)
A13: R2 Transit delay / spoilage | B13: 0.5 | C13: 2 | D13: 5 | E13: 0.1 | F13: 0.25 | G13: 0.5 | H13: 0.001 | I13: 0.004 | J13: 0.015 | L13: R3 recall frequency: anchored to FDA (~9 US pet-food recalls/yr industry-wide) and FSA recall data, scaled for a single premium producer with new international suppliers
A14: R3 Contamination / recall | B14: 0.1 | C14: 0.25 | D14: 0.8 | E14: 0.3 | F14: 0.6 | G14: 0.9 | H14: 0.02 | I14: 0.05 | J14: 0.1 | L14: R5 inter-hub variance: calibrated judgement; brand-critical, weak knowledge
A15: R4 Supplier quality drift | B15: 0.3 | C15: 1 | D15: 3 | E15: 0.2 | F15: 0.4 | G15: 0.7 | H15: 0.001 | I15: 0.0035 | J15: 0.012
A16: R5 Inter-hub variance | B16: 0.2 | C16: 0.6 | D16: 1.5 | E16: 0.4 | F16: 0.6 | G16: 0.85 | H16: 0.005 | I16: 0.01 | J16: 0.03
A18: F = events per year; V = P(quality harmed | event); Mag% = loss as a share of annual revenue.
A20: SUPPLY CHAIN
A21: Assumption | B21: Low | C21: Most likely | D21: High | L21: Notes
A22: Disruption frequency (/yr) | B22: 0.8 | C22: 1.5 | D22: 3.5 | L22: Supply frequency & duration: anchored to McKinsey (2020) - month-plus disruptions every 3.7 years (~0.27/yr)
A23: Disruption duration (days) | B23: 3 | C23: 10 | D23: 80
A24: Buffer stock (days) | B24: 42
A26: PRODUCTION HUBS
A27: Per-hub annual disruption probability (q) | B27: 0.05 | L27: Hub q: calibrated judgement (weak knowledge)
A29: ONLINE AVAILABILITY
A30: Target unplanned downtime (minutes/yr) | B30: 5.26 | L30: 5.26 = 99.999% ; 52.6 = 99.99%
A32: VENDOR LOCK-IN
A33: Assumption (£k) | B33: Low | C33: Most likely | D33: High | L33: Notes
A34: P(forced migration in horizon) | B34: 0.3
A35: Switch cost, high lock-in (£k) | B35: 350 | C35: 600 | D35: 1000 | L35: Switch costs reflect the ERP/WMS orchestrating the automated warehouses (operational, not just back-office); exit requires re-integrating physical fulfilment.
A36: Switch cost, low lock-in (£k) | B36: 100 | C36: 200 | D36: 400
A38: DATA BREACH
A39: Assumption | B39: Low | C39: Most likely | D39: High | L39: Notes
A40: P(reportable breach /yr) | B40: 0.15 | L40: Breach: anchored to IBM (2025) Cost of a Data Breach; UK average £3.29m used as upper bound; SME estimate below it
A41: Breach magnitude (% of revenue) | B41: 0.02 | C41: 0.04 | D41: 0.08

Sheet Model
A1: Deterministic Model (expected values and closed-form probabilities)
A2: All figures link to 'Inputs'. PERT mean = (low + 4×most likely + high) / 6.
A4: QUALITY
A5: Risk | B5: F mean | C5: V mean | D5: rate = F×V | E5: Mag mean (£) | F5: Expected loss (£) | H5: aF | I5: bF | J5: aV | K5: bV | L5: aMag | M5: bMag
A6: =Inputs!A12 -> R1 Cold-chain excursion | B6: =(Inputs!B12+4*Inputs!C12+Inputs!D12)/6 -> 3.5 | C6: =(Inputs!E12+4*Inputs!F12+Inputs!G12)/6 -> 0.31666667 | D6: =B6*C6 -> 1.1083333 | E6: =((Inputs!H12+4*Inputs!I12+Inputs!J12)/6)*Inputs!$C$6 -> 26833.333 | F6: =D6*E6 -> 29740.278 | H6: =1+4*(Inputs!C12-Inputs!B12)/(Inputs!D12-Inputs!B12) -> 2.1428571 | I6: =1+4*(Inputs!D12-Inputs!C12)/(Inputs!D12-Inputs!B12) -> 3.8571429 | J6: =1+4*(Inputs!F12-Inputs!E12)/(Inputs!G12-Inputs!E12) -> 2.5 | K6: =1+4*(Inputs!G12-Inputs!F12)/(Inputs!G12-Inputs!E12) -> 3.5 | L6: =1+4*(Inputs!I12-Inputs!H12)/(Inputs!J12-Inputs!H12) -> 1.8888889 | M6: =1+4*(Inputs!J12-Inputs!I12)/(Inputs!J12-Inputs!H12) -> 4.1111111
A7: =Inputs!A13 -> R2 Transit delay / spoilage | B7: =(Inputs!B13+4*Inputs!C13+Inputs!D13)/6 -> 2.25 | C7: =(Inputs!E13+4*Inputs!F13+Inputs!G13)/6 -> 0.26666667 | D7: =B7*C7 -> 0.6 | E7: =((Inputs!H13+4*Inputs!I13+Inputs!J13)/6)*Inputs!$C$6 -> 37333.333 | F7: =D7*E7 -> 22400 | H7: =1+4*(Inputs!C13-Inputs!B13)/(Inputs!D13-Inputs!B13) -> 2.3333333 | I7: =1+4*(Inputs!D13-Inputs!C13)/(Inputs!D13-Inputs!B13) -> 3.6666667 | J7: =1+4*(Inputs!F13-Inputs!E13)/(Inputs!G13-Inputs!E13) -> 2.5 | K7: =1+4*(Inputs!G13-Inputs!F13)/(Inputs!G13-Inputs!E13) -> 3.5 | L7: =1+4*(Inputs!I13-Inputs!H13)/(Inputs!J13-Inputs!H13) -> 1.8571429 | M7: =1+4*(Inputs!J13-Inputs!I13)/(Inputs!J13-Inputs!H13) -> 4.1428571
A8: =Inputs!A14 -> R3 Contamination / recall | B8: =(Inputs!B14+4*Inputs!C14+Inputs!D14)/6 -> 0.31666667 | C8: =(Inputs!E14+4*Inputs!F14+Inputs!G14)/6 -> 0.6 | D8: =B8*C8 -> 0.19 | E8: =((Inputs!H14+4*Inputs!I14+Inputs!J14)/6)*Inputs!$C$6 -> 373333.33 | F8: =D8*E8 -> 70933.333 | H8: =1+4*(Inputs!C14-Inputs!B14)/(Inputs!D14-Inputs!B14) -> 1.8571429 | I8: =1+4*(Inputs!D14-Inputs!C14)/(Inputs!D14-Inputs!B14) -> 4.1428571 | J8: =1+4*(Inputs!F14-Inputs!E14)/(Inputs!G14-Inputs!E14) -> 3 | K8: =1+4*(Inputs!G14-Inputs!F14)/(Inputs!G14-Inputs!E14) -> 3 | L8: =1+4*(Inputs!I14-Inputs!H14)/(Inputs!J14-Inputs!H14) -> 2.5 | M8: =1+4*(Inputs!J14-Inputs!I14)/(Inputs!J14-Inputs!H14) -> 3.5
A9: =Inputs!A15 -> R4 Supplier quality drift | B9: =(Inputs!B15+4*Inputs!C15+Inputs!D15)/6 -> 1.2166667 | C9: =(Inputs!E15+4*Inputs!F15+Inputs!G15)/6 -> 0.41666667 | D9: =B9*C9 -> 0.50694444 | E9: =((Inputs!H15+4*Inputs!I15+Inputs!J15)/6)*Inputs!$C$6 -> 31500 | F9: =D9*E9 -> 15968.75 | H9: =1+4*(Inputs!C15-Inputs!B15)/(Inputs!D15-Inputs!B15) -> 2.037037 | I9: =1+4*(Inputs!D15-Inputs!C15)/(Inputs!D15-Inputs!B15) -> 3.962963 | J9: =1+4*(Inputs!F15-Inputs!E15)/(Inputs!G15-Inputs!E15) -> 2.6 | K9: =1+4*(Inputs!G15-Inputs!F15)/(Inputs!G15-Inputs!E15) -> 3.4 | L9: =1+4*(Inputs!I15-Inputs!H15)/(Inputs!J15-Inputs!H15) -> 1.9090909 | M9: =1+4*(Inputs!J15-Inputs!I15)/(Inputs!J15-Inputs!H15) -> 4.0909091
A10: =Inputs!A16 -> R5 Inter-hub variance | B10: =(Inputs!B16+4*Inputs!C16+Inputs!D16)/6 -> 0.68333333 | C10: =(Inputs!E16+4*Inputs!F16+Inputs!G16)/6 -> 0.60833333 | D10: =B10*C10 -> 0.41569444 | E10: =((Inputs!H16+4*Inputs!I16+Inputs!J16)/6)*Inputs!$C$6 -> 87500 | F10: =D10*E10 -> 36373.264 | H10: =1+4*(Inputs!C16-Inputs!B16)/(Inputs!D16-Inputs!B16) -> 2.2307692 | I10: =1+4*(Inputs!D16-Inputs!C16)/(Inputs!D16-Inputs!B16) -> 3.7692308 | J10: =1+4*(Inputs!F16-Inputs!E16)/(Inputs!G16-Inputs!E16) -> 2.7777778 | K10: =1+4*(Inputs!G16-Inputs!F16)/(Inputs!G16-Inputs!E16) -> 3.2222222 | L10: =1+4*(Inputs!I16-Inputs!H16)/(Inputs!J16-Inputs!H16) -> 1.8 | M10: =1+4*(Inputs!J16-Inputs!I16)/(Inputs!J16-Inputs!H16) -> 4.2
A11: Total / result | D11: =SUM(D6:D10) -> 2.8209722 | F11: =SUM(F6:F10) -> 175415.62 | H11: Note
A13: P(≥1 quality-affecting event / yr) | B13: =1-EXP(-D11) -> 0.94045198
A14: P(serious / recall event, R3) / yr | B14: =1-EXP(-D8) -> 0.17304087
A15: P(brand-material inter-hub variance, R5) / yr | B15: =1-EXP(-D10) -> 0.34011813
A16: Expected annual quality loss (£) | B16: =F11 -> 175415.62
A19: DERIVED UNITS (at most-likely base)
A20: Revenue per day (£) | B20: =Inputs!C6/365 -> 19178.082
A21: Gross margin per day (£) | B21: =Inputs!C6*Inputs!C7/365 -> 8630.137
A22: Online revenue per minute (£) | B22: =Inputs!C6*Inputs!C8/525600 -> 5.3272451
A23: Online revenue per hour (£) | B23: =Inputs!C6*Inputs!C8/525600*60 -> 319.6347
A25: SUPPLY AVAILABILITY
A26: Disruption frequency mean (/yr) | B26: =(Inputs!B22+4*Inputs!C22+Inputs!D22)/6 -> 1.7166667
A27: Duration alpha / beta | B27: =1+4*(Inputs!C23-Inputs!B23)/(Inputs!D23-Inputs!B23) -> 1.3636364 | C27: =1+4*(Inputs!D23-Inputs!C23)/(Inputs!D23-Inputs!B23) -> 4.6363636
A28: Note: Buffer-exceeding (month-plus) disruption rate vs McKinsey (2020) ~0.27/yr (every 3.7 yrs)
A29: Buffer (days) | B29: P(≥1 stockout / yr)
A30: 14 | B30: =1-EXP(-B$26*(1-BETADIST((A30-Inputs!B23)/(Inputs!D23-Inputs!B23),B$27,C$27))) -> 0.66409876
A31: 21 | B31: =1-EXP(-B$26*(1-BETADIST((A31-Inputs!B23)/(Inputs!D23-Inputs!B23),B$27,C$27))) -> 0.50886971
A32: 28 | B32: =1-EXP(-B$26*(1-BETADIST((A32-Inputs!B23)/(Inputs!D23-Inputs!B23),B$27,C$27))) -> 0.34639894
A33: 42 | B33: =1-EXP(-B$26*(1-BETADIST((A33-Inputs!B23)/(Inputs!D23-Inputs!B23),B$27,C$27))) -> 0.10487549
A34: 60 | B34: =1-EXP(-B$26*(1-BETADIST((A34-Inputs!B23)/(Inputs!D23-Inputs!B23),B$27,C$27))) -> 0.006246476
A35: Stockout cost per day beyond buffer (£) = gross margin per day | B35: =Inputs!C6*Inputs!C7/365 -> 8630.137
A36: Note: buffer alone cannot cover month-plus disruptions; dual sourcing and multi-hub redundancy are the primary controls.
A38: PRODUCTION-HUB AVAILABILITY
A39: P(≥2 of 3 hubs down) = 3q²(1−q)+q³ | B39: =3*Inputs!B27^2*(1-Inputs!B27)+Inputs!B27^3 -> 0.00725
A41: ONLINE DOWNTIME (direct lost sales)
A42: Direct lost online sales at target downtime (£/yr) | B42: =Inputs!C6*Inputs!C8/525600*Inputs!B30 -> 28.021309
A43: Note: direct cost is small; the requirement is justified by reputation, not transactions.
A45: VENDOR LOCK-IN
A46: Switch cost high-lock mean (£k) | B46: =(Inputs!B35+4*Inputs!C35+Inputs!D35)/6 -> 625
A47: Switch cost low-lock mean (£k) | B47: =(Inputs!B36+4*Inputs!C36+Inputs!D36)/6 -> 216.66667
A48: Decision value of low-lock platform (£k) | B48: =Inputs!B34*(B46-B47) -> 122.5
A50: DATA BREACH
A51: Expected loss given breach (£) | B51: =((Inputs!B41+4*Inputs!C41+Inputs!D41)/6)*Inputs!C6 -> 303333.33
A52: Annualised breach loss (£) | B52: =Inputs!B40*B51 -> 45500

Sheet Simulation
A2: Summary (simulated annual quality loss)
A3: Mean (£) | C3: =AVERAGE(AK12:AK1011) -> 169364.74
A4: Median P50 (£) | C4: =MEDIAN(AK12:AK1011) -> 108457.25
A5: P90 (£) | C5: =PERCENTILE(AK12:AK1011,0.9) -> 448901.86
A6: P95 (£) | C6: =PERCENTILE(AK12:AK1011,0.95) -> 560636.32
A8: Live Monte Carlo (Quality Loss). Recalculate (F9) to reshuffle.
A9: 1000 iterations. Each row samples F, V and magnitude from their PERT distributions and draws a Poisson event count.
B11: R1 F | C11: R1 V | D11: R1 mag | E11: R1 r | F11: R1 u | G11: R1 count | H11: R1 loss | I11: R2 F | J11: R2 V | K11: R2 mag | L11: R2 r | M11: R2 u | N11: R2 count | O11: R2 loss | P11: R3 F | Q11: R3 V | R11: R3 mag | S11: R3 r | T11: R3 u | U11: R3 count | V11: R3 loss | W11: R4 F | X11: R4 V | Y11: R4 mag | Z11: R4 r | AA11: R4 u | AB11: R4 count | AC11: R4 loss | AD11: R5 F | AE11: R5 V | AF11: R5 mag | AG11: R5 r | AH11: R5 u | AI11: R5 count | AJ11: R5 loss | AK11: Total loss
B12: =Inputs!B12+(Inputs!D12-Inputs!B12)*BETAINV(RAND(),Model!H6,Model!I6) -> 3.4165347 | C12: =Inputs!E12+(Inputs!G12-Inputs!E12)*BETAINV(RAND(),Model!J6,Model!K6) -> 0.31316026 | D12: =(Inputs!H12+(Inputs!J12-Inputs!H12)*BETAINV(RAND(),Model!L6,Model!M6))*Inputs!$C$6 -> 41359.902 | E12: =B12*C12 -> 1.0699229 | F12: =RAND() -> 0.4657148 | G12: =IF(F12<EXP(-E12),0,IF(F12<EXP(-E12)*(1+E12),1,IF(F12<EXP(-E12)*(1+E12+E12^2/2),2,IF(F12<EXP(-E12)*(1+E12+E12^2/2+E12^3/6),3,4)))) -> 1 | H12: =G12*D12 -> 41359.902 | I12: =Inputs!B13+(Inputs!D13-Inputs!B13)*BETAINV(RAND(),Model!H7,Model!I7) -> 1.1863252 | J12: =Inputs!E13+(Inputs!G13-Inputs!E13)*BETAINV(RAND(),Model!J7,Model!K7) -> 0.22191204 | K12: =(Inputs!H13+(Inputs!J13-Inputs!H13)*BETAINV(RAND(),Model!L7,Model!M7))*Inputs!$C$6 -> 36519.383 | L12: =I12*J12 -> 0.26325985 | M12: =RAND() -> 0.034776356 | N12: =IF(M12<EXP(-L12),0,IF(M12<EXP(-L12)*(1+L12),1,IF(M12<EXP(-L12)*(1+L12+L12^2/2),2,IF(M12<EXP(-L12)*(1+L12+L12^2/2+L12^3/6),3,4)))) -> 0 | O12: =N12*K12 -> 0 | P12: =Inputs!B14+(Inputs!D14-Inputs!B14)*BETAINV(RAND(),Model!H8,Model!I8) -> 0.32088482 | Q12: =Inputs!E14+(Inputs!G14-Inputs!E14)*BETAINV(RAND(),Model!J8,Model!K8) -> 0.74627 | R12: =(Inputs!H14+(Inputs!J14-Inputs!H14)*BETAINV(RAND(),Model!L8,Model!M8))*Inputs!$C$6 -> 305314.33 | S12: =P12*Q12 -> 0.23946672 | T12: =RAND() -> 0.57242786 | U12: =IF(T12<EXP(-S12),0,IF(T12<EXP(-S12)*(1+S12),1,IF(T12<EXP(-S12)*(1+S12+S12^2/2),2,IF(T12<EXP(-S12)*(1+S12+S12^2/2+S12^3/6),3,4)))) -> 0 | V12: =U12*R12 -> 0 | W12: =Inputs!B15+(Inputs!D15-Inputs!B15)*BETAINV(RAND(),Model!H9,Model!I9) -> 0.94597771 | X12: =Inputs!E15+(Inputs!G15-Inputs!E15)*BETAINV(RAND(),Model!J9,Model!K9) -> 0.45775815 | Y12: =(Inputs!H15+(Inputs!J15-Inputs!H15)*BETAINV(RAND(),Model!L9,Model!M9))*Inputs!$C$6 -> 36525.799 | Z12: =W12*X12 -> 0.43302901 | AA12: =RAND() -> 0.86745177 | AB12: =IF(AA12<EXP(-Z12),0,IF(AA12<EXP(-Z12)*(1+Z12),1,IF(AA12<EXP(-Z12)*(1+Z12+Z12^2/2),2,IF(AA12<EXP(-Z12)*(1+Z12+Z12^2/2+Z12^3/6),3,4)))) -> 1 | AC12: =AB12*Y12 -> 36525.799 | AD12: =Inputs!B16+(Inputs!D16-Inputs!B16)*BETAINV(RAND(),Model!H10,Model!I10) -> 0.64015975 | AE12: =Inputs!E16+(Inputs!G16-Inputs!E16)*BETAINV(RAND(),Model!J10,Model!K10) -> 0.71937545 | AF12: =(Inputs!H16+(Inputs!J16-Inputs!H16)*BETAINV(RAND(),Model!L10,Model!M10))*Inputs!$C$6 -> 54267.671 | AG12: =AD12*AE12 -> 0.4605152 | AH12: =RAND() -> 0.58134215 | AI12: =IF(AH12<EXP(-AG12),0,IF(AH12<EXP(-AG12)*(1+AG12),1,IF(AH12<EXP(-AG12)*(1+AG12+AG12^2/2),2,IF(AH12<EXP(-AG12)*(1+AG12+AG12^2/2+AG12^3/6),3,4)))) -> 0 | AJ12: =AI12*AF12 -> 0 | AK12: =H12+O12+V12+AC12+AJ12 -> 77885.701
B13: =Inputs!B12+(Inputs!D12-Inputs!B12)*BETAINV(RAND(),Model!H6,Model!I6) -> 5.4429746 | C13: =Inputs!E12+(Inputs!G12-Inputs!E12)*BETAINV(RAND(),Model!J6,Model!K6) -> 0.29735871 | D13: =(Inputs!H12+(Inputs!J12-Inputs!H12)*BETAINV(RAND(),Model!L6,Model!M6))*Inputs!$C$6 -> 16457.73 | E13: =B13*C13 -> 1.6185159 | F13: =RAND() -> 0.25949383 | G13: =IF(F13<EXP(-E13),0,IF(F13<EXP(-E13)*(1+E13),1,IF(F13<EXP(-E13)*(1+E13+E13^2/2),2,IF(F13<EXP(-E13)*(1+E13+E13^2/2+E13^3/6),3,4)))) -> 1 | H13: =G13*D13 -> 16457.73 | I13: =Inputs!B13+(Inputs!D13-Inputs!B13)*BETAINV(RAND(),Model!H7,Model!I7) -> 4.0373127 | J13: =Inputs!E13+(Inputs!G13-Inputs!E13)*BETAINV(RAND(),Model!J7,Model!K7) -> 0.11849302 | K13: =(Inputs!H13+(Inputs!J13-Inputs!H13)*BETAINV(RAND(),Model!L7,Model!M7))*Inputs!$C$6 -> 53135.487 | L13: =I13*J13 -> 0.47839337 | M13: =RAND() -> 0.68089845 | N13: =IF(M13<EXP(-L13),0,IF(M13<EXP(-L13)*(1+L13),1,IF(M13<EXP(-L13)*(1+L13+L13^2/2),2,IF(M13<EXP(-L13)*(1+L13+L13^2/2+L13^3/6),3,4)))) -> 1 | O13: =N13*K13 -> 53135.487 | P13: =Inputs!B14+(Inputs!D14-Inputs!B14)*BETAINV(RAND(),Model!H8,Model!I8) -> 0.14119605 | Q13: =Inputs!E14+(Inputs!G14-Inputs!E14)*BETAINV(RAND(),Model!J8,Model!K8) -> 0.50185527 | R13: =(Inputs!H14+(Inputs!J14-Inputs!H14)*BETAINV(RAND(),Model!L8,Model!M8))*Inputs!$C$6 -> 402787.1 | S13: =P13*Q13 -> 0.07085998 | T13: =RAND() -> 0.61598315 | U13: =IF(T13<EXP(-S13),0,IF(T13<EXP(-S13)*(1+S13),1,IF(T13<EXP(-S13)*(1+S13+S13^2/2),2,IF(T13<EXP(-S13)*(1+S13+S13^2/2+S13^3/6),3,4)))) -> 0 | V13: =U13*R13 -> 0 | W13: =Inputs!B15+(Inputs!D15-Inputs!B15)*BETAINV(RAND(),Model!H9,Model!I9) -> 1.7765996 | X13: =Inputs!E15+(Inputs!G15-Inputs!E15)*BETAINV(RAND(),Model!J9,Model!K9) -> 0.39590983 | Y13: =(Inputs!H15+(Inputs!J15-Inputs!H15)*BETAINV(RAND(),Model!L9,Model!M9))*Inputs!$C$6 -> 15957.161 | Z13: =W13*X13 -> 0.70337325 | AA13: =RAND() -> 0.1285682 | AB13: =IF(AA13<EXP(-Z13),0,IF(AA13<EXP(-Z13)*(1+Z13),1,IF(AA13<EXP(-Z13)*(1+Z13+Z13^2/2),2,IF(AA13<EXP(-Z13)*(1+Z13+Z13^2/2+Z13^3/6),3,4)))) -> 0 | AC13: =AB13*Y13 -> 0 | AD13: =Inputs!B16+(Inputs!D16-Inputs!B16)*BETAINV(RAND(),Model!H10,Model!I10) -> 0.93868527 | AE13: =Inputs!E16+(Inputs!G16-Inputs!E16)*BETAINV(RAND(),Model!J10,Model!K10) -> 0.72143336 | AF13: =(Inputs!H16+(Inputs!J16-Inputs!H16)*BETAINV(RAND(),Model!L10,Model!M10))*Inputs!$C$6 -> 50063.419 | AG13: =AD13*AE13 -> 0.67719886 | AH13: =RAND() -> 0.61853357 | AI13: =IF(AH13<EXP(-AG13),0,IF(AH13<EXP(-AG13)*(1+AG13),1,IF(AH13<EXP(-AG13)*(1+AG13+AG13^2/2),2,IF(AH13<EXP(-AG13)*(1+AG13+AG13^2/2+AG13^3/6),3,4)))) -> 1 | AJ13: =AI13*AF13 -> 50063.419 | AK13: =H13+O13+V13+AC13+AJ13 -> 119656.64
B14: =Inputs!B12+(Inputs!D12-Inputs!B12)*BETAINV(RAND(),Model!H6,Model!I6) -> 2.8991463 | C14: =Inputs!E12+(Inputs!G12-Inputs!E12)*BETAINV(RAND(),Model!J6,Model!K6) -> 0.41195147 | D14: =(Inputs!H12+(Inputs!J12-Inputs!H12)*BETAINV(RAND(),Model!L6,Model!M6))*Inputs!$C$6 -> 42590.997 | E14: =B14*C14 -> 1.1943076 | F14: =RAND() -> 0.33104784 | G14: =IF(F14<EXP(-E14),0,IF(F14<EXP(-E14)*(1+E14),1,IF(F14<EXP(-E14)*(1+E14+E14^2/2),2,IF(F14<EXP(-E14)*(1+E14+E14^2/2+E14^3/6),3,4)))) -> 1 | H14: =G14*D14 -> 42590.997 | I14: =Inputs!B13+(Inputs!D13-Inputs!B13)*BETAINV(RAND(),Model!H7,Model!I7) -> 1.0032515 | J14: =Inputs!E13+(Inputs!G13-Inputs!E13)*BETAINV(RAND(),Model!J7,Model!K7) -> 0.29159952 | K14: =(Inputs!H13+(Inputs!J13-Inputs!H13)*BETAINV(RAND(),Model!L7,Model!M7))*Inputs!$C$6 -> 19381.31 | L14: =I14*J14 -> 0.29254765 | M14: =RAND() -> 0.24340115 | N14: =IF(M14<EXP(-L14),0,IF(M14<EXP(-L14)*(1+L14),1,IF(M14<EXP(-L14)*(1+L14+L14^2/2),2,IF(M14<EXP(-L14)*(1+L14+L14^2/2+L14^3/6),3,4)))) -> 0 | O14: =N14*K14 -> 0 | P14: =Inputs!B14+(Inputs!D14-Inputs!B14)*BETAINV(RAND(),Model!H8,Model!I8) -> 0.32022509 | Q14: =Inputs!E14+(Inputs!G14-Inputs!E14)*BETAINV(RAND(),Model!J8,Model!K8) -> 0.70678778 | R14: =(Inputs!H14+(Inputs!J14-Inputs!H14)*BETAINV(RAND(),Model!L8,Model!M8))*Inputs!$C$6 -> 449728.62 | S14: =P14*Q14 -> 0.22633118 | T14: =RAND() -> 0.37312027 | U14: =IF(T14<EXP(-S14),0,IF(T14<EXP(-S14)*(1+S14),1,IF(T14<EXP(-S14)*(1+S14+S14^2/2),2,IF(T14<EXP(-S14)*(1+S14+S14^2/2+S14^3/6),3,4)))) -> 0 | V14: =U14*R14 -> 0 | W14: =Inputs!B15+(Inputs!D15-Inputs!B15)*BETAINV(RAND(),Model!H9,Model!I9) -> 0.81317782 | X14: =Inputs!E15+(Inputs!G15-Inputs!E15)*BETAINV(RAND(),Model!J9,Model!K9) -> 0.46827302 | Y14: =(Inputs!H15+(Inputs!J15-Inputs!H15)*BETAINV(RAND(),Model!L9,Model!M9))*Inputs!$C$6 -> 20800.509 | Z14: =W14*X14 -> 0.38078923 | AA14: =RAND() -> 0.4811397 | AB14: =IF(AA14<EXP(-Z14),0,IF(AA14<EXP(-Z14)*(1+Z14),1,IF(AA14<EXP(-Z14)*(1+Z14+Z14^2/2),2,IF(AA14<EXP(-Z14)*(1+Z14+Z14^2/2+Z14^3/6),3,4)))) -> 0 | AC14: =AB14*Y14 -> 0 | AD14: =Inputs!B16+(Inputs!D16-Inputs!B16)*BETAINV(RAND(),Model!H10,Model!I10) -> 0.59719583 | AE14: =Inputs!E16+(Inputs!G16-Inputs!E16)*BETAINV(RAND(),Model!J10,Model!K10) -> 0.62925625 | AF14: =(Inputs!H16+(Inputs!J16-Inputs!H16)*BETAINV(RAND(),Model!L10,Model!M10))*Inputs!$C$6 -> 59409.463 | AG14: =AD14*AE14 -> 0.37578921 | AH14: =RAND() -> 0.64361128 | AI14: =IF(AH14<EXP(-AG14),0,IF(AH14<EXP(-AG14)*(1+AG14),1,IF(AH14<EXP(-AG14)*(1+AG14+AG14^2/2),2,IF(AH14<EXP(-AG14)*(1+AG14+AG14^2/2+AG14^3/6),3,4)))) -> 0 | AJ14: =AI14*AF14 -> 0 | AK14: =H14+O14+V14+AC14+AJ14 -> 42590.997
B15: =Inputs!B12+(Inputs!D12-Inputs!B12)*BETAINV(RAND(),Model!H6,Model!I6) -> 3.1062039 | C15: =Inputs!E12+(Inputs!G12-Inputs!E12)*BETAINV(RAND(),Model!J6,Model!K6) -> 0.2325814 | D15: =(Inputs!H12+(Inputs!J12-Inputs!H12)*BETAINV(RAND(),Model!L6,Model!M6))*Inputs!$C$6 -> 41334.516 | E15: =B15*C15 -> 0.72244526 | F15: =RAND() -> 0.17740048 | G15: =IF(F15<EXP(-E15),0,IF(F15<EXP(-E15)*(1+E15),1,IF(F15<EXP(-E15)*(1+E15+E15^2/2),2,IF(F15<EXP(-E15)*(1+E15+E15^2/2+E15^3/6),3,4)))) -> 0 | H15: =G15*D15 -> 0 | I15: =Inputs!B13+(Inputs!D13-Inputs!B13)*BETAINV(RAND(),Model!H7,Model!I7) -> 1.3763275 | J15: =Inputs!E13+(Inputs!G13-Inputs!E13)*BETAINV(RAND(),Model!J7,Model!K7) -> 0.2621962 | K15: =(Inputs!H13+(Inputs!J13-Inputs!H13)*BETAINV(RAND(),Model!L7,Model!M7))*Inputs!$C$6 -> 32745.011 | L15: =I15*J15 -> 0.36086783 | M15: =RAND() -> 0.77824605 | N15: =IF(M15<EXP(-L15),0,IF(M15<EXP(-L15)*(1+L15),1,IF(M15<EXP(-L15)*(1+L15+L15^2/2),2,IF(M15<EXP(-L15)*(1+L15+L15^2/2+L15^3/6),3,4)))) -> 1 | O15: =N15*K15 -> 32745.011 | P15: =Inputs!B14+(Inputs!D14-Inputs!B14)*BETAINV(RAND(),Model!H8,Model!I8) -> 0.29640393 | Q15: =Inputs!E14+(Inputs!G14-Inputs!E14)*BETAINV(RAND(),Model!J8,Model!K8) -> 0.63665011 | R15: =(Inputs!H14+(Inputs!J14-Inputs!H14)*BETAINV(RAND(),Model!L8,Model!M8))*Inputs!$C$6 -> 347386.17 | S15: =P15*Q15 -> 0.1887056 | T15: =RAND() -> 0.76026681 | U15: =IF(T15<EXP(-S15),0,IF(T15<EXP(-S15)*(1+S15),1,IF(T15<EXP(-S15)*(1+S15+S15^2/2),2,IF(T15<EXP(-S15)*(1+S15+S15^2/2+S15^3/6),3,4)))) -> 0 | V15: =U15*R15 -> 0 | W15: =Inputs!B15+(Inputs!D15-Inputs!B15)*BETAINV(RAND(),Model!H9,Model!I9) -> 1.176182 | X15: =Inputs!E15+(Inputs!G15-Inputs!E15)*BETAINV(RAND(),Model!J9,Model!K9) -> 0.41457 | Y15: =(Inputs!H15+(Inputs!J15-Inputs!H15)*BETAINV(RAND(),Model!L9,Model!M9))*Inputs!$C$6 -> 8903.9126 | Z15: =W15*X15 -> 0.48760976 | AA15: =RAND() -> 0.90978053 | AB15: =IF(AA15<EXP(-Z15),0,IF(AA15<EXP(-Z15)*(1+Z15),1,IF(AA15<EXP(-Z15)*(1+Z15+Z15^2/2),2,IF(AA15<EXP(-Z15)*(1+Z15+Z15^2/2+Z15^3/6),3,4)))) -> 1 | AC15: =AB15*Y15 -> 8903.9126 | AD15: =Inputs!B16+(Inputs!D16-Inputs!B16)*BETAINV(RAND(),Model!H10,Model!I10) -> 0.80086208 | AE15: =Inputs!E16+(Inputs!G16-Inputs!E16)*BETAINV(RAND(),Model!J10,Model!K10) -> 0.61256528 | AF15: =(Inputs!H16+(Inputs!J16-Inputs!H16)*BETAINV(RAND(),Model!L10,Model!M10))*Inputs!$C$6 -> 135329.18 | AG15: =AD15*AE15 -> 0.4905803 | AH15: =RAND() -> 0.78986386 | AI15: =IF(AH15<EXP(-AG15),0,IF(AH15<EXP(-AG15)*(1+AG15),1,IF(AH15<EXP(-AG15)*(1+AG15+AG15^2/2),2,IF(AH15<EXP(-AG15)*(1+AG15+AG15^2/2+AG15^3/6),3,4)))) -> 1 | AJ15: =AI15*AF15 -> 135329.18 | AK15: =H15+O15+V15+AC15+AJ15 -> 176978.1
B16: =Inputs!B12+(Inputs!D12-Inputs!B12)*BETAINV(RAND(),Model!H6,Model!I6) -> 5.9129646 | C16: =Inputs!E12+(Inputs!G12-Inputs!E12)*BETAINV(RAND(),Model!J6,Model!K6) -> 0.4025378 | D16: =(Inputs!H12+(Inputs!J12-Inputs!H12)*BETAINV(RAND(),Model!L6,Model!M6))*Inputs!$C$6 -> 39701.745 | E16: =B16*C16 -> 2.3801918 | F16: =RAND() -> 0.70868742 | G16: =IF(F16<EXP(-E16),0,IF(F16<EXP(-E16)*(1+E16),1,IF(F16<EXP(-E16)*(1+E16+E16^2/2),2,IF(F16<EXP(-E16)*(1+E16+E16^2/2+E16^3/6),3,4)))) -> 3 | H16: =G16*D16 -> 119105.23 | I16: =Inputs!B13+(Inputs!D13-Inputs!B13)*BETAINV(RAND(),Model!H7,Model!I7) -> 2.7671966 | J16: =Inputs!E13+(Inputs!G13-Inputs!E13)*BETAINV(RAND(),Model!J7,Model!K7) -> 0.30764682 | K16: =(Inputs!H13+(Inputs!J13-Inputs!H13)*BETAINV(RAND(),Model!L7,Model!M7))*Inputs!$C$6 -> 21385 | L16: =I16*J16 -> 0.85131923 | M16: =RAND() -> 0.60139844 | N16: =IF(M16<EXP(-L16),0,IF(M16<EXP(-L16)*(1+L16),1,IF(M16<EXP(-L16)*(1+L16+L16^2/2),2,IF(M16<EXP(-L16)*(1+L16+L16^2/2+L16^3/6),3,4)))) -> 1 | O16: =N16*K16 -> 21385 | P16: =Inputs!B14+(Inputs!D14-Inputs!B14)*BETAINV(RAND(),Model!H8,Model!I8) -> 0.20545386 | Q16: =Inputs!E14+(Inputs!G14-Inputs!E14)*BETAINV(RAND(),Model!J8,Model!K8) -> 0.68454722 | R16: =(Inputs!H14+(Inputs!J14-Inputs!H14)*BETAINV(RAND(),Model!L8,Model!M8))*Inputs!$C$6 -> 218634.55 | S16: =P16*Q16 -> 0.14064287 | T16: =RAND() -> 0.9570384 | U16: =IF(T16<EXP(-S16),0,IF(T16<EXP(-S16)*(1+S16),1,IF(T16<EXP(-S16)*(1+S16+S16^2/2),2,IF(T16<EXP(-S16)*(1+S16+S16^2/2+S16^3/6),3,4)))) -> 1 | V16: =U16*R16 -> 218634.55 | W16: =Inputs!B15+(Inputs!D15-Inputs!B15)*BETAINV(RAND(),Model!H9,Model!I9) -> 0.60560441 | X16: =Inputs!E15+(Inputs!G15-Inputs!E15)*BETAINV(RAND(),Model!J9,Model!K9) -> 0.55196421 | Y16: =(Inputs!H15+(Inputs!J15-Inputs!H15)*BETAINV(RAND(),Model!L9,Model!M9))*Inputs!$C$6 -> 44288.16 | Z16: =W16*X16 -> 0.33427196 | AA16: =RAND() -> 0.53184467 | AB16: =IF(AA16<EXP(-Z16),0,IF(AA16<EXP(-Z16)*(1+Z16),1,IF(AA16<EXP(-Z16)*(1+Z16+Z16^2/2),2,IF(AA16<EXP(-Z16)*(1+Z16+Z16^2/2+Z16^3/6),3,4)))) -> 0 | AC16: =AB16*Y16 -> 0 | AD16: =Inputs!B16+(Inputs!D16-Inputs!B16)*BETAINV(RAND(),Model!H10,Model!I10) -> 0.45475867 | AE16: =Inputs!E16+(Inputs!G16-Inputs!E16)*BETAINV(RAND(),Model!J10,Model!K10) -> 0.67974321 | AF16: =(Inputs!H16+(Inputs!J16-Inputs!H16)*BETAINV(RAND(),Model!L10,Model!M10))*Inputs!$C$6 -> 49901.083 | AG16: =AD16*AE16 -> 0.30911912 | AH16: =RAND() -> 0.89003832 | AI16: =IF(AH16<EXP(-AG16),0,IF(AH16<EXP(-AG16)*(1+AG16),1,IF(AH16<EXP(-AG16)*(1+AG16+AG16^2/2),2,IF(AH16<EXP(-AG16)*(1+AG16+AG16^2/2+AG16^3/6),3,4)))) -> 1 | AJ16: =AI16*AF16 -> 49901.083 | AK16: =H16+O16+V16+AC16+AJ16 -> 409025.87
B17: =Inputs!B12+(Inputs!D12-Inputs!B12)*BETAINV(RAND(),Model!H6,Model!I6) -> 3.1553492 | C17: =Inputs!E12+(Inputs!G12-Inputs!E12)*BETAINV(RAND(),Model!J6,Model!K6) -> 0.39684416 | D17: =(Inputs!H12+(Inputs!J12-Inputs!H12)*BETAINV(RAND(),Model!L6,Model!M6))*Inputs!$C$6 -> 17691.137 | E17: =B17*C17 -> 1.2521819 | F17: =RAND() -> 0.10368429 | G17: =IF(F17<EXP(-E17),0,IF(F17<EXP(-E17)*(1+E17),1,IF(F17<EXP(-E17)*(1+E17+E17^2/2),2,IF(F17<EXP(-E17)*(1+E17+E17^2/2+E17^3/6),3,4)))) -> 0 | H17: =G17*D17 -> 0 | I17: =Inputs!B13+(Inputs!D13-Inputs!B13)*BETAINV(RAND(),Model!H7,Model!I7) -> 3.389889 | J17: =Inputs!E13+(Inputs!G13-Inputs!E13)*BETAINV(RAND(),Model!J7,Model!K7) -> 0.23746264 | K17: =(Inputs!H13+(Inputs!J13-Inputs!H13)*BETAINV(RAND(),Model!L7,Model!M7))*Inputs!$C$6 -> 23019.067 | L17: =I17*J17 -> 0.80497199 | M17: =RAND() -> 0.69091639 | N17: =IF(M17<EXP(-L17),0,IF(M17<EXP(-L17)*(1+L17),1,IF(M17<EXP(-L17)*(1+L17+L17^2/2),2,IF(M17<EXP(-L17)*(1+L17+L17^2/2+L17^3/6),3,4)))) -> 1 | O17: =N17*K17 -> 23019.067 | P17: =Inputs!B14+(Inputs!D14-Inputs!B14)*BETAINV(RAND(),Model!H8,Model!I8) -> 0.10720353 | Q17: =Inputs!E14+(Inputs!G14-Inputs!E14)*BETAINV(RAND(),Model!J8,Model!K8) -> 0.38870894 | R17: =(Inputs!H14+(Inputs!J14-Inputs!H14)*BETAINV(RAND(),Model!L8,Model!M8))*Inputs!$C$6 -> 400601.45 | S17: =P17*Q17 -> 0.041670972 | T17: =RAND() -> 0.86820865 | U17: =IF(T17<EXP(-S17),0,IF(T17<EXP(-S17)*(1+S17),1,IF(T17<EXP(-S17)*(1+S17+S17^2/2),2,IF(T17<EXP(-S17)*(1+S17+S17^2/2+S17^3/6),3,4)))) -> 0 | V17: =U17*R17 -> 0 | W17: =Inputs!B15+(Inputs!D15-Inputs!B15)*BETAINV(RAND(),Model!H9,Model!I9) -> 0.67078613 | X17: =Inputs!E15+(Inputs!G15-Inputs!E15)*BETAINV(RAND(),Model!J9,Model!K9) -> 0.34618287 | Y17: =(Inputs!H15+(Inputs!J15-Inputs!H15)*BETAINV(RAND(),Model!L9,Model!M9))*Inputs!$C$6 -> 43094.271 | Z17: =W17*X17 -> 0.23221467 | AA17: =RAND() -> 0.71802798 | AB17: =IF(AA17<EXP(-Z17),0,IF(AA17<EXP(-Z17)*(1+Z17),1,IF(AA17<EXP(-Z17)*(1+Z17+Z17^2/2),2,IF(AA17<EXP(-Z17)*(1+Z17+Z17^2/2+Z17^3/6),3,4)))) -> 0 | AC17: =AB17*Y17 -> 0 | AD17: =Inputs!B16+(Inputs!D16-Inputs!B16)*BETAINV(RAND(),Model!H10,Model!I10) -> 0.36642392 | AE17: =Inputs!E16+(Inputs!G16-Inputs!E16)*BETAINV(RAND(),Model!J10,Model!K10) -> 0.65114406 | AF17: =(Inputs!H16+(Inputs!J16-Inputs!H16)*BETAINV(RAND(),Model!L10,Model!M10))*Inputs!$C$6 -> 89205.405 | AG17: =AD17*AE17 -> 0.23859476 | AH17: =RAND() -> 0.15812745 | AI17: =IF(AH17<EXP(-AG17),0,IF(AH17<EXP(-AG17)*(1+AG17),1,IF(AH17<EXP(-AG17)*(1+AG17+AG17^2/2),2,IF(AH17<EXP(-AG17)*(1+AG17+AG17^2/2+AG17^3/6),3,4)))) -> 0 | AJ17: =AI17*AF17 -> 0 | AK17: =H17+O17+V17+AC17+AJ17 -> 23019.067
B18: =Inputs!B12+(Inputs!D12-Inputs!B12)*BETAINV(RAND(),Model!H6,Model!I6) -> 3.4842229 | C18: =Inputs!E12+(Inputs!G12-Inputs!E12)*BETAINV(RAND(),Model!J6,Model!K6) -> 0.39478271 | D18: =(Inputs!H12+(Inputs!J12-Inputs!H12)*BETAINV(RAND(),Model!L6,Model!M6))*Inputs!$C$6 -> 25136.965 | E18: =B18*C18 -> 1.375511 | F18: =RAND() -> 0.2660267 | G18: =IF(F18<EXP(-E18),0,IF(F18<EXP(-E18)*(1+E18),1,IF(F18<EXP(-E18)*(1+E18+E18^2/2),2,IF(F18<EXP(-E18)*(1+E18+E18^2/2+E18^3/6),3,4)))) -> 1 | H18: =G18*D18 -> 25136.965 | I18: =Inputs!B13+(Inputs!D13-Inputs!B13)*BETAINV(RAND(),Model!H7,Model!I7) -> 3.3925084 | J18: =Inputs!E13+(Inputs!G13-Inputs!E13)*BETAINV(RAND(),Model!J7,Model!K7) -> 0.28075184 | K18: =(Inputs!H13+(Inputs!J13-Inputs!H13)*BETAINV(RAND(),Model!L7,Model!M7))*Inputs!$C$6 -> 34995.011 | L18: =I18*J18 -> 0.95245297 | M18: =RAND() -> 0.5027459 | N18: =IF(M18<EXP(-L18),0,IF(M18<EXP(-L18)*(1+L18),1,IF(M18<EXP(-L18)*(1+L18+L18^2/2),2,IF(M18<EXP(-L18)*(1+L18+L18^2/2+L18^3/6),3,4)))) -> 1 | O18: =N18*K18 -> 34995.011 | P18: =Inputs!B14+(Inputs!D14-Inputs!B14)*BETAINV(RAND(),Model!H8,Model!I8) -> 0.5468183 | Q18: =Inputs!E14+(Inputs!G14-Inputs!E14)*BETAINV(RAND(),Model!J8,Model!K8) -> 0.64008899 | R18: =(Inputs!H14+(Inputs!J14-Inputs!H14)*BETAINV(RAND(),Model!L8,Model!M8))*Inputs!$C$6 -> 417999.12 | S18: =P18*Q18 -> 0.35001238 | T18: =RAND() -> 0.30975258 | U18: =IF(T18<EXP(-S18),0,IF(T18<EXP(-S18)*(1+S18),1,IF(T18<EXP(-S18)*(1+S18+S18^2/2),2,IF(T18<EXP(-S18)*(1+S18+S18^2/2+S18^3/6),3,4)))) -> 0 | V18: =U18*R18 -> 0 | W18: =Inputs!B15+(Inputs!D15-Inputs!B15)*BETAINV(RAND(),Model!H9,Model!I9) -> 1.0984893 | X18: =Inputs!E15+(Inputs!G15-Inputs!E15)*BETAINV(RAND(),Model!J9,Model!K9) -> 0.42697035 | Y18: =(Inputs!H15+(Inputs!J15-Inputs!H15)*BETAINV(RAND(),Model!L9,Model!M9))*Inputs!$C$6 -> 24932.013 | Z18: =W18*X18 -> 0.46902236 | AA18: =RAND() -> 0.49412264 | AB18: =IF(AA18<EXP(-Z18),0,IF(AA18<EXP(-Z18)*(1+Z18),1,IF(AA18<EXP(-Z18)*(1+Z18+Z18^2/2),2,IF(AA18<EXP(-Z18)*(1+Z18+Z18^2/2+Z18^3/6),3,4)))) -> 0 | AC18: =AB18*Y18 -> 0 | AD18: =Inputs!B16+(Inputs!D16-Inputs!B16)*BETAINV(RAND(),Model!H10,Model!I10) -> 0.47049608 | AE18: =Inputs!E16+(Inputs!G16-Inputs!E16)*BETAINV(RAND(),Model!J10,Model!K10) -> 0.59865082 | AF18: =(Inputs!H16+(Inputs!J16-Inputs!H16)*BETAINV(RAND(),Model!L10,Model!M10))*Inputs!$C$6 -> 153198.2 | AG18: =AD18*AE18 -> 0.28166287 | AH18: =RAND() -> 0.30628843 | AI18: =IF(AH18<EXP(-AG18),0,IF(AH18<EXP(-AG18)*(1+AG18),1,IF(AH18<EXP(-AG18)*(1+AG18+AG18^2/2),2,IF(AH18<EXP(-AG18)*(1+AG18+AG18^2/2+AG18^3/6),3,4)))) -> 0 | AJ18: =AI18*AF18 -> 0 | AK18: =H18+O18+V18+AC18+AJ18 -> 60131.977
B19: =Inputs!B12+(Inputs!D12-Inputs!B12)*BETAINV(RAND(),Model!H6,Model!I6) -> 2.8640426 | C19: =Inputs!E12+(Inputs!G12-Inputs!E12)*BETAINV(RAND(),Model!J6,Model!K6) -> 0.24602936 | D19: =(Inputs!H12+(Inputs!J12-Inputs!H12)*BETAINV(RAND(),Model!L6,Model!M6))*Inputs!$C$6 -> 27677.501 | E19: =B19*C19 -> 0.70463858 | F19: =RAND() -> 0.54010905 | G19: =IF(F19<EXP(-E19),0,IF(F19<EXP(-E19)*(1+E19),1,IF(F19<EXP(-E19)*(1+E19+E19^2/2),2,IF(F19<EXP(-E19)*(1+E19+E19^2/2+E19^3/6),3,4)))) -> 1 | H19: =G19*D19 -> 27677.501 | I19: =Inputs!B13+(Inputs!D13-Inputs!B13)*BETAINV(RAND(),Model!H7,Model!I7) -> 2.9176737 | J19: =Inputs!E13+(Inputs!G13-Inputs!E13)*BETAINV(RAND(),Model!J7,Model!K7) -> 0.27069899 | K19: =(Inputs!H13+(Inputs!J13-Inputs!H13)*BETAINV(RAND(),Model!L7,Model!M7))*Inputs!$C$6 -> 45870.341 | L19: =I19*J19 -> 0.78981131 | M19: =RAND() -> 0.59045157 | N19: =IF(M19<EXP(-L19),0,IF(M19<EXP(-L19)*(1+L19),1,IF(M19<EXP(-L19)*(1+L19+L19^2/2),2,IF(M19<EXP(-L19)*(1+L19+L19^2/2+L19^3/6),3,4)))) -> 1 | O19: =N19*K19 -> 45870.341 | P19: =Inputs!B14+(Inputs!D14-Inputs!B14)*BETAINV(RAND(),Model!H8,Model!I8) -> 0.42335802 | Q19: =Inputs!E14+(Inputs!G14-Inputs!E14)*BETAINV(RAND(),Model!J8,Model!K8) -> 0.76955233 | R19: =(Inputs!H14+(Inputs!J14-Inputs!H14)*BETAINV(RAND(),Model!L8,Model!M8))*Inputs!$C$6 -> 358899.1 | S19: =P19*Q19 -> 0.32579615 | T19: =RAND() -> 0.18440905 | U19: =IF(T19<EXP(-S19),0,IF(T19<EXP(-S19)*(1+S19),1,IF(T19<EXP(-S19)*(1+S19+S19^2/2),2,IF(T19<EXP(-S19)*(1+S19+S19^2/2+S19^3/6),3,4)))) -> 0 | V19: =U19*R19 -> 0 | W19: =Inputs!B15+(Inputs!D15-Inputs!B15)*BETAINV(RAND(),Model!H9,Model!I9) -> 1.2530663 | X19: =Inputs!E15+(Inputs!G15-Inputs!E15)*BETAINV(RAND(),Model!J9,Model!K9) -> 0.40297761 | Y19: =(Inputs!H15+(Inputs!J15-Inputs!H15)*BETAINV(RAND(),Model!L9,Model!M9))*Inputs!$C$6 -> 24613.818 | Z19: =W19*X19 -> 0.50495767 | AA19: =RAND() -> 0.38160911 | AB19: =IF(AA19<EXP(-Z19),0,IF(AA19<EXP(-Z19)*(1+Z19),1,IF(AA19<EXP(-Z19)*(1+Z19+Z19^2/2),2,IF(AA19<EXP(-Z19)*(1+Z19+Z19^2/2+Z19^3/6),3,4)))) -> 0 | AC19: =AB19*Y19 -> 0 | AD19: =Inputs!B16+(Inputs!D16-Inputs!B16)*BETAINV(RAND(),Model!H10,Model!I10) -> 0.54438929 | AE19: =Inputs!E16+(Inputs!G16-Inputs!E16)*BETAINV(RAND(),Model!J10,Model!K10) -> 0.64681665 | AF19: =(Inputs!H16+(Inputs!J16-Inputs!H16)*BETAINV(RAND(),Model!L10,Model!M10))*Inputs!$C$6 -> 110267.93 | AG19: =AD19*AE19 -> 0.35212006 | AH19: =RAND() -> 0.67628015 | AI19: =IF(AH19<EXP(-AG19),0,IF(AH19<EXP(-AG19)*(1+AG19),1,IF(AH19<EXP(-AG19)*(1+AG19+AG19^2/2),2,IF(AH19<EXP(-AG19)*(1+AG19+AG19^2/2+AG19^3/6),3,4)))) -> 0 | AJ19: =AI19*AF19 -> 0 | AK19: =H19+O19+V19+AC19+AJ19 -> 73547.841
B20: =Inputs!B12+(Inputs!D12-Inputs!B12)*BETAINV(RAND(),Model!H6,Model!I6) -> 2.3587697 | C20: =Inputs!E12+(Inputs!G12-Inputs!E12)*BETAINV(RAND(),Model!J6,Model!K6) -> 0.23373169 | D20: =(Inputs!H12+(Inputs!J12-Inputs!H12)*BETAINV(RAND(),Model!L6,Model!M6))*Inputs!$C$6 -> 13966.411 | E20: =B20*C20 -> 0.55131925 | F20: =RAND() -> 0.97033965 | G20: =IF(F20<EXP(-E20),0,IF(F20<EXP(-E20)*(1+E20),1,IF(F20<EXP(-E20)*(1+E20+E20^2/2),2,IF(F20<EXP(-E20)*(1+E20+E20^2/2+E20^3/6),3,4)))) -> 2 | H20: =G20*D20 -> 27932.822 | I20: =Inputs!B13+(Inputs!D13-Inputs!B13)*BETAINV(RAND(),Model!H7,Model!I7) -> 2.8069922 | J20: =Inputs!E13+(Inputs!G13-Inputs!E13)*BETAINV(RAND(),Model!J7,Model!K7) -> 0.29649235 | K20: =(Inputs!H13+(Inputs!J13-Inputs!H13)*BETAINV(RAND(),Model!L7,Model!M7))*Inputs!$C$6 -> 28012.502 | L20: =I20*J20 -> 0.83225171 | M20: =RAND() -> 0.25864642 | N20: =IF(M20<EXP(-L20),0,IF(M20<EXP(-L20)*(1+L20),1,IF(M20<EXP(-L20)*(1+L20+L20^2/2),2,IF(M20<EXP(-L20)*(1+L20+L20^2/2+L20^3/6),3,4)))) -> 0 | O20: =N20*K20 -> 0 | P20: =Inputs!B14+(Inputs!D14-Inputs!B14)*BETAINV(RAND(),Model!H8,Model!I8) -> 0.34864255 | Q20: =Inputs!E14+(Inputs!G14-Inputs!E14)*BETAINV(RAND(),Model!J8,Model!K8) -> 0.56609475 | R20: =(Inputs!H14+(Inputs!J14-Inputs!H14)*BETAINV(RAND(),Model!L8,Model!M8))*Inputs!$C$6 -> 378010.42 | S20: =P20*Q20 -> 0.19736472 | T20: =RAND() -> 0.78487766 | U20: =IF(T20<EXP(-S20),0,IF(T20<EXP(-S20)*(1+S20),1,IF(T20<EXP(-S20)*(1+S20+S20^2/2),2,IF(T20<EXP(-S20)*(1+S20+S20^2/2+S20^3/6),3,4)))) -> 0 | V20: =U20*R20 -> 0 | W20: =Inputs!B15+(Inputs!D15-Inputs!B15)*BETAINV(RAND(),Model!H9,Model!I9) -> 1.3744486 | X20: =Inputs!E15+(Inputs!G15-Inputs!E15)*BETAINV(RAND(),Model!J9,Model!K9) -> 0.29964296 | Y20: =(Inputs!H15+(Inputs!J15-Inputs!H15)*BETAINV(RAND(),Model!L9,Model!M9))*Inputs!$C$6 -> 7934.702 | Z20: =W20*X20 -> 0.41184384 | AA20: =RAND() -> 0.372176 | AB20: =IF(AA20<EXP(-Z20),0,IF(AA20<EXP(-Z20)*(1+Z20),1,IF(AA20<EXP(-Z20)*(1+Z20+Z20^2/2),2,IF(AA20<EXP(-Z20)*(1+Z20+Z20^2/2+Z20^3/6),3,4)))) -> 0 | AC20: =AB20*Y20 -> 0 | AD20: =Inputs!B16+(Inputs!D16-Inputs!B16)*BETAINV(RAND(),Model!H10,Model!I10) -> 0.56272526 | AE20: =Inputs!E16+(Inputs!G16-Inputs!E16)*BETAINV(RAND(),Model!J10,Model!K10) -> 0.63322424 | AF20: =(Inputs!H16+(Inputs!J16-Inputs!H16)*BETAINV(RAND(),Model!L10,Model!M10))*Inputs!$C$6 -> 96935.119 | AG20: =AD20*AE20 -> 0.35633128 | AH20: =RAND() -> 0.38561731 | AI20: =IF(AH20<EXP(-AG20),0,IF(AH20<EXP(-AG20)*(1+AG20),1,IF(AH20<EXP(-AG20)*(1+AG20+AG20^2/2),2,IF(AH20<EXP(-AG20)*(1+AG20+AG20^2/2+AG20^3/6),3,4)))) -> 0 | AJ20: =AI20*AF20 -> 0 | AK20: =H20+O20+V20+AC20+AJ20 -> 27932.822
B21: =Inputs!B12+(Inputs!D12-Inputs!B12)*BETAINV(RAND(),Model!H6,Model!I6) -> 5.0512907 | C21: =Inputs!E12+(Inputs!G12-Inputs!E12)*BETAINV(RAND(),Model!J6,Model!K6) -> 0.39977197 | D21: =(Inputs!H12+(Inputs!J12-Inputs!H12)*BETAINV(RAND(),Model!L6,Model!M6))*Inputs!$C$6 -> 39215.857 | E21: =B21*C21 -> 2.0193645 | F21: =RAND() -> 0.7368181 | G21: =IF(F21<EXP(-E21),0,IF(F21<EXP(-E21)*(1+E21),1,IF(F21<EXP(-E21)*(1+E21+E21^2/2),2,IF(F21<EXP(-E21)*(1+E21+E21^2/2+E21^3/6),3,4)))) -> 3 | H21: =G21*D21 -> 117647.57 | I21: =Inputs!B13+(Inputs!D13-Inputs!B13)*BETAINV(RAND(),Model!H7,Model!I7) -> 1.1119548 | J21: =Inputs!E13+(Inputs!G13-Inputs!E13)*BETAINV(RAND(),Model!J7,Model!K7) -> 0.34349203 | K21: =(Inputs!H13+(Inputs!J13-Inputs!H13)*BETAINV(RAND(),Model!L7,Model!M7))*Inputs!$C$6 -> 45992.634 | L21: =I21*J21 -> 0.38194761 | M21: =RAND() -> 0.22827819 | N21: =IF(M21<EXP(-L21),0,IF(M21<EXP(-L21)*(1+L21),1,IF(M21<EXP(-L21)*(1+L21+L21^2/2),2,IF(M21<EXP(-L21)*(1+L21+L21^2/2+L21^3/6),3,4)))) -> 0 | O21: =N21*K21 -> 0 | P21: =Inputs!B14+(Inputs!D14-Inputs!B14)*BETAINV(RAND(),Model!H8,Model!I8) -> 0.14868196 | Q21: =Inputs!E14+(Inputs!G14-Inputs!E14)*BETAINV(RAND(),Model!J8,Model!K8) -> 0.60007131 | R21: =(Inputs!H14+(Inputs!J14-Inputs!H14)*BETAINV(RAND(),Model!L8,Model!M8))*Inputs!$C$6 -> 383614.81 | S21: =P21*Q21 -> 0.089219777 | T21: =RAND() -> 0.37974076 | U21: =IF(T21<EXP(-S21),0,IF(T21<EXP(-S21)*(1+S21),1,IF(T21<EXP(-S21)*(1+S21+S21^2/2),2,IF(T21<EXP(-S21)*(1+S21+S21^2/2+S21^3/6),3,4)))) -> 0 | V21: =U21*R21 -> 0 | W21: =Inputs!B15+(Inputs!D15-Inputs!B15)*BETAINV(RAND(),Model!H9,Model!I9) -> 0.86581828 | X21: =Inputs!E15+(Inputs!G15-Inputs!E15)*BETAINV(RAND(),Model!J9,Model!K9) -> 0.27436001 | Y21: =(Inputs!H15+(Inputs!J15-Inputs!H15)*BETAINV(RAND(),Model!L9,Model!M9))*Inputs!$C$6 -> 57697.424 | Z21: =W21*X21 -> 0.23754591 | AA21: =RAND() -> 0.70175482 | AB21: =IF(AA21<EXP(-Z21),0,IF(AA21<EXP(-Z21)*(1+Z21),1,IF(AA21<EXP(-Z21)*(1+Z21+Z21^2/2),2,IF(AA21<EXP(-Z21)*(1+Z21+Z21^2/2+Z21^3/6),3,4)))) -> 0 | AC21: =AB21*Y21 -> 0 | AD21: =Inputs!B16+(Inputs!D16-Inputs!B16)*BETAINV(RAND(),Model!H10,Model!I10) -> 0.67751859 | AE21: =Inputs!E16+(Inputs!G16-Inputs!E16)*BETAINV(RAND(),Model!J10,Model!K10) -> 0.50915121 | AF21: =(Inputs!H16+(Inputs!J16-Inputs!H16)*BETAINV(RAND(),Model!L10,Model!M10))*Inputs!$C$6 -> 121211.7 | AG21: =AD21*AE21 -> 0.34495941 | AH21: =RAND() -> 0.021768727 | AI21: =IF(AH21<EXP(-AG21),0,IF(AH21<EXP(-AG21)*(1+AG21),1,IF(AH21<EXP(-AG21)*(1+AG21+AG21^2/2),2,IF(AH21<EXP(-AG21)*(1+AG21+AG21^2/2+AG21^3/6),3,4)))) -> 0 | AJ21: =AI21*AF21 -> 0 | AK21: =H21+O21+V21+AC21+AJ21 -> 117647.57
B22: =Inputs!B12+(Inputs!D12-Inputs!B12)*BETAINV(RAND(),Model!H6,Model!I6) -> 1.8416677 | C22: =Inputs!E12+(Inputs!G12-Inputs!E12)*BETAINV(RAND(),Model!J6,Model!K6) -> 0.22221065 | D22: =(Inputs!H12+(Inputs!J12-Inputs!H12)*BETAINV(RAND(),Model!L6,Model!M6))*Inputs!$C$6 -> 43370.524 | E22: =B22*C22 -> 0.40923819 | F22: =RAND() -> 0.8671523 | G22: =IF(F22<EXP(-E22),0,IF(F22<EXP(-E22)*(1+E22),1,IF(F22<EXP(-E22)*(1+E22+E22^2/2),2,IF(F22<EXP(-E22)*(1+E22+E22^2/2+E22^3/6),3,4)))) -> 1 | H22: =G22*D22 -> 43370.524 | I22: =Inputs!B13+(Inputs!D13-Inputs!B13)*BETAINV(RAND(),Model!H7,Model!I7) -> 2.3492192 | J22: =Inputs!E13+(Inputs!G13-Inputs!E13)*BETAINV(RAND(),Model!J7,Model!K7) -> 0.21677072 | K22: =(Inputs!H13+(Inputs!J13-Inputs!H13)*BETAINV(RAND(),Model!L7,Model!M7))*Inputs!$C$6 -> 18922.497 | L22: =I22*J22 -> 0.50924195 | M22: =RAND() -> 0.57014561 | N22: =IF(M22<EXP(-L22),0,IF(M22<EXP(-L22)*(1+L22),1,IF(M22<EXP(-L22)*(1+L22+L22^2/2),2,IF(M22<EXP(-L22)*(1+L22+L22^2/2+L22^3/6),3,4)))) -> 0 | O22: =N22*K22 -> 0 | P22: =Inputs!B14+(Inputs!D14-Inputs!B14)*BETAINV(RAND(),Model!H8,Model!I8) -> 0.27912457 | Q22: =Inputs!E14+(Inputs!G14-Inputs!E14)*BETAINV(RAND(),Model!J8,Model!K8) -> 0.67655033 | R22: =(Inputs!H14+(Inputs!J14-Inputs!H14)*BETAINV(RAND(),Model!L8,Model!M8))*Inputs!$C$6 -> 270913.07 | S22: =P22*Q22 -> 0.18884182 | T22: =RAND() -> 0.83932724 | U22: =IF(T22<EXP(-S22),0,IF(T22<EXP(-S22)*(1+S22),1,IF(T22<EXP(-S22)*(1+S22+S22^2/2),2,IF(T22<EXP(-S22)*(1+S22+S22^2/2+S22^3/6),3,4)))) -> 1 | V22: =U22*R22 -> 270913.07 | W22: =Inputs!B15+(Inputs!D15-Inputs!B15)*BETAINV(RAND(),Model!H9,Model!I9) -> 1.5062166 | X22: =Inputs!E15+(Inputs!G15-Inputs!E15)*BETAINV(RAND(),Model!J9,Model!K9) -> 0.64690933 | Y22: =(Inputs!H15+(Inputs!J15-Inputs!H15)*BETAINV(RAND(),Model!L9,Model!M9))*Inputs!$C$6 -> 55665.747 | Z22: =W22*X22 -> 0.97438559 | AA22: =RAND() -> 0.01798646 | AB22: =IF(AA22<EXP(-Z22),0,IF(AA22<EXP(-Z22)*(1+Z22),1,IF(AA22<EXP(-Z22)*(1+Z22+Z22^2/2),2,IF(AA22<EXP(-Z22)*(1+Z22+Z22^2/2+Z22^3/6),3,4)))) -> 0 | AC22: =AB22*Y22 -> 0 | AD22: =Inputs!B16+(Inputs!D16-Inputs!B16)*BETAINV(RAND(),Model!H10,Model!I10) -> 1.067885 | AE22: =Inputs!E16+(Inputs!G16-Inputs!E16)*BETAINV(RAND(),Model!J10,Model!K10) -> 0.49888607 | AF22: =(Inputs!H16+(Inputs!J16-Inputs!H16)*BETAINV(RAND(),Model!L10,Model!M10))*Inputs!$C$6 -> 63665.707 | AG22: =AD22*AE22 -> 0.53275295 | AH22: =RAND() -> 0.092621616 | AI22: =IF(AH22<EXP(-AG22),0,IF(AH22<EXP(-AG22)*(1+AG22),1,IF(AH22<EXP(-AG22)*(1+AG22+AG22^2/2),2,IF(AH22<EXP(-AG22)*(1+AG22+AG22^2/2+AG22^3/6),3,4)))) -> 0 | AJ22: =AI22*AF22 -> 0 | AK22: =H22+O22+V22+AC22+AJ22 -> 314283.6
B23: =Inputs!B12+(Inputs!D12-Inputs!B12)*BETAINV(RAND(),Model!H6,Model!I6) -> 5.0364066 | C23: =Inputs!E12+(Inputs!G12-Inputs!E12)*BETAINV(RAND(),Model!J6,Model!K6) -> 0.17366164 | D23: =(Inputs!H12+(Inputs!J12-Inputs!H12)*BETAINV(RAND(),Model!L6,Model!M6))*Inputs!$C$6 -> 30669.595 | E23: =B23*C23 -> 0.87463061 | F23: =RAND() -> 0.4754431 | G23: =IF(F23<EXP(-E23),0,IF(F23<EXP(-E23)*(1+E23),1,IF(F23<EXP(-E23)*(1+E23+E23^2/2),2,IF(F23<EXP(-E23)*(1+E23+E23^2/2+E23^3/6),3,4)))) -> 1 | H23: =G23*D23 -> 30669.595 | I23: =Inputs!B13+(Inputs!D13-Inputs!B13)*BETAINV(RAND(),Model!H7,Model!I7) -> 2.7203644 | J23: =Inputs!E13+(Inputs!G13-Inputs!E13)*BETAINV(RAND(),Model!J7,Model!K7) -> 0.35380611 | K23: =(Inputs!H13+(Inputs!J13-Inputs!H13)*BETAINV(RAND(),Model!L7,Model!M7))*Inputs!$C$6 -> 31497.623 | L23: =I23*J23 -> 0.96248154 | M23: =RAND() -> 0.31180461 | N23: =IF(M23<EXP(-L23),0,IF(M23<EXP(-L23)*(1+L23),1,IF(M23<EXP(-L23)*(1+L23+L23^2/2),2,IF(M23<EXP(-L23)*(1+L23+L23^2/2+L23^3/6),3,4)))) -> 0 | O23: =N23*K23 -> 0 | P23: =Inputs!B14+(Inputs!D14-Inputs!B14)*BETAINV(RAND(),Model!H8,Model!I8) -> 0.22793242 | Q23: =Inputs!E14+(Inputs!G14-Inputs!E14)*BETAINV(RAND(),Model!J8,Model!K8) -> 0.71668091 | R23: =(Inputs!H14+(Inputs!J14-Inputs!H14)*BETAINV(RAND(),Model!L8,Model!M8))*Inputs!$C$6 -> 209096.04 | S23: =P23*Q23 -> 0.16335481 | T23: =RAND() -> 0.88648937 | U23: =IF(T23<EXP(-S23),0,IF(T23<EXP(-S23)*(1+S23),1,IF(T23<EXP(-S23)*(1+S23+S23^2/2),2,IF(T23<EXP(-S23)*(1+S23+S23^2/2+S23^3/6),3,4)))) -> 1 | V23: =U23*R23 -> 209096.04 | W23: =Inputs!B15+(Inputs!D15-Inputs!B15)*BETAINV(RAND(),Model!H9,Model!I9) -> 0.64192755 | X23: =Inputs!E15+(Inputs!G15-Inputs!E15)*BETAINV(RAND(),Model!J9,Model!K9) -> 0.49449238 | Y23: =(Inputs!H15+(Inputs!J15-Inputs!H15)*BETAINV(RAND(),Model!L9,Model!M9))*Inputs!$C$6 -> 36338.158 | Z23: =W23*X23 -> 0.31742828 | AA23: =RAND() -> 0.85094406 | AB23: =IF(AA23<EXP(-Z23),0,IF(AA23<EXP(-Z23)*(1+Z23),1,IF(AA23<EXP(-Z23)*(1+Z23+Z23^2/2),2,IF(AA23<EXP(-Z23)*(1+Z23+Z23^2/2+Z23^3/6),3,4)))) -> 1 | AC23: =AB23*Y23 -> 36338.158 | AD23: =Inputs!B16+(Inputs!D16-Inputs!B16)*BETAINV(RAND(),Model!H10,Model!I10) -> 0.98903091 | AE23: =Inputs!E16+(Inputs!G16-Inputs!E16)*BETAINV(RAND(),Model!J10,Model!K10) -> 0.72302428 | AF23: =(Inputs!H16+(Inputs!J16-Inputs!H16)*BETAINV(RAND(),Model!L10,Model!M10))*Inputs!$C$6 -> 52329.569 | AG23: =AD23*AE23 -> 0.71509336 | AH23: =RAND() -> 0.17638155 | AI23: =IF(AH23<EXP(-AG23),0,IF(AH23<EXP(-AG23)*(1+AG23),1,IF(AH23<EXP(-AG23)*(1+AG23+AG23^2/2),2,IF(AH23<EXP(-AG23)*(1+AG23+AG23^2/2+AG23^3/6),3,4)))) -> 0 | AJ23: =AI23*AF23 -> 0 | AK23: =H23+O23+V23+AC23+AJ23 -> 276103.79
B24: =Inputs!B12+(Inputs!D12-Inputs!B12)*BETAINV(RAND(),Model!H6,Model!I6) -> 2.7130798 | C24: =Inputs!E12+(Inputs!G12-Inputs!E12)*BETAINV(RAND(),Model!J6,Model!K6) -> 0.2723294 | D24: =(Inputs!H12+(Inputs!J12-Inputs!H12)*BETAINV(RAND(),Model!L6,Model!M6))*Inputs!$C$6 -> 27387.14 | E24: =B24*C24 -> 0.7388514 | F24: =RAND() -> 0.099620321 | G24: =IF(F24<EXP(-E24),0,IF(F24<EXP(-E24)*(1+E24),1,IF(F24<EXP(-E24)*(1+E24+E24^2/2),2,IF(F24<EXP(-E24)*(1+E24+E24^2/2+E24^3/6),3,4)))) -> 0 | H24: =G24*D24 -> 0 | I24: =Inputs!B13+(Inputs!D13-Inputs!B13)*BETAINV(RAND(),Model!H7,Model!I7) -> 1.3980574 | J24: =Inputs!E13+(Inputs!G13-Inputs!E13)*BETAINV(RAND(),Model!J7,Model!K7) -> 0.2729067 | K24: =(Inputs!H13+(Inputs!J13-Inputs!H13)*BETAINV(RAND(),Model!L7,Model!M7))*Inputs!$C$6 -> 34275.218 | L24: =I24*J24 -> 0.38153924 | M24: =RAND() -> 0.54601699 | N24: =IF(M24<EXP(-L24),0,IF(M24<EXP(-L24)*(1+L24),1,IF(M24<EXP(-L24)*(1+L24+L24^2/2),2,IF(M24<EXP(-L24)*(1+L24+L24^2/2+L24^3/6),3,4)))) -> 0 | O24: =N24*K24 -> 0 | P24: =Inputs!B14+(Inputs!D14-Inputs!B14)*BETAINV(RAND(),Model!H8,Model!I8) -> 0.18288642 | Q24: =Inputs!E14+(Inputs!G14-Inputs!E14)*BETAINV(RAND(),Model!J8,Model!K8) -> 0.50082552 | R24: =(Inputs!H14+(Inputs!J14-Inputs!H14)*BETAINV(RAND(),Model!L8,Model!M8))*Inputs!$C$6 -> 323601.88 | S24: =P24*Q24 -> 0.091594186 | T24: =RAND() -> 0.26822627 | U24: =IF(T24<EXP(-S24),0,IF(T24<EXP(-S24)*(1+S24),1,IF(T24<EXP(-S24)*(1+S24+S24^2/2),2,IF(T24<EXP(-S24)*(1+S24+S24^2/2+S24^3/6),3,4)))) -> 0 | V24: =U24*R24 -> 0 | W24: =Inputs!B15+(Inputs!D15-Inputs!B15)*BETAINV(RAND(),Model!H9,Model!I9) -> 2.0088556 | X24: =Inputs!E15+(Inputs!G15-Inputs!E15)*BETAINV(RAND(),Model!J9,Model!K9) -> 0.43905206 | Y24: =(Inputs!H15+(Inputs!J15-Inputs!H15)*BETAINV(RAND(),Model!L9,Model!M9))*Inputs!$C$6 -> 26305.859 | Z24: =W24*X24 -> 0.88199218 | AA24: =RAND() -> 0.9122106 | AB24: =IF(AA24<EXP(-Z24),0,IF(AA24<EXP(-Z24)*(1+Z24),1,IF(AA24<EXP(-Z24)*(1+Z24+Z24^2/2),2,IF(AA24<EXP(-Z24)*(1+Z24+Z24^2/2+Z24^3/6),3,4)))) -> 2 | AC24: =AB24*Y24 -> 52611.717 | AD24: =Inputs!B16+(Inputs!D16-Inputs!B16)*BETAINV(RAND(),Model!H10,Model!I10) -> 0.66787453 | AE24: =Inputs!E16+(Inputs!G16-Inputs!E16)*BETAINV(RAND(),Model!J10,Model!K10) -> 0.69216401 | AF24: =(Inputs!H16+(Inputs!J16-Inputs!H16)*BETAINV(RAND(),Model!L10,Model!M10))*Inputs!$C$6 -> 129947.53 | AG24: =AD24*AE24 -> 0.46227872 | AH24: =RAND() -> 0.10147126 | AI24: =IF(AH24<EXP(-AG24),0,IF(AH24<EXP(-AG24)*(1+AG24),1,IF(AH24<EXP(-AG24)*(1+AG24+AG24^2/2),2,IF(AH24<EXP(-AG24)*(1+AG24+AG24^2/2+AG24^3/6),3,4)))) -> 0 | AJ24: =AI24*AF24 -> 0 | AK24: =H24+O24+V24+AC24+AJ24 -> 52611.717
B25: =Inputs!B12+(Inputs!D12-Inputs!B12)*BETAINV(RAND(),Model!H6,Model!I6) -> 3.0670855 | C25: =Inputs!E12+(Inputs!G12-Inputs!E12)*BETAINV(RAND(),Model!J6,Model!K6) -> 0.3415103 | D25: =(Inputs!H12+(Inputs!J12-Inputs!H12)*BETAINV(RAND(),Model!L6,Model!M6))*Inputs!$C$6 -> 44996.741 | E25: =B25*C25 -> 1.0474413 | F25: =RAND() -> 0.031746829 | G25: =IF(F25<EXP(-E25),0,IF(F25<EXP(-E25)*(1+E25),1,IF(F25<EXP(-E25)*(1+E25+E25^2/2),2,IF(F25<EXP(-E25)*(1+E25+E25^2/2+E25^3/6),3,4)))) -> 0 | H25: =G25*D25 -> 0 | I25: =Inputs!B13+(Inputs!D13-Inputs!B13)*BETAINV(RAND(),Model!H7,Model!I7) -> 2.2188865 | J25: =Inputs!E13+(Inputs!G13-Inputs!E13)*BETAINV(RAND(),Model!J7,Model!K7) -> 0.3698465 | K25: =(Inputs!H13+(Inputs!J13-Inputs!H13)*BETAINV(RAND(),Model!L7,Model!M7))*Inputs!$C$6 -> 39233.974 | L25: =I25*J25 -> 0.82064741 | M25: =RAND() -> 0.60879566 | N25: =IF(M25<EXP(-L25),0,IF(M25<EXP(-L25)*(1+L25),1,IF(M25<EXP(-L25)*(1+L25+L25^2/2),2,IF(M25<EXP(-L25)*(1+L25+L25^2/2+L25^3/6),3,4)))) -> 1 | O25: =N25*K25 -> 39233.974 | P25: =Inputs!B14+(Inputs!D14-Inputs!B14)*BETAINV(RAND(),Model!H8,Model!I8) -> 0.39653423 | Q25: =Inputs!E14+(Inputs!G14-Inputs!E14)*BETAINV(RAND(),Model!J8,Model!K8) -> 0.62784833 | R25: =(Inputs!H14+(Inputs!J14-Inputs!H14)*BETAINV(RAND(),Model!L8,Model!M8))*Inputs!$C$6 -> 195402.68 | S25: =P25*Q25 -> 0.24896336 | T25: =RAND() -> 0.53133195 | U25: =IF(T25<EXP(-S25),0,IF(T25<EXP(-S25)*(1+S25),1,IF(T25<EXP(-S25)*(1+S25+S25^2/2),2,IF(T25<EXP(-S25)*(1+S25+S25^2/2+S25^3/6),3,4)))) -> 0 | V25: =U25*R25 -> 0 | W25: =Inputs!B15+(Inputs!D15-Inputs!B15)*BETAINV(RAND(),Model!H9,Model!I9) -> 2.1838954 | X25: =Inputs!E15+(Inputs!G15-Inputs!E15)*BETAINV(RAND(),Model!J9,Model!K9) -> 0.34124869 | Y25: =(Inputs!H15+(Inputs!J15-Inputs!H15)*BETAINV(RAND(),Model!L9,Model!M9))*Inputs!$C$6 -> 37734.667 | Z25: =W25*X25 -> 0.74525142 | AA25: =RAND() -> 0.052004822 | AB25: =IF(AA25<EXP(-Z25),0,IF(AA25<EXP(-Z25)*(1+Z25),1,IF(AA25<EXP(-Z25)*(1+Z25+Z25^2/2),2,IF(AA25<EXP(-Z25)*(1+Z25+Z25^2/2+Z25^3/6),3,4)))) -> 0 | AC25: =AB25*Y25 -> 0 | AD25: =Inputs!B16+(Inputs!D16-Inputs!B16)*BETAINV(RAND(),Model!H10,Model!I10) -> 1.0795812 | AE25: =Inputs!E16+(Inputs!G16-Inputs!E16)*BETAINV(RAND(),Model!J10,Model!K10) -> 0.61638322 | AF25: =(Inputs!H16+(Inputs!J16-Inputs!H16)*BETAINV(RAND(),Model!L10,Model!M10))*Inputs!$C$6 -> 44140.769 | AG25: =AD25*AE25 -> 0.66543571 | AH25: =RAND() -> 0.79162312 | AI25: =IF(AH25<EXP(-AG25),0,IF(AH25<EXP(-AG25)*(1+AG25),1,IF(AH25<EXP(-AG25)*(1+AG25+AG25^2/2),2,IF(AH25<EXP(-AG25)*(1+AG25+AG25^2/2+AG25^3/6),3,4)))) -> 1 | AJ25: =AI25*AF25 -> 44140.769 | AK25: =H25+O25+V25+AC25+AJ25 -> 83374.743
B26: =Inputs!B12+(Inputs!D12-Inputs!B12)*BETAINV(RAND(),Model!H6,Model!I6) -> 3.3972517 | C26: =Inputs!E12+(Inputs!G12-Inputs!E12)*BETAINV(RAND(),Model!J6,Model!K6) -> 0.42868732 | D26: =(Inputs!H12+(Inputs!J12-Inputs!H12)*BETAINV(RAND(),Model!L6,Model!M6))*Inputs!$C$6 -> 20341.637 | E26: =B26*C26 -> 1.4563587 | F26: =RAND() -> 0.22162447 | G26: =IF(F26<EXP(-E26),0,IF(F26<EXP(-E26)*(1+E26),1,IF(F26<EXP(-E26)*(1+E26+E26^2/2),2,IF(F26<EXP(-E26)*(1+E26+E26^2/2+E26^3/6),3,4)))) -> 0 | H26: =G26*D26 -> 0 | I26: =Inputs!B13+(Inputs!D13-Inputs!B13)*BETAINV(RAND(),Model!H7,Model!I7) -> 3.2120336 | J26: =Inputs!E13+(Inputs!G13-Inputs!E13)*BETAINV(RAND(),Model!J7,Model!K7) -> 0.33290504 | K26: =(Inputs!H13+(Inputs!J13-Inputs!H13)*BETAINV(RAND(),Model!L7,Model!M7))*Inputs!$C$6 -> 47946.253 | L26: =I26*J26 -> 1.0693022 | M26: =RAND() -> 0.7617418 | N26: =IF(M26<EXP(-L26),0,IF(M26<EXP(-L26)*(1+L26),1,IF(M26<EXP(-L26)*(1+L26+L26^2/2),2,IF(M26<EXP(-L26)*(1+L26+L26^2/2+L26^3/6),3,4)))) -> 2 | O26: =N26*K26 -> 95892.507 | P26: =Inputs!B14+(Inputs!D14-Inputs!B14)*BETAINV(RAND(),Model!H8,Model!I8) -> 0.1255638 | Q26: =Inputs!E14+(Inputs!G14-Inputs!E14)*BETAINV(RAND(),Model!J8,Model!K8) -> 0.64337701 | R26: =(Inputs!H14+(Inputs!J14-Inputs!H14)*BETAINV(RAND(),Model!L8,Model!M8))*Inputs!$C$6 -> 381211.2 | S26: =P26*Q26 -> 0.080784864 | T26: =RAND() -> 0.23960387 | U26: =IF(T26<EXP(-S26),0,IF(T26<EXP(-S26)*(1+S26),1,IF(T26<EXP(-S26)*(1+S26+S26^2/2),2,IF(T26<EXP(-S26)*(1+S26+S26^2/2+S26^3/6),3,4)))) -> 0 | V26: =U26*R26 -> 0 | W26: =Inputs!B15+(Inputs!D15-Inputs!B15)*BETAINV(RAND(),Model!H9,Model!I9) -> 0.59501877 | X26: =Inputs!E15+(Inputs!G15-Inputs!E15)*BETAINV(RAND(),Model!J9,Model!K9) -> 0.38093908 | Y26: =(Inputs!H15+(Inputs!J15-Inputs!H15)*BETAINV(RAND(),Model!L9,Model!M9))*Inputs!$C$6 -> 66598.116 | Z26: =W26*X26 -> 0.2266659 | AA26: =RAND() -> 0.32272239 | AB26: =IF(AA26<EXP(-Z26),0,IF(AA26<EXP(-Z26)*(1+Z26),1,IF(AA26<EXP(-Z26)*(1+Z26+Z26^2/2),2,IF(AA26<EXP(-Z26)*(1+Z26+Z26^2/2+Z26^3/6),3,4)))) -> 0 | AC26: =AB26*Y26 -> 0 | AD26: =Inputs!B16+(Inputs!D16-Inputs!B16)*BETAINV(RAND(),Model!H10,Model!I10) -> 0.52966587 | AE26: =Inputs!E16+(Inputs!G16-Inputs!E16)*BETAINV(RAND(),Model!J10,Model!K10) -> 0.70251236 | AF26: =(Inputs!H16+(Inputs!J16-Inputs!H16)*BETAINV(RAND(),Model!L10,Model!M10))*Inputs!$C$6 -> 93741.333 | AG26: =AD26*AE26 -> 0.37209682 | AH26: =RAND() -> 0.25564239 | AI26: =IF(AH26<EXP(-AG26),0,IF(AH26<EXP(-AG26)*(1+AG26),1,IF(AH26<EXP(-AG26)*(1+AG26+AG26^2/2),2,IF(AH26<EXP(-AG26)*(1+AG26+AG26^2/2+AG26^3/6),3,4)))) -> 0 | AJ26: =AI26*AF26 -> 0 | AK26: =H26+O26+V26+AC26+AJ26 -> 95892.507
B27: =Inputs!B12+(Inputs!D12-Inputs!B12)*BETAINV(RAND(),Model!H6,Model!I6) -> 4.8598189 | C27: =Inputs!E12+(Inputs!G12-Inputs!E12)*BETAINV(RAND(),Model!J6,Model!K6) -> 0.33184262 | D27: =(Inputs!H12+(Inputs!J12-Inputs!H12)*BETAINV(RAND(),Model!L6,Model!M6))*Inputs!$C$6 -> 20003.505 | E27: =B27*C27 -> 1.612695 | F27: =RAND() -> 0.28285904 | G27: =IF(F27<EXP(-E27),0,IF(F27<EXP(-E27)*(1+E27),1,IF(F27<EXP(-E27)*(1+E27+E27^2/2),2,IF(F27<EXP(-E27)*(1+E27+E27^2/2+E27^3/6),3,4)))) -> 1 | H27: =G27*D27 -> 20003.505 | I27: =Inputs!B13+(Inputs!D13-Inputs!B13)*BETAINV(RAND(),Model!H7,Model!I7) -> 1.3596487 | J27: =Inputs!E13+(Inputs!G13-Inputs!E13)*BETAINV(RAND(),Model!J7,Model!K7) -> 0.36118949 | K27: =(Inputs!H13+(Inputs!J13-Inputs!H13)*BETAINV(RAND(),Model!L7,Model!M7))*Inputs!$C$6 -> 28790.061 | L27: =I27*J27 -> 0.49109081 | M27: =RAND() -> 0.78642174 | N27: =IF(M27<EXP(-L27),0,IF(M27<EXP(-L27)*(1+L27),1,IF(M27<EXP(-L27)*(1+L27+L27^2/2),2,IF(M27<EXP(-L27)*(1+L27+L27^2/2+L27^3/6),3,4)))) -> 1 | O27: =N27*K27 -> 28790.061 | P27: =Inputs!B14+(Inputs!D14-Inputs!B14)*BETAINV(RAND(),Model!H8,Model!I8) -> 0.60717078 | Q27: =Inputs!E14+(Inputs!G14-Inputs!E14)*BETAINV(RAND(),Model!J8,Model!K8) -> 0.69374003 | R27: =(Inputs!H14+(Inputs!J14-Inputs!H14)*BETAINV(RAND(),Model!L8,Model!M8))*Inputs!$C$6 -> 294136.15 | S27: =P27*Q27 -> 0.42121868 | T27: =RAND() -> 0.35291561 | U27: =IF(T27<EXP(-S27),0,IF(T27<EXP(-S27)*(1+S27),1,IF(T27<EXP(-S27)*(1+S27+S27^2/2),2,IF(T27<EXP(-S27)*(1+S27+S27^2/2+S27^3/6),3,4)))) -> 0 | V27: =U27*R27 -> 0 | W27: =Inputs!B15+(Inputs!D15-Inputs!B15)*BETAINV(RAND(),Model!H9,Model!I9) -> 0.79675707 | X27: =Inputs!E15+(Inputs!G15-Inputs!E15)*BETAINV(RAND(),Model!J9,Model!K9) -> 0.41341462 | Y27: =(Inputs!H15+(Inputs!J15-Inputs!H15)*BETAINV(RAND(),Model!L9,Model!M9))*Inputs!$C$6 -> 10516.433 | Z27: =W27*X27 -> 0.32939102 | AA27: =RAND() -> 0.50967266 | AB27: =IF(AA27<EXP(-Z27),0,IF(AA27<EXP(-Z27)*(1+Z27),1,IF(AA27<EXP(-Z27)*(1+Z27+Z27^2/2),2,IF(AA27<EXP(-Z27)*(1+Z27+Z27^2/2+Z27^3/6),3,4)))) -> 0 | AC27: =AB27*Y27 -> 0 | AD27: =Inputs!B16+(Inputs!D16-Inputs!B16)*BETAINV(RAND(),Model!H10,Model!I10) -> 1.0307583 | AE27: =Inputs!E16+(Inputs!G16-Inputs!E16)*BETAINV(RAND(),Model!J10,Model!K10) -> 0.60606428 | AF27: =(Inputs!H16+(Inputs!J16-Inputs!H16)*BETAINV(RAND(),Model!L10,Model!M10))*Inputs!$C$6 -> 118712.17 | AG27: =AD27*AE27 -> 0.62470577 | AH27: =RAND() -> 0.49728165 | AI27: =IF(AH27<EXP(-AG27),0,IF(AH27<EXP(-AG27)*(1+AG27),1,IF(AH27<EXP(-AG27)*(1+AG27+AG27^2/2),2,IF(AH27<EXP(-AG27)*(1+AG27+AG27^2/2+AG27^3/6),3,4)))) -> 0 | AJ27: =AI27*AF27 -> 0 | AK27: =H27+O27+V27+AC27+AJ27 -> 48793.566
B28: =Inputs!B12+(Inputs!D12-Inputs!B12)*BETAINV(RAND(),Model!H6,Model!I6) -> 6.281707 | C28: =Inputs!E12+(Inputs!G12-Inputs!E12)*BETAINV(RAND(),Model!J6,Model!K6) -> 0.32344687 | D28: =(Inputs!H12+(Inputs!J12-Inputs!H12)*BETAINV(RAND(),Model!L6,Model!M6))*Inputs!$C$6 -> 26728.343 | E28: =B28*C28 -> 2.0317985 | F28: =RAND() -> 0.3235145 | G28: =IF(F28<EXP(-E28),0,IF(F28<EXP(-E28)*(1+E28),1,IF(F28<EXP(-E28)*(1+E28+E28^2/2),2,IF(F28<EXP(-E28)*(1+E28+E28^2/2+E28^3/6),3,4)))) -> 1 | H28: =G28*D28 -> 26728.343 | I28: =Inputs!B13+(Inputs!D13-Inputs!B13)*BETAINV(RAND(),Model!H7,Model!I7) -> 4.0657581 | J28: =Inputs!E13+(Inputs!G13-Inputs!E13)*BETAINV(RAND(),Model!J7,Model!K7) -> 0.30564677 | K28: =(Inputs!H13+(Inputs!J13-Inputs!H13)*BETAINV(RAND(),Model!L7,Model!M7))*Inputs!$C$6 -> 51210.572 | L28: =I28*J28 -> 1.2426858 | M28: =RAND() -> 0.75534356 | N28: =IF(M28<EXP(-L28),0,IF(M28<EXP(-L28)*(1+L28),1,IF(M28<EXP(-L28)*(1+L28+L28^2/2),2,IF(M28<EXP(-L28)*(1+L28+L28^2/2+L28^3/6),3,4)))) -> 2 | O28: =N28*K28 -> 102421.14 | P28: =Inputs!B14+(Inputs!D14-Inputs!B14)*BETAINV(RAND(),Model!H8,Model!I8) -> 0.24208878 | Q28: =Inputs!E14+(Inputs!G14-Inputs!E14)*BETAINV(RAND(),Model!J8,Model!K8) -> 0.41911428 | R28: =(Inputs!H14+(Inputs!J14-Inputs!H14)*BETAINV(RAND(),Model!L8,Model!M8))*Inputs!$C$6 -> 310280.8 | S28: =P28*Q28 -> 0.10146287 | T28: =RAND() -> 0.64052898 | U28: =IF(T28<EXP(-S28),0,IF(T28<EXP(-S28)*(1+S28),1,IF(T28<EXP(-S28)*(1+S28+S28^2/2),2,IF(T28<EXP(-S28)*(1+S28+S28^2/2+S28^3/6),3,4)))) -> 0 | V28: =U28*R28 -> 0 | W28: =Inputs!B15+(Inputs!D15-Inputs!B15)*BETAINV(RAND(),Model!H9,Model!I9) -> 1.7672386 | X28: =Inputs!E15+(Inputs!G15-Inputs!E15)*BETAINV(RAND(),Model!J9,Model!K9) -> 0.49096453 | Y28: =(Inputs!H15+(Inputs!J15-Inputs!H15)*BETAINV(RAND(),Model!L9,Model!M9))*Inputs!$C$6 -> 24942.849 | Z28: =W28*X28 -> 0.86765147 | AA28: =RAND() -> 0.31336444 | AB28: =IF(AA28<EXP(-Z28),0,IF(AA28<EXP(-Z28)*(1+Z28),1,IF(AA28<EXP(-Z28)*(1+Z28+Z28^2/2),2,IF(AA28<EXP(-Z28)*(1+Z28+Z28^2/2+Z28^3/6),3,4)))) -> 0 | AC28: =AB28*Y28 -> 0 | AD28: =Inputs!B16+(Inputs!D16-Inputs!B16)*BETAINV(RAND(),Model!H10,Model!I10) -> 0.55518083 | AE28: =Inputs!E16+(Inputs!G16-Inputs!E16)*BETAINV(RAND(),Model!J10,Model!K10) -> 0.56629698 | AF28: =(Inputs!H16+(Inputs!J16-Inputs!H16)*BETAINV(RAND(),Model!L10,Model!M10))*Inputs!$C$6 -> 89484.957 | AG28: =AD28*AE28 -> 0.31439723 | AH28: =RAND() -> 0.88955852 | AI28: =IF(AH28<EXP(-AG28),0,IF(AH28<EXP(-AG28)*(1+AG28),1,IF(AH28<EXP(-AG28)*(1+AG28+AG28^2/2),2,IF(AH28<EXP(-AG28)*(1+AG28+AG28^2/2+AG28^3/6),3,4)))) -> 1 | AJ28: =AI28*AF28 -> 89484.957 | AK28: =H28+O28+V28+AC28+AJ28 -> 218634.45
B29: =Inputs!B12+(Inputs!D12-Inputs!B12)*BETAINV(RAND(),Model!H6,Model!I6) -> 2.3542727 | C29: =Inputs!E12+(Inputs!G12-Inputs!E12)*BETAINV(RAND(),Model!J6,Model!K6) -> 0.37073496 | D29: =(Inputs!H12+(Inputs!J12-Inputs!H12)*BETAINV(RAND(),Model!L6,Model!M6))*Inputs!$C$6 -> 37681.33 | E29: =B29*C29 -> 0.87281119 | F29: =RAND() -> 0.90882717 | G29: =IF(F29<EXP(-E29),0,IF(F29<EXP(-E29)*(1+E29),1,IF(F29<EXP(-E29)*(1+E29+E29^2/2),2,IF(F29<EXP(-E29)*(1+E29+E29^2/2+E29^3/6),3,4)))) -> 2 | H29: =G29*D29 -> 75362.661 | I29: =Inputs!B13+(Inputs!D13-Inputs!B13)*BETAINV(RAND(),Model!H7,Model!I7) -> 1.0500941 | J29: =Inputs!E13+(Inputs!G13-Inputs!E13)*BETAINV(RAND(),Model!J7,Model!K7) -> 0.15397051 | K29: =(Inputs!H13+(Inputs!J13-Inputs!H13)*BETAINV(RAND(),Model!L7,Model!M7))*Inputs!$C$6 -> 13797.343 | L29: =I29*J29 -> 0.16168352 | M29: =RAND() -> 0.074584895 | N29: =IF(M29<EXP(-L29),0,IF(M29<EXP(-L29)*(1+L29),1,IF(M29<EXP(-L29)*(1+L29+L29^2/2),2,IF(M29<EXP(-L29)*(1+L29+L29^2/2+L29^3/6),3,4)))) -> 0 | O29: =N29*K29 -> 0 | P29: =Inputs!B14+(Inputs!D14-Inputs!B14)*BETAINV(RAND(),Model!H8,Model!I8) -> 0.49699146 | Q29: =Inputs!E14+(Inputs!G14-Inputs!E14)*BETAINV(RAND(),Model!J8,Model!K8) -> 0.56714315 | R29: =(Inputs!H14+(Inputs!J14-Inputs!H14)*BETAINV(RAND(),Model!L8,Model!M8))*Inputs!$C$6 -> 323408.01 | S29: =P29*Q29 -> 0.2818653 | T29: =RAND() -> 0.52921237 | U29: =IF(T29<EXP(-S29),0,IF(T29<EXP(-S29)*(1+S29),1,IF(T29<EXP(-S29)*(1+S29+S29^2/2),2,IF(T29<EXP(-S29)*(1+S29+S29^2/2+S29^3/6),3,4)))) -> 0 | V29: =U29*R29 -> 0 | W29: =Inputs!B15+(Inputs!D15-Inputs!B15)*BETAINV(RAND(),Model!H9,Model!I9) -> 0.37374604 | X29: =Inputs!E15+(Inputs!G15-Inputs!E15)*BETAINV(RAND(),Model!J9,Model!K9) -> 0.28291467 | Y29: =(Inputs!H15+(Inputs!J15-Inputs!H15)*BETAINV(RAND(),Model!L9,Model!M9))*Inputs!$C$6 -> 67199.958 | Z29: =W29*X29 -> 0.10573824 | AA29: =RAND() -> 0.64324142 | AB29: =IF(AA29<EXP(-Z29),0,IF(AA29<EXP(-Z29)*(1+Z29),1,IF(AA29<EXP(-Z29)*(1+Z29+Z29^2/2),2,IF(AA29<EXP(-Z29)*(1+Z29+Z29^2/2+Z29^3/6),3,4)))) -> 0 | AC29: =AB29*Y29 -> 0 | AD29: =Inputs!B16+(Inputs!D16-Inputs!B16)*BETAINV(RAND(),Model!H10,Model!I10) -> 0.78637055 | AE29: =Inputs!E16+(Inputs!G16-Inputs!E16)*BETAINV(RAND(),Model!J10,Model!K10) -> 0.64310758 | AF29: =(Inputs!H16+(Inputs!J16-Inputs!H16)*BETAINV(RAND(),Model!L10,Model!M10))*Inputs!$C$6 -> 85892.976 | AG29: =AD29*AE29 -> 0.50572086 | AH29: =RAND() -> 0.40322182 | AI29: =IF(AH29<EXP(-AG29),0,IF(AH29<EXP(-AG29)*(1+AG29),1,IF(AH29<EXP(-AG29)*(1+AG29+AG29^2/2),2,IF(AH29<EXP(-AG29)*(1+AG29+AG29^2/2+AG29^3/6),3,4)))) -> 0 | AJ29: =AI29*AF29 -> 0 | AK29: =H29+O29+V29+AC29+AJ29 -> 75362.661
B30: =Inputs!B12+(Inputs!D12-Inputs!B12)*BETAINV(RAND(),Model!H6,Model!I6) -> 5.2886264 | C30: =Inputs!E12+(Inputs!G12-Inputs!E12)*BETAINV(RAND(),Model!J6,Model!K6) -> 0.4595346 | D30: =(Inputs!H12+(Inputs!J12-Inputs!H12)*BETAINV(RAND(),Model!L6,Model!M6))*Inputs!$C$6 -> 28864.598 | E30: =B30*C30 -> 2.4303068 | F30: =RAND() -> 0.57653298 | G30: =IF(F30<EXP(-E30),0,IF(F30<EXP(-E30)*(1+E30),1,IF(F30<EXP(-E30)*(1+E30+E30^2/2),2,IF(F30<EXP(-E30)*(1+E30+E30^2/2+E30^3/6),3,4)))) -> 3 | H30: =G30*D30 -> 86593.793 | I30: =Inputs!B13+(Inputs!D13-Inputs!B13)*BETAINV(RAND(),Model!H7,Model!I7) -> 2.3547663 | J30: =Inputs!E13+(Inputs!G13-Inputs!E13)*BETAINV(RAND(),Model!J7,Model!K7) -> 0.37169682 | K30: =(Inputs!H13+(Inputs!J13-Inputs!H13)*BETAINV(RAND(),Model!L7,Model!M7))*Inputs!$C$6 -> 21279.703 | L30: =I30*J30 -> 0.87525916 | M30: =RAND() -> 0.28377581 | N30: =IF(M30<EXP(-L30),0,IF(M30<EXP(-L30)*(1+L30),1,IF(M30<EXP(-L30)*(1+L30+L30^2/2),2,IF(M30<EXP(-L30)*(1+L30+L30^2/2+L30^3/6),3,4)))) -> 0 | O30: =N30*K30 -> 0 | P30: =Inputs!B14+(Inputs!D14-Inputs!B14)*BETAINV(RAND(),Model!H8,Model!I8) -> 0.42258334 | Q30: =Inputs!E14+(Inputs!G14-Inputs!E14)*BETAINV(RAND(),Model!J8,Model!K8) -> 0.50246916 | R30: =(Inputs!H14+(Inputs!J14-Inputs!H14)*BETAINV(RAND(),Model!L8,Model!M8))*Inputs!$C$6 -> 261510.93 | S30: =P30*Q30 -> 0.2123351 | T30: =RAND() -> 0.88175834 | U30: =IF(T30<EXP(-S30),0,IF(T30<EXP(-S30)*(1+S30),1,IF(T30<EXP(-S30)*(1+S30+S30^2/2),2,IF(T30<EXP(-S30)*(1+S30+S30^2/2+S30^3/6),3,4)))) -> 1 | V30: =U30*R30 -> 261510.93 | W30: =Inputs!B15+(Inputs!D15-Inputs!B15)*BETAINV(RAND(),Model!H9,Model!I9) -> 0.93326987 | X30: =Inputs!E15+(Inputs!G15-Inputs!E15)*BETAINV(RAND(),Model!J9,Model!K9) -> 0.49745375 | Y30: =(Inputs!H15+(Inputs!J15-Inputs!H15)*BETAINV(RAND(),Model!L9,Model!M9))*Inputs!$C$6 -> 14922.91 | Z30: =W30*X30 -> 0.46425859 | AA30: =RAND() -> 0.3249427 | AB30: =IF(AA30<EXP(-Z30),0,IF(AA30<EXP(-Z30)*(1+Z30),1,IF(AA30<EXP(-Z30)*(1+Z30+Z30^2/2),2,IF(AA30<EXP(-Z30)*(1+Z30+Z30^2/2+Z30^3/6),3,4)))) -> 0 | AC30: =AB30*Y30 -> 0 | AD30: =Inputs!B16+(Inputs!D16-Inputs!B16)*BETAINV(RAND(),Model!H10,Model!I10) -> 0.48959222 | AE30: =Inputs!E16+(Inputs!G16-Inputs!E16)*BETAINV(RAND(),Model!J10,Model!K10) -> 0.72298745 | AF30: =(Inputs!H16+(Inputs!J16-Inputs!H16)*BETAINV(RAND(),Model!L10,Model!M10))*Inputs!$C$6 -> 53020.447 | AG30: =AD30*AE30 -> 0.35396903 | AH30: =RAND() -> 0.46174212 | AI30: =IF(AH30<EXP(-AG30),0,IF(AH30<EXP(-AG30)*(1+AG30),1,IF(AH30<EXP(-AG30)*(1+AG30+AG30^2/2),2,IF(AH30<EXP(-AG30)*(1+AG30+AG30^2/2+AG30^3/6),3,4)))) -> 0 | AJ30: =AI30*AF30 -> 0 | AK30: =H30+O30+V30+AC30+AJ30 -> 348104.72
B31: =Inputs!B12+(Inputs!D12-Inputs!B12)*BETAINV(RAND(),Model!H6,Model!I6) -> 2.2799567 | C31: =Inputs!E12+(Inputs!G12-Inputs!E12)*BETAINV(RAND(),Model!J6,Model!K6) -> 0.35330995 | D31: =(Inputs!H12+(Inputs!J12-Inputs!H12)*BETAINV(RAND(),Model!L6,Model!M6))*Inputs!$C$6 -> 13722.893 | E31: =B31*C31 -> 0.80553138 | F31: =RAND() -> 0.75672747 | G31: =IF(F31<EXP(-E31),0,IF(F31<EXP(-E31)*(1+E31),1,IF(F31<EXP(-E31)*(1+E31+E31^2/2),2,IF(F31<EXP(-E31)*(1+E31+E31^2/2+E31^3/6),3,4)))) -> 1 | H31: =G31*D31 -> 13722.893 | I31: =Inputs!B13+(Inputs!D13-Inputs!B13)*BETAINV(RAND(),Model!H7,Model!I7) -> 2.3084737 | J31: =Inputs!E13+(Inputs!G13-Inputs!E13)*BETAINV(RAND(),Model!J7,Model!K7) -> 0.19633403 | K31: =(Inputs!H13+(Inputs!J13-Inputs!H13)*BETAINV(RAND(),Model!L7,Model!M7))*Inputs!$C$6 -> 35172.656 | L31: =I31*J31 -> 0.45323194 | M31: =RAND() -> 0.9428562 | N31: =IF(M31<EXP(-L31),0,IF(M31<EXP(-L31)*(1+L31),1,IF(M31<EXP(-L31)*(1+L31+L31^2/2),2,IF(M31<EXP(-L31)*(1+L31+L31^2/2+L31^3/6),3,4)))) -> 2 | O31: =N31*K31 -> 70345.312 | P31: =Inputs!B14+(Inputs!D14-Inputs!B14)*BETAINV(RAND(),Model!H8,Model!I8) -> 0.26456012 | Q31: =Inputs!E14+(Inputs!G14-Inputs!E14)*BETAINV(RAND(),Model!J8,Model!K8) -> 0.74333569 | R31: =(Inputs!H14+(Inputs!J14-Inputs!H14)*BETAINV(RAND(),Model!L8,Model!M8))*Inputs!$C$6 -> 483990.11 | S31: =P31*Q31 -> 0.19665698 | T31: =RAND() -> 0.64187849 | U31: =IF(T31<EXP(-S31),0,IF(T31<EXP(-S31)*(1+S31),1,IF(T31<EXP(-S31)*(1+S31+S31^2/2),2,IF(T31<EXP(-S31)*(1+S31+S31^2/2+S31^3/6),3,4)))) -> 0 | V31: =U31*R31 -> 0 | W31: =Inputs!B15+(Inputs!D15-Inputs!B15)*BETAINV(RAND(),Model!H9,Model!I9) -> 1.5506365 | X31: =Inputs!E15+(Inputs!G15-Inputs!E15)*BETAINV(RAND(),Model!J9,Model!K9) -> 0.62954602 | Y31: =(Inputs!H15+(Inputs!J15-Inputs!H15)*BETAINV(RAND(),Model!L9,Model!M9))*Inputs!$C$6 -> 23471.276 | Z31: =W31*X31 -> 0.97619703 | AA31: =RAND() -> 0.099951013 | AB31: =IF(AA31<EXP(-Z31),0,IF(AA31<EXP(-Z31)*(1+Z31),1,IF(AA31<EXP(-Z31)*(1+Z31+Z31^2/2),2,IF(AA31<EXP(-Z31)*(1+Z31+Z31^2/2+Z31^3/6),3,4)))) -> 0 | AC31: =AB31*Y31 -> 0 | AD31: =Inputs!B16+(Inputs!D16-Inputs!B16)*BETAINV(RAND(),Model!H10,Model!I10) -> 0.45302993 | AE31: =Inputs!E16+(Inputs!G16-Inputs!E16)*BETAINV(RAND(),Model!J10,Model!K10) -> 0.47210693 | AF31: =(Inputs!H16+(Inputs!J16-Inputs!H16)*BETAINV(RAND(),Model!L10,Model!M10))*Inputs!$C$6 -> 86493.706 | AG31: =AD31*AE31 -> 0.21387857 | AH31: =RAND() -> 0.26630091 | AI31: =IF(AH31<EXP(-AG31),0,IF(AH31<EXP(-AG31)*(1+AG31),1,IF(AH31<EXP(-AG31)*(1+AG31+AG31^2/2),2,IF(AH31<EXP(-AG31)*(1+AG31+AG31^2/2+AG31^3/6),3,4)))) -> 0 | AJ31: =AI31*AF31 -> 0 | AK31: =H31+O31+V31+AC31+AJ31 -> 84068.205
B32: =Inputs!B12+(Inputs!D12-Inputs!B12)*BETAINV(RAND(),Model!H6,Model!I6) -> 4.730467 | C32: =Inputs!E12+(Inputs!G12-Inputs!E12)*BETAINV(RAND(),Model!J6,Model!K6) -> 0.44871843 | D32: =(Inputs!H12+(Inputs!J12-Inputs!H12)*BETAINV(RAND(),Model!L6,Model!M6))*Inputs!$C$6 -> 17903.21 | E32: =B32*C32 -> 2.1226478 | F32: =RAND() -> 0.19591197 | G32: =IF(F32<EXP(-E32),0,IF(F32<EXP(-E32)*(1+E32),1,IF(F32<EXP(-E32)*(1+E32+E32^2/2),2,IF(F32<EXP(-E32)*(1+E32+E32^2/2+E32^3/6),3,4)))) -> 1 | H32: =G32*D32 -> 17903.21 | I32: =Inputs!B13+(Inputs!D13-Inputs!B13)*BETAINV(RAND(),Model!H7,Model!I7) -> 2.1094856 | J32: =Inputs!E13+(Inputs!G13-Inputs!E13)*BETAINV(RAND(),Model!J7,Model!K7) -> 0.33614298 | K32: =(Inputs!H13+(Inputs!J13-Inputs!H13)*BETAINV(RAND(),Model!L7,Model!M7))*Inputs!$C$6 -> 45756.278 | L32: =I32*J32 -> 0.70908878 | M32: =RAND() -> 0.94828265 | N32: =IF(M32<EXP(-L32),0,IF(M32<EXP(-L32)*(1+L32),1,IF(M32<EXP(-L32)*(1+L32+L32^2/2),2,IF(M32<EXP(-L32)*(1+L32+L32^2/2+L32^3/6),3,4)))) -> 2 | O32: =N32*K32 -> 91512.556 | P32: =Inputs!B14+(Inputs!D14-Inputs!B14)*BETAINV(RAND(),Model!H8,Model!I8) -> 0.3204318 | Q32: =Inputs!E14+(Inputs!G14-Inputs!E14)*BETAINV(RAND(),Model!J8,Model!K8) -> 0.83250624 | R32: =(Inputs!H14+(Inputs!J14-Inputs!H14)*BETAINV(RAND(),Model!L8,Model!M8))*Inputs!$C$6 -> 313972.1 | S32: =P32*Q32 -> 0.26676147 | T32: =RAND() -> 0.14159673 | U32: =IF(T32<EXP(-S32),0,IF(T32<EXP(-S32)*(1+S32),1,IF(T32<EXP(-S32)*(1+S32+S32^2/2),2,IF(T32<EXP(-S32)*(1+S32+S32^2/2+S32^3/6),3,4)))) -> 0 | V32: =U32*R32 -> 0 | W32: =Inputs!B15+(Inputs!D15-Inputs!B15)*BETAINV(RAND(),Model!H9,Model!I9) -> 1.600573 | X32: =Inputs!E15+(Inputs!G15-Inputs!E15)*BETAINV(RAND(),Model!J9,Model!K9) -> 0.46329397 | Y32: =(Inputs!H15+(Inputs!J15-Inputs!H15)*BETAINV(RAND(),Model!L9,Model!M9))*Inputs!$C$6 -> 24544.86 | Z32: =W32*X32 -> 0.74153583 | AA32: =RAND() -> 0.13783785 | AB32: =IF(AA32<EXP(-Z32),0,IF(AA32<EXP(-Z32)*(1+Z32),1,IF(AA32<EXP(-Z32)*(1+Z32+Z32^2/2),2,IF(AA32<EXP(-Z32)*(1+Z32+Z32^2/2+Z32^3/6),3,4)))) -> 0 | AC32: =AB32*Y32 -> 0 | AD32: =Inputs!B16+(Inputs!D16-Inputs!B16)*BETAINV(RAND(),Model!H10,Model!I10) -> 0.43604754 | AE32: =Inputs!E16+(Inputs!G16-Inputs!E16)*BETAINV(RAND(),Model!J10,Model!K10) -> 0.58287427 | AF32: =(Inputs!H16+(Inputs!J16-Inputs!H16)*BETAINV(RAND(),Model!L10,Model!M10))*Inputs!$C$6 -> 96059.777 | AG32: =AD32*AE32 -> 0.25416089 | AH32: =RAND() -> 0.59090875 | AI32: =IF(AH32<EXP(-AG32),0,IF(AH32<EXP(-AG32)*(1+AG32),1,IF(AH32<EXP(-AG32)*(1+AG32+AG32^2/2),2,IF(AH32<EXP(-AG32)*(1+AG32+AG32^2/2+AG32^3/6),3,4)))) -> 0 | AJ32: =AI32*AF32 -> 0 | AK32: =H32+O32+V32+AC32+AJ32 -> 109415.77
B33: =Inputs!B12+(Inputs!D12-Inputs!B12)*BETAINV(RAND(),Model!H6,Model!I6) -> 3.4620237 | C33: =Inputs!E12+(Inputs!G12-Inputs!E12)*BETAINV(RAND(),Model!J6,Model!K6) -> 0.32987372 | D33: =(Inputs!H12+(Inputs!J12-Inputs!H12)*BETAINV(RAND(),Model!L6,Model!M6))*Inputs!$C$6 -> 54009.788 | E33: =B33*C33 -> 1.1420306 | F33: =RAND() -> 0.47233258 | G33: =IF(F33<EXP(-E33),0,IF(F33<EXP(-E33)*(1+E33),1,IF(F33<EXP(-E33)*(1+E33+E33^2/2),2,IF(F33<EXP(-E33)*(1+E33+E33^2/2+E33^3/6),3,4)))) -> 1 | H33: =G33*D33 -> 54009.788 | I33: =Inputs!B13+(Inputs!D13-Inputs!B13)*BETAINV(RAND(),Model!H7,Model!I7) -> 2.0127665 | J33: =Inputs!E13+(Inputs!G13-Inputs!E13)*BETAINV(RAND(),Model!J7,Model!K7) -> 0.27980767 | K33: =(Inputs!H13+(Inputs!J13-Inputs!H13)*BETAINV(RAND(),Model!L7,Model!M7))*Inputs!$C$6 -> 66290.608 | L33: =I33*J33 -> 0.56318752 | M33: =RAND() -> 0.84811572 | N33: =IF(M33<EXP(-L33),0,IF(M33<EXP(-L33)*(1+L33),1,IF(M33<EXP(-L33)*(1+L33+L33^2/2),2,IF(M33<EXP(-L33)*(1+L33+L33^2/2+L33^3/6),3,4)))) -> 1 | O33: =N33*K33 -> 66290.608 | P33: =Inputs!B14+(Inputs!D14-Inputs!B14)*BETAINV(RAND(),Model!H8,Model!I8) -> 0.27195106 | Q33: =Inputs!E14+(Inputs!G14-Inputs!E14)*BETAINV(RAND(),Model!J8,Model!K8) -> 0.60635559 | R33: =(Inputs!H14+(Inputs!J14-Inputs!H14)*BETAINV(RAND(),Model!L8,Model!M8))*Inputs!$C$6 -> 344707.54 | S33: =P33*Q33 -> 0.16489904 | T33: =RAND() -> 0.87146899 | U33: =IF(T33<EXP(-S33),0,IF(T33<EXP(-S33)*(1+S33),1,IF(T33<EXP(-S33)*(1+S33+S33^2/2),2,IF(T33<EXP(-S33)*(1+S33+S33^2/2+S33^3/6),3,4)))) -> 1 | V33: =U33*R33 -> 344707.54 | W33: =Inputs!B15+(Inputs!D15-Inputs!B15)*BETAINV(RAND(),Model!H9,Model!I9) -> 0.91694033 | X33: =Inputs!E15+(Inputs!G15-Inputs!E15)*BETAINV(RAND(),Model!J9,Model!K9) -> 0.36390458 | Y33: =(Inputs!H15+(Inputs!J15-Inputs!H15)*BETAINV(RAND(),Model!L9,Model!M9))*Inputs!$C$6 -> 36010.226 | Z33: =W33*X33 -> 0.33367879 | AA33: =RAND() -> 0.015706924 | AB33: =IF(AA33<EXP(-Z33),0,IF(AA33<EXP(-Z33)*(1+Z33),1,IF(AA33<EXP(-Z33)*(1+Z33+Z33^2/2),2,IF(AA33<EXP(-Z33)*(1+Z33+Z33^2/2+Z33^3/6),3,4)))) -> 0 | AC33: =AB33*Y33 -> 0 | AD33: =Inputs!B16+(Inputs!D16-Inputs!B16)*BETAINV(RAND(),Model!H10,Model!I10) -> 0.81356662 | AE33: =Inputs!E16+(Inputs!G16-Inputs!E16)*BETAINV(RAND(),Model!J10,Model!K10) -> 0.55927525 | AF33: =(Inputs!H16+(Inputs!J16-Inputs!H16)*BETAINV(RAND(),Model!L10,Model!M10))*Inputs!$C$6 -> 138852.94 | AG33: =AD33*AE33 -> 0.45500768 | AH33: =RAND() -> 0.057680498 | AI33: =IF(AH33<EXP(-AG33),0,IF(AH33<EXP(-AG33)*(1+AG33),1,IF(AH33<EXP(-AG33)*(1+AG33+AG33^2/2),2,IF(AH33<EXP(-AG33)*(1+AG33+AG33^2/2+AG33^3/6),3,4)))) -> 0 | AJ33: =AI33*AF33 -> 0 | AK33: =H33+O33+V33+AC33+AJ33 -> 465007.94
B34: =Inputs!B12+(Inputs!D12-Inputs!B12)*BETAINV(RAND(),Model!H6,Model!I6) -> 3.3746109 | C34: =Inputs!E12+(Inputs!G12-Inputs!E12)*BETAINV(RAND(),Model!J6,Model!K6) -> 0.26604206 | D34: =(Inputs!H12+(Inputs!J12-Inputs!H12)*BETAINV(RAND(),Model!L6,Model!M6))*Inputs!$C$6 -> 17979.335 | E34: =B34*C34 -> 0.89778846 | F34: =RAND() -> 0.47447811 | G34: =IF(F34<EXP(-E34),0,IF(F34<EXP(-E34)*(1+E34),1,IF(F34<EXP(-E34)*(1+E34+E34^2/2),2,IF(F34<EXP(-E34)*(1+E34+E34^2/2+E34^3/6),3,4)))) -> 1 | H34: =G34*D34 -> 17979.335 | I34: =Inputs!B13+(Inputs!D13-Inputs!B13)*BETAINV(RAND(),Model!H7,Model!I7) -> 1.2281476 | J34: =Inputs!E13+(Inputs!G13-Inputs!E13)*BETAINV(RAND(),Model!J7,Model!K7) -> 0.30122494 | K34: =(Inputs!H13+(Inputs!J13-Inputs!H13)*BETAINV(RAND(),Model!L7,Model!M7))*Inputs!$C$6 -> 54482.024 | L34: =I34*J34 -> 0.3699487 | M34: =RAND() -> 0.74392326 | N34: =IF(M34<EXP(-L34),0,IF(M34<EXP(-L34)*(1+L34),1,IF(M34<EXP(-L34)*(1+L34+L34^2/2),2,IF(M34<EXP(-L34)*(1+L34+L34^2/2+L34^3/6),3,4)))) -> 1 | O34: =N34*K34 -> 54482.024 | P34: =Inputs!B14+(Inputs!D14-Inputs!B14)*BETAINV(RAND(),Model!H8,Model!I8) -> 0.34971169 | Q34: =Inputs!E14+(Inputs!G14-Inputs!E14)*BETAINV(RAND(),Model!J8,Model!K8) -> 0.40483611 | R34: =(Inputs!H14+(Inputs!J14-Inputs!H14)*BETAINV(RAND(),Model!L8,Model!M8))*Inputs!$C$6 -> 227629.08 | S34: =P34*Q34 -> 0.14157592 | T34: =RAND() -> 0.53064052 | U34: =IF(T34<EXP(-S34),0,IF(T34<EXP(-S34)*(1+S34),1,IF(T34<EXP(-S34)*(1+S34+S34^2/2),2,IF(T34<EXP(-S34)*(1+S34+S34^2/2+S34^3/6),3,4)))) -> 0 | V34: =U34*R34 -> 0 | W34: =Inputs!B15+(Inputs!D15-Inputs!B15)*BETAINV(RAND(),Model!H9,Model!I9) -> 1.7408909 | X34: =Inputs!E15+(Inputs!G15-Inputs!E15)*BETAINV(RAND(),Model!J9,Model!K9) -> 0.42216855 | Y34: =(Inputs!H15+(Inputs!J15-Inputs!H15)*BETAINV(RAND(),Model!L9,Model!M9))*Inputs!$C$6 -> 28323.088 | Z34: =W34*X34 -> 0.73494937 | AA34: =RAND() -> 0.10293607 | AB34: =IF(AA34<EXP(-Z34),0,IF(AA34<EXP(-Z34)*(1+Z34),1,IF(AA34<EXP(-Z34)*(1+Z34+Z34^2/2),2,IF(AA34<EXP(-Z34)*(1+Z34+Z34^2/2+Z34^3/6),3,4)))) -> 0 | AC34: =AB34*Y34 -> 0 | AD34: =Inputs!B16+(Inputs!D16-Inputs!B16)*BETAINV(RAND(),Model!H10,Model!I10) -> 0.42512543 | AE34: =Inputs!E16+(Inputs!G16-Inputs!E16)*BETAINV(RAND(),Model!J10,Model!K10) -> 0.69151436 | AF34: =(Inputs!H16+(Inputs!J16-Inputs!H16)*BETAINV(RAND(),Model!L10,Model!M10))*Inputs!$C$6 -> 83154.427 | AG34: =AD34*AE34 -> 0.29398034 | AH34: =RAND() -> 0.18332021 | AI34: =IF(AH34<EXP(-AG34),0,IF(AH34<EXP(-AG34)*(1+AG34),1,IF(AH34<EXP(-AG34)*(1+AG34+AG34^2/2),2,IF(AH34<EXP(-AG34)*(1+AG34+AG34^2/2+AG34^3/6),3,4)))) -> 0 | AJ34: =AI34*AF34 -> 0 | AK34: =H34+O34+V34+AC34+AJ34 -> 72461.359
B35: =Inputs!B12+(Inputs!D12-Inputs!B12)*BETAINV(RAND(),Model!H6,Model!I6) -> 1.8627586 | C35: =Inputs!E12+(Inputs!G12-Inputs!E12)*BETAINV(RAND(),Model!J6,Model!K6) -> 0.30581661 | D35: =(Inputs!H12+(Inputs!J12-Inputs!H12)*BETAINV(RAND(),Model!L6,Model!M6))*Inputs!$C$6 -> 10903.828 | E35: =B35*C35 -> 0.56966254 | F35: =RAND() -> 0.70779857 | G35: =IF(F35<EXP(-E35),0,IF(F35<EXP(-E35)*(1+E35),1,IF(F35<EXP(-E35)*(1+E35+E35^2/2),2,IF(F35<EXP(-E35)*(1+E35+E35^2/2+E35^3/6),3,4)))) -> 1 | H35: =G35*D35 -> 10903.828 | I35: =Inputs!B13+(Inputs!D13-Inputs!B13)*BETAINV(RAND(),Model!H7,Model!I7) -> 2.6713739 | J35: =Inputs!E13+(Inputs!G13-Inputs!E13)*BETAINV(RAND(),Model!J7,Model!K7) -> 0.47495378 | K35: =(Inputs!H13+(Inputs!J13-Inputs!H13)*BETAINV(RAND(),Model!L7,Model!M7))*Inputs!$C$6 -> 20774.8 | L35: =I35*J35 -> 1.2687791 | M35: =RAND() -> 0.55485492 | N35: =IF(M35<EXP(-L35),0,IF(M35<EXP(-L35)*(1+L35),1,IF(M35<EXP(-L35)*(1+L35+L35^2/2),2,IF(M35<EXP(-L35)*(1+L35+L35^2/2+L35^3/6),3,4)))) -> 1 | O35: =N35*K35 -> 20774.8 | P35: =Inputs!B14+(Inputs!D14-Inputs!B14)*BETAINV(RAND(),Model!H8,Model!I8) -> 0.27472086 | Q35: =Inputs!E14+(Inputs!G14-Inputs!E14)*BETAINV(RAND(),Model!J8,Model!K8) -> 0.6686693 | R35: =(Inputs!H14+(Inputs!J14-Inputs!H14)*BETAINV(RAND(),Model!L8,Model!M8))*Inputs!$C$6 -> 545765.34 | S35: =P35*Q35 -> 0.18369741 | T35: =RAND() -> 0.50914537 | U35: =IF(T35<EXP(-S35),0,IF(T35<EXP(-S35)*(1+S35),1,IF(T35<EXP(-S35)*(1+S35+S35^2/2),2,IF(T35<EXP(-S35)*(1+S35+S35^2/2+S35^3/6),3,4)))) -> 0 | V35: =U35*R35 -> 0 | W35: =Inputs!B15+(Inputs!D15-Inputs!B15)*BETAINV(RAND(),Model!H9,Model!I9) -> 0.8410343 | X35: =Inputs!E15+(Inputs!G15-Inputs!E15)*BETAINV(RAND(),Model!J9,Model!K9) -> 0.45858011 | Y35: =(Inputs!H15+(Inputs!J15-Inputs!H15)*BETAINV(RAND(),Model!L9,Model!M9))*Inputs!$C$6 -> 20917.994 | Z35: =W35*X35 -> 0.3856816 | AA35: =RAND() -> 0.38136309 | AB35: =IF(AA35<EXP(-Z35),0,IF(AA35<EXP(-Z35)*(1+Z35),1,IF(AA35<EXP(-Z35)*(1+Z35+Z35^2/2),2,IF(AA35<EXP(-Z35)*(1+Z35+Z35^2/2+Z35^3/6),3,4)))) -> 0 | AC35: =AB35*Y35 -> 0 | AD35: =Inputs!B16+(Inputs!D16-Inputs!B16)*BETAINV(RAND(),Model!H10,Model!I10) -> 1.0835212 | AE35: =Inputs!E16+(Inputs!G16-Inputs!E16)*BETAINV(RAND(),Model!J10,Model!K10) -> 0.68405818 | AF35: =(Inputs!H16+(Inputs!J16-Inputs!H16)*BETAINV(RAND(),Model!L10,Model!M10))*Inputs!$C$6 -> 67442.567 | AG35: =AD35*AE35 -> 0.74119155 | AH35: =RAND() -> 0.37137899 | AI35: =IF(AH35<EXP(-AG35),0,IF(AH35<EXP(-AG35)*(1+AG35),1,IF(AH35<EXP(-AG35)*(1+AG35+AG35^2/2),2,IF(AH35<EXP(-AG35)*(1+AG35+AG35^2/2+AG35^3/6),3,4)))) -> 0 | AJ35: =AI35*AF35 -> 0 | AK35: =H35+O35+V35+AC35+AJ35 -> 31678.628
B36: =Inputs!B12+(Inputs!D12-Inputs!B12)*BETAINV(RAND(),Model!H6,Model!I6) -> 1.8098803 | C36: =Inputs!E12+(Inputs!G12-Inputs!E12)*BETAINV(RAND(),Model!J6,Model!K6) -> 0.31318456 | D36: =(Inputs!H12+(Inputs!J12-Inputs!H12)*BETAINV(RAND(),Model!L6,Model!M6))*Inputs!$C$6 -> 51925.001 | E36: =B36*C36 -> 0.56682655 | F36: =RAND() -> 0.77794021 | G36: =IF(F36<EXP(-E36),0,IF(F36<EXP(-E36)*(1+E36),1,IF(F36<EXP(-E36)*(1+E36+E36^2/2),2,IF(F36<EXP(-E36)*(1+E36+E36^2/2+E36^3/6),3,4)))) -> 1 | H36: =G36*D36 -> 51925.001 | I36: =Inputs!B13+(Inputs!D13-Inputs!B13)*BETAINV(RAND(),Model!H7,Model!I7) -> 0.64785875 | J36: =Inputs!E13+(Inputs!G13-Inputs!E13)*BETAINV(RAND(),Model!J7,Model!K7) -> 0.40823439 | K36: =(Inputs!H13+(Inputs!J13-Inputs!H13)*BETAINV(RAND(),Model!L7,Model!M7))*Inputs!$C$6 -> 33287.267 | L36: =I36*J36 -> 0.26447822 | M36: =RAND() -> 0.12341629 | N36: =IF(M36<EXP(-L36),0,IF(M36<EXP(-L36)*(1+L36),1,IF(M36<EXP(-L36)*(1+L36+L36^2/2),2,IF(M36<EXP(-L36)*(1+L36+L36^2/2+L36^3/6),3,4)))) -> 0 | O36: =N36*K36 -> 0 | P36: =Inputs!B14+(Inputs!D14-Inputs!B14)*BETAINV(RAND(),Model!H8,Model!I8) -> 0.25454985 | Q36: =Inputs!E14+(Inputs!G14-Inputs!E14)*BETAINV(RAND(),Model!J8,Model!K8) -> 0.59698047 | R36: =(Inputs!H14+(Inputs!J14-Inputs!H14)*BETAINV(RAND(),Model!L8,Model!M8))*Inputs!$C$6 -> 492091.34 | S36: =P36*Q36 -> 0.15196129 | T36: =RAND() -> 0.21588006 | U36: =IF(T36<EXP(-S36),0,IF(T36<EXP(-S36)*(1+S36),1,IF(T36<EXP(-S36)*(1+S36+S36^2/2),2,IF(T36<EXP(-S36)*(1+S36+S36^2/2+S36^3/6),3,4)))) -> 0 | V36: =U36*R36 -> 0 | W36: =Inputs!B15+(Inputs!D15-Inputs!B15)*BETAINV(RAND(),Model!H9,Model!I9) -> 0.88784299 | X36: =Inputs!E15+(Inputs!G15-Inputs!E15)*BETAINV(RAND(),Model!J9,Model!K9) -> 0.47065988 | Y36: =(Inputs!H15+(Inputs!J15-Inputs!H15)*BETAINV(RAND(),Model!L9,Model!M9))*Inputs!$C$6 -> 18754.19 | Z36: =W36*X36 -> 0.41787208 | AA36: =RAND() -> 0.20074579 | AB36: =IF(AA36<EXP(-Z36),0,IF(AA36<EXP(-Z36)*(1+Z36),1,IF(AA36<EXP(-Z36)*(1+Z36+Z36^2/2),2,IF(AA36<EXP(-Z36)*(1+Z36+Z36^2/2+Z36^3/6),3,4)))) -> 0 | AC36: =AB36*Y36 -> 0 | AD36: =Inputs!B16+(Inputs!D16-Inputs!B16)*BETAINV(RAND(),Model!H10,Model!I10) -> 0.57336129 | AE36: =Inputs!E16+(Inputs!G16-Inputs!E16)*BETAINV(RAND(),Model!J10,Model!K10) -> 0.61678107 | AF36: =(Inputs!H16+(Inputs!J16-Inputs!H16)*BETAINV(RAND(),Model!L10,Model!M10))*Inputs!$C$6 -> 114901.83 | AG36: =AD36*AE36 -> 0.35363839 | AH36: =RAND() -> 0.74672608 | AI36: =IF(AH36<EXP(-AG36),0,IF(AH36<EXP(-AG36)*(1+AG36),1,IF(AH36<EXP(-AG36)*(1+AG36+AG36^2/2),2,IF(AH36<EXP(-AG36)*(1+AG36+AG36^2/2+AG36^3/6),3,4)))) -> 1 | AJ36: =AI36*AF36 -> 114901.83 | AK36: =H36+O36+V36+AC36+AJ36 -> 166826.83
B37: =Inputs!B12+(Inputs!D12-Inputs!B12)*BETAINV(RAND(),Model!H6,Model!I6) -> 2.0276771 | C37: =Inputs!E12+(Inputs!G12-Inputs!E12)*BETAINV(RAND(),Model!J6,Model!K6) -> 0.29029332 | D37: =(Inputs!H12+(Inputs!J12-Inputs!H12)*BETAINV(RAND(),Model!L6,Model!M6))*Inputs!$C$6 -> 12707.037 | E37: =B37*C37 -> 0.58862114 | F37: =RAND() -> 0.749451 | G37: =IF(F37<EXP(-E37),0,IF(F37<EXP(-E37)*(1+E37),1,IF(F37<EXP(-E37)*(1+E37+E37^2/2),2,IF(F37<EXP(-E37)*(1+E37+E37^2/2+E37^3/6),3,4)))) -> 1 | H37: =G37*D37 -> 12707.037 | I37: =Inputs!B13+(Inputs!D13-Inputs!B13)*BETAINV(RAND(),Model!H7,Model!I7) -> 3.046895 | J37: =Inputs!E13+(Inputs!G13-Inputs!E13)*BETAINV(RAND(),Model!J7,Model!K7) -> 0.26252023 | K37: =(Inputs!H13+(Inputs!J13-Inputs!H13)*BETAINV(RAND(),Model!L7,Model!M7))*Inputs!$C$6 -> 64875.602 | L37: =I37*J37 -> 0.79987157 | M37: =RAND() -> 0.33667078 | N37: =IF(M37<EXP(-L37),0,IF(M37<EXP(-L37)*(1+L37),1,IF(M37<EXP(-L37)*(1+L37+L37^2/2),2,IF(M37<EXP(-L37)*(1+L37+L37^2/2+L37^3/6),3,4)))) -> 0 | O37: =N37*K37 -> 0 | P37: =Inputs!B14+(Inputs!D14-Inputs!B14)*BETAINV(RAND(),Model!H8,Model!I8) -> 0.33995045 | Q37: =Inputs!E14+(Inputs!G14-Inputs!E14)*BETAINV(RAND(),Model!J8,Model!K8) -> 0.70877743 | R37: =(Inputs!H14+(Inputs!J14-Inputs!H14)*BETAINV(RAND(),Model!L8,Model!M8))*Inputs!$C$6 -> 409457.53 | S37: =P37*Q37 -> 0.2409492 | T37: =RAND() -> 0.46061255 | U37: =IF(T37<EXP(-S37),0,IF(T37<EXP(-S37)*(1+S37),1,IF(T37<EXP(-S37)*(1+S37+S37^2/2),2,IF(T37<EXP(-S37)*(1+S37+S37^2/2+S37^3/6),3,4)))) -> 0 | V37: =U37*R37 -> 0 | W37: =Inputs!B15+(Inputs!D15-Inputs!B15)*BETAINV(RAND(),Model!H9,Model!I9) -> 1.1237272 | X37: =Inputs!E15+(Inputs!G15-Inputs!E15)*BETAINV(RAND(),Model!J9,Model!K9) -> 0.3982973 | Y37: =(Inputs!H15+(Inputs!J15-Inputs!H15)*BETAINV(RAND(),Model!L9,Model!M9))*Inputs!$C$6 -> 22745.522 | Z37: =W37*X37 -> 0.4475775 | AA37: =RAND() -> 0.9218976 | AB37: =IF(AA37<EXP(-Z37),0,IF(AA37<EXP(-Z37)*(1+Z37),1,IF(AA37<EXP(-Z37)*(1+Z37+Z37^2/2),2,IF(AA37<EXP(-Z37)*(1+Z37+Z37^2/2+Z37^3/6),3,4)))) -> 1 | AC37: =AB37*Y37 -> 22745.522 | AD37: =Inputs!B16+(Inputs!D16-Inputs!B16)*BETAINV(RAND(),Model!H10,Model!I10) -> 0.64665944 | AE37: =Inputs!E16+(Inputs!G16-Inputs!E16)*BETAINV(RAND(),Model!J10,Model!K10) -> 0.50989848 | AF37: =(Inputs!H16+(Inputs!J16-Inputs!H16)*BETAINV(RAND(),Model!L10,Model!M10))*Inputs!$C$6 -> 44085.584 | AG37: =AD37*AE37 -> 0.32973067 | AH37: =RAND() -> 0.37068965 | AI37: =IF(AH37<EXP(-AG37),0,IF(AH37<EXP(-AG37)*(1+AG37),1,IF(AH37<EXP(-AG37)*(1+AG37+AG37^2/2),2,IF(AH37<EXP(-AG37)*(1+AG37+AG37^2/2+AG37^3/6),3,4)))) -> 0 | AJ37: =AI37*AF37 -> 0 | AK37: =H37+O37+V37+AC37+AJ37 -> 35452.56
B38: =Inputs!B12+(Inputs!D12-Inputs!B12)*BETAINV(RAND(),Model!H6,Model!I6) -> 4.6027993 | C38: =Inputs!E12+(Inputs!G12-Inputs!E12)*BETAINV(RAND(),Model!J6,Model!K6) -> 0.32452367 | D38: =(Inputs!H12+(Inputs!J12-Inputs!H12)*BETAINV(RAND(),Model!L6,Model!M6))*Inputs!$C$6 -> 28159.242 | E38: =B38*C38 -> 1.4937173 | F38: =RAND() -> 0.52924556 | G38: =IF(F38<EXP(-E38),0,IF(F38<EXP(-E38)*(1+E38),1,IF(F38<EXP(-E38)*(1+E38+E38^2/2),2,IF(F38<EXP(-E38)*(1+E38+E38^2/2+E38^3/6),3,4)))) -> 1 | H38: =G38*D38 -> 28159.242 | I38: =Inputs!B13+(Inputs!D13-Inputs!B13)*BETAINV(RAND(),Model!H7,Model!I7) -> 3.7849762 | J38: =Inputs!E13+(Inputs!G13-Inputs!E13)*BETAINV(RAND(),Model!J7,Model!K7) -> 0.27000924 | K38: =(Inputs!H13+(Inputs!J13-Inputs!H13)*BETAINV(RAND(),Model!L7,Model!M7))*Inputs!$C$6 -> 50137.707 | L38: =I38*J38 -> 1.0219785 | M38: =RAND() -> 0.38213607 | N38: =IF(M38<EXP(-L38),0,IF(M38<EXP(-L38)*(1+L38),1,IF(M38<EXP(-L38)*(1+L38+L38^2/2),2,IF(M38<EXP(-L38)*(1+L38+L38^2/2+L38^3/6),3,4)))) -> 1 | O38: =N38*K38 -> 50137.707 | P38: =Inputs!B14+(Inputs!D14-Inputs!B14)*BETAINV(RAND(),Model!H8,Model!I8) -> 0.32920738 | Q38: =Inputs!E14+(Inputs!G14-Inputs!E14)*BETAINV(RAND(),Model!J8,Model!K8) -> 0.71126247 | R38: =(Inputs!H14+(Inputs!J14-Inputs!H14)*BETAINV(RAND(),Model!L8,Model!M8))*Inputs!$C$6 -> 430565.52 | S38: =P38*Q38 -> 0.23415285 | T38: =RAND() -> 0.27893929 | U38: =IF(T38<EXP(-S38),0,IF(T38<EXP(-S38)*(1+S38),1,IF(T38<EXP(-S38)*(1+S38+S38^2/2),2,IF(T38<EXP(-S38)*(1+S38+S38^2/2+S38^3/6),3,4)))) -> 0 | V38: =U38*R38 -> 0 | W38: =Inputs!B15+(Inputs!D15-Inputs!B15)*BETAINV(RAND(),Model!H9,Model!I9) -> 1.5540111 | X38: =Inputs!E15+(Inputs!G15-Inputs!E15)*BETAINV(RAND(),Model!J9,Model!K9) -> 0.36895582 | Y38: =(Inputs!H15+(Inputs!J15-Inputs!H15)*BETAINV(RAND(),Model!L9,Model!M9))*Inputs!$C$6 -> 29713.648 | Z38: =W38*X38 -> 0.57336144 | AA38: =RAND() -> 0.47090172 | AB38: =IF(AA38<EXP(-Z38),0,IF(AA38<EXP(-Z38)*(1+Z38),1,IF(AA38<EXP(-Z38)*(1+Z38+Z38^2/2),2,IF(AA38<EXP(-Z38)*(1+Z38+Z38^2/2+Z38^3/6),3,4)))) -> 0 | AC38: =AB38*Y38 -> 0 | AD38: =Inputs!B16+(Inputs!D16-Inputs!B16)*BETAINV(RAND(),Model!H10,Model!I10) -> 0.94096242 | AE38: =Inputs!E16+(Inputs!G16-Inputs!E16)*BETAINV(RAND(),Model!J10,Model!K10) -> 0.61076337 | AF38: =(Inputs!H16+(Inputs!J16-Inputs!H16)*BETAINV(RAND(),Model!L10,Model!M10))*Inputs!$C$6 -> 93075.51 | AG38: =AD38*AE38 -> 0.57470538 | AH38: =RAND() -> 0.73293397 | AI38: =IF(AH38<EXP(-AG38),0,IF(AH38<EXP(-AG38)*(1+AG38),1,IF(AH38<EXP(-AG38)*(1+AG38+AG38^2/2),2,IF(AH38<EXP(-AG38)*(1+AG38+AG38^2/2+AG38^3/6),3,4)))) -> 1 | AJ38: =AI38*AF38 -> 93075.51 | AK38: =H38+O38+V38+AC38+AJ38 -> 171372.46
B39: =Inputs!B12+(Inputs!D12-Inputs!B12)*BETAINV(RAND(),Model!H6,Model!I6) -> 4.8250248 | C39: =Inputs!E12+(Inputs!G12-Inputs!E12)*BETAINV(RAND(),Model!J6,Model!K6) -> 0.3115258 | D39: =(Inputs!H12+(Inputs!J12-Inputs!H12)*BETAINV(RAND(),Model!L6,Model!M6))*Inputs!$C$6 -> 42939.996 | E39: =B39*C39 -> 1.5031197 | F39: =RAND() -> 0.040412499 | G39: =IF(F39<EXP(-E39),0,IF(F39<EXP(-E39)*(1+E39),1,IF(F39<EXP(-E39)*(1+E39+E39^2/2),2,IF(F39<EXP(-E39)*(1+E39+E39^2/2+E39^3/6),3,4)))) -> 0 | H39: =G39*D39 -> 0 | I39: =Inputs!B13+(Inputs!D13-Inputs!B13)*BETAINV(RAND(),Model!H7,Model!I7) -> 2.4197672 | J39: =Inputs!E13+(Inputs!G13-Inputs!E13)*BETAINV(RAND(),Model!J7,Model!K7) -> 0.19871667 | K39: =(Inputs!H13+(Inputs!J13-Inputs!H13)*BETAINV(RAND(),Model!L7,Model!M7))*Inputs!$C$6 -> 35943.583 | L39: =I39*J39 -> 0.48084807 | M39: =RAND() -> 0.28976169 | N39: =IF(M39<EXP(-L39),0,IF(M39<EXP(-L39)*(1+L39),1,IF(M39<EXP(-L39)*(1+L39+L39^2/2),2,IF(M39<EXP(-L39)*(1+L39+L39^2/2+L39^3/6),3,4)))) -> 0 | O39: =N39*K39 -> 0 | P39: =Inputs!B14+(Inputs!D14-Inputs!B14)*BETAINV(RAND(),Model!H8,Model!I8) -> 0.16555259 | Q39: =Inputs!E14+(Inputs!G14-Inputs!E14)*BETAINV(RAND(),Model!J8,Model!K8) -> 0.56607564 | R39: =(Inputs!H14+(Inputs!J14-Inputs!H14)*BETAINV(RAND(),Model!L8,Model!M8))*Inputs!$C$6 -> 308680.29 | S39: =P39*Q39 -> 0.093715286 | T39: =RAND() -> 0.53284628 | U39: =IF(T39<EXP(-S39),0,IF(T39<EXP(-S39)*(1+S39),1,IF(T39<EXP(-S39)*(1+S39+S39^2/2),2,IF(T39<EXP(-S39)*(1+S39+S39^2/2+S39^3/6),3,4)))) -> 0 | V39: =U39*R39 -> 0 | W39: =Inputs!B15+(Inputs!D15-Inputs!B15)*BETAINV(RAND(),Model!H9,Model!I9) -> 2.0518459 | X39: =Inputs!E15+(Inputs!G15-Inputs!E15)*BETAINV(RAND(),Model!J9,Model!K9) -> 0.38245259 | Y39: =(Inputs!H15+(Inputs!J15-Inputs!H15)*BETAINV(RAND(),Model!L9,Model!M9))*Inputs!$C$6 -> 41722.558 | Z39: =W39*X39 -> 0.78473378 | AA39: =RAND() -> 0.62059164 | AB39: =IF(AA39<EXP(-Z39),0,IF(AA39<EXP(-Z39)*(1+Z39),1,IF(AA39<EXP(-Z39)*(1+Z39+Z39^2/2),2,IF(AA39<EXP(-Z39)*(1+Z39+Z39^2/2+Z39^3/6),3,4)))) -> 1 | AC39: =AB39*Y39 -> 41722.558 | AD39: =Inputs!B16+(Inputs!D16-Inputs!B16)*BETAINV(RAND(),Model!H10,Model!I10) -> 0.8543102 | AE39: =Inputs!E16+(Inputs!G16-Inputs!E16)*BETAINV(RAND(),Model!J10,Model!K10) -> 0.53785898 | AF39: =(Inputs!H16+(Inputs!J16-Inputs!H16)*BETAINV(RAND(),Model!L10,Model!M10))*Inputs!$C$6 -> 106584.58 | AG39: =AD39*AE39 -> 0.45949841 | AH39: =RAND() -> 0.55287772 | AI39: =IF(AH39<EXP(-AG39),0,IF(AH39<EXP(-AG39)*(1+AG39),1,IF(AH39<EXP(-AG39)*(1+AG39+AG39^2/2),2,IF(AH39<EXP(-AG39)*(1+AG39+AG39^2/2+AG39^3/6),3,4)))) -> 0 | AJ39: =AI39*AF39 -> 0 | AK39: =H39+O39+V39+AC39+AJ39 -> 41722.558
B40: =Inputs!B12+(Inputs!D12-Inputs!B12)*BETAINV(RAND(),Model!H6,Model!I6) -> 2.365436 | C40: =Inputs!E12+(Inputs!G12-Inputs!E12)*BETAINV(RAND(),Model!J6,Model!K6) -> 0.18755303 | D40: =(Inputs!H12+(Inputs!J12-Inputs!H12)*BETAINV(RAND(),Model!L6,Model!M6))*Inputs!$C$6 -> 21601.687 | E40: =B40*C40 -> 0.4436447 | F40: =RAND() -> 0.060570975 | G40: =IF(F40<EXP(-E40),0,IF(F40<EXP(-E40)*(1+E40),1,IF(F40<EXP(-E40)*(1+E40+E40^2/2),2,IF(F40<EXP(-E40)*(1+E40+E40^2/2+E40^3/6),3,4)))) -> 0 | H40: =G40*D40 -> 0 | I40: =Inputs!B13+(Inputs!D13-Inputs!B13)*BETAINV(RAND(),Model!H7,Model!I7) -> 1.7573681 | J40: =Inputs!E13+(Inputs!G13-Inputs!E13)*BETAINV(RAND(),Model!J7,Model!K7) -> 0.17047473 | K40: =(Inputs!H13+(Inputs!J13-Inputs!H13)*BETAINV(RAND(),Model!L7,Model!M7))*Inputs!$C$6 -> 66480.82 | L40: =I40*J40 -> 0.29958686 | M40: =RAND() -> 0.68918341 | N40: =IF(M40<EXP(-L40),0,IF(M40<EXP(-L40)*(1+L40),1,IF(M40<EXP(-L40)*(1+L40+L40^2/2),2,IF(M40<EXP(-L40)*(1+L40+L40^2/2+L40^3/6),3,4)))) -> 0 | O40: =N40*K40 -> 0 | P40: =Inputs!B14+(Inputs!D14-Inputs!B14)*BETAINV(RAND(),Model!H8,Model!I8) -> 0.60454179 | Q40: =Inputs!E14+(Inputs!G14-Inputs!E14)*BETAINV(RAND(),Model!J8,Model!K8) -> 0.58342714 | R40: =(Inputs!H14+(Inputs!J14-Inputs!H14)*BETAINV(RAND(),Model!L8,Model!M8))*Inputs!$C$6 -> 252179.25 | S40: =P40*Q40 -> 0.35270609 | T40: =RAND() -> 0.51244111 | U40: =IF(T40<EXP(-S40),0,IF(T40<EXP(-S40)*(1+S40),1,IF(T40<EXP(-S40)*(1+S40+S40^2/2),2,IF(T40<EXP(-S40)*(1+S40+S40^2/2+S40^3/6),3,4)))) -> 0 | V40: =U40*R40 -> 0 | W40: =Inputs!B15+(Inputs!D15-Inputs!B15)*BETAINV(RAND(),Model!H9,Model!I9) -> 1.4062945 | X40: =Inputs!E15+(Inputs!G15-Inputs!E15)*BETAINV(RAND(),Model!J9,Model!K9) -> 0.41456126 | Y40: =(Inputs!H15+(Inputs!J15-Inputs!H15)*BETAINV(RAND(),Model!L9,Model!M9))*Inputs!$C$6 -> 47882.938 | Z40: =W40*X40 -> 0.58299523 | AA40: =RAND() -> 0.40201456 | AB40: =IF(AA40<EXP(-Z40),0,IF(AA40<EXP(-Z40)*(1+Z40),1,IF(AA40<EXP(-Z40)*(1+Z40+Z40^2/2),2,IF(AA40<EXP(-Z40)*(1+Z40+Z40^2/2+Z40^3/6),3,4)))) -> 0 | AC40: =AB40*Y40 -> 0 | AD40: =Inputs!B16+(Inputs!D16-Inputs!B16)*BETAINV(RAND(),Model!H10,Model!I10) -> 0.63226891 | AE40: =Inputs!E16+(Inputs!G16-Inputs!E16)*BETAINV(RAND(),Model!J10,Model!K10) -> 0.74741379 | AF40: =(Inputs!H16+(Inputs!J16-Inputs!H16)*BETAINV(RAND(),Model!L10,Model!M10))*Inputs!$C$6 -> 121916.6 | AG40: =AD40*AE40 -> 0.4725665 | AH40: =RAND() -> 0.73509334 | AI40: =IF(AH40<EXP(-AG40),0,IF(AH40<EXP(-AG40)*(1+AG40),1,IF(AH40<EXP(-AG40)*(1+AG40+AG40^2/2),2,IF(AH40<EXP(-AG40)*(1+AG40+AG40^2/2+AG40^3/6),3,4)))) -> 1 | AJ40: =AI40*AF40 -> 121916.6 | AK40: =H40+O40+V40+AC40+AJ40 -> 121916.6
B41: =Inputs!B12+(Inputs!D12-Inputs!B12)*BETAINV(RAND(),Model!H6,Model!I6) -> 3.6417433 | C41: =Inputs!E12+(Inputs!G12-Inputs!E12)*BETAINV(RAND(),Model!J6,Model!K6) -> 0.31773339 | D41: =(Inputs!H12+(Inputs!J12-Inputs!H12)*BETAINV(RAND(),Model!L6,Model!M6))*Inputs!$C$6 -> 28574.424 | E41: =B41*C41 -> 1.1571035 | F41: =RAND() -> 0.80622243 | G41: =IF(F41<EXP(-E41),0,IF(F41<EXP(-E41)*(1+E41),1,IF(F41<EXP(-E41)*(1+E41+E41^2/2),2,IF(F41<EXP(-E41)*(1+E41+E41^2/2+E41^3/6),3,4)))) -> 2 | H41: =G41*D41 -> 57148.848 | I41: =Inputs!B13+(Inputs!D13-Inputs!B13)*BETAINV(RAND(),Model!H7,Model!I7) -> 2.8544767 | J41: =Inputs!E13+(Inputs!G13-Inputs!E13)*BETAINV(RAND(),Model!J7,Model!K7) -> 0.39770757 | K41: =(Inputs!H13+(Inputs!J13-Inputs!H13)*BETAINV(RAND(),Model!L7,Model!M7))*Inputs!$C$6 -> 35136.622 | L41: =I41*J41 -> 1.135247 | M41: =RAND() -> 0.32468726 | N41: =IF(M41<EXP(-L41),0,IF(M41<EXP(-L41)*(1+L41),1,IF(M41<EXP(-L41)*(1+L41+L41^2/2),2,IF(M41<EXP(-L41)*(1+L41+L41^2/2+L41^3/6),3,4)))) -> 1 | O41: =N41*K41 -> 35136.622 | P41: =Inputs!B14+(Inputs!D14-Inputs!B14)*BETAINV(RAND(),Model!H8,Model!I8) -> 0.33634116 | Q41: =Inputs!E14+(Inputs!G14-Inputs!E14)*BETAINV(RAND(),Model!J8,Model!K8) -> 0.60580322 | R41: =(Inputs!H14+(Inputs!J14-Inputs!H14)*BETAINV(RAND(),Model!L8,Model!M8))*Inputs!$C$6 -> 313959.04 | S41: =P41*Q41 -> 0.20375656 | T41: =RAND() -> 0.70238055 | U41: =IF(T41<EXP(-S41),0,IF(T41<EXP(-S41)*(1+S41),1,IF(T41<EXP(-S41)*(1+S41+S41^2/2),2,IF(T41<EXP(-S41)*(1+S41+S41^2/2+S41^3/6),3,4)))) -> 0 | V41: =U41*R41 -> 0 | W41: =Inputs!B15+(Inputs!D15-Inputs!B15)*BETAINV(RAND(),Model!H9,Model!I9) -> 1.4014769 | X41: =Inputs!E15+(Inputs!G15-Inputs!E15)*BETAINV(RAND(),Model!J9,Model!K9) -> 0.34140404 | Y41: =(Inputs!H15+(Inputs!J15-Inputs!H15)*BETAINV(RAND(),Model!L9,Model!M9))*Inputs!$C$6 -> 41977.7 | Z41: =W41*X41 -> 0.47846988 | AA41: =RAND() -> 0.81699376 | AB41: =IF(AA41<EXP(-Z41),0,IF(AA41<EXP(-Z41)*(1+Z41),1,IF(AA41<EXP(-Z41)*(1+Z41+Z41^2/2),2,IF(AA41<EXP(-Z41)*(1+Z41+Z41^2/2+Z41^3/6),3,4)))) -> 1 | AC41: =AB41*Y41 -> 41977.7 | AD41: =Inputs!B16+(Inputs!D16-Inputs!B16)*BETAINV(RAND(),Model!H10,Model!I10) -> 0.44182679 | AE41: =Inputs!E16+(Inputs!G16-Inputs!E16)*BETAINV(RAND(),Model!J10,Model!K10) -> 0.55183433 | AF41: =(Inputs!H16+(Inputs!J16-Inputs!H16)*BETAINV(RAND(),Model!L10,Model!M10))*Inputs!$C$6 -> 157605.42 | AG41: =AD41*AE41 -> 0.24381519 | AH41: =RAND() -> 0.94453086 | AI41: =IF(AH41<EXP(-AG41),0,IF(AH41<EXP(-AG41)*(1+AG41),1,IF(AH41<EXP(-AG41)*(1+AG41+AG41^2/2),2,IF(AH41<EXP(-AG41)*(1+AG41+AG41^2/2+AG41^3/6),3,4)))) -> 1 | AJ41: =AI41*AF41 -> 157605.42 | AK41: =H41+O41+V41+AC41+AJ41 -> 291868.59
B42: =Inputs!B12+(Inputs!D12-Inputs!B12)*BETAINV(RAND(),Model!H6,Model!I6) -> 3.6207851 | C42: =Inputs!E12+(Inputs!G12-Inputs!E12)*BETAINV(RAND(),Model!J6,Model!K6) -> 0.26775725 | D42: =(Inputs!H12+(Inputs!J12-Inputs!H12)*BETAINV(RAND(),Model!L6,Model!M6))*Inputs!$C$6 -> 43918.512 | E42: =B42*C42 -> 0.96949146 | F42: =RAND() -> 0.90682115 | G42: =IF(F42<EXP(-E42),0,IF(F42<EXP(-E42)*(1+E42),1,IF(F42<EXP(-E42)*(1+E42+E42^2/2),2,IF(F42<EXP(-E42)*(1+E42+E42^2/2+E42^3/6),3,4)))) -> 2 | H42: =G42*D42 -> 87837.024 | I42: =Inputs!B13+(Inputs!D13-Inputs!B13)*BETAINV(RAND(),Model!H7,Model!I7) -> 2.3928576 | J42: =Inputs!E13+(Inputs!G13-Inputs!E13)*BETAINV(RAND(),Model!J7,Model!K7) -> 0.40506533 | K42: =(Inputs!H13+(Inputs!J13-Inputs!H13)*BETAINV(RAND(),Model!L7,Model!M7))*Inputs!$C$6 -> 44480.953 | L42: =I42*J42 -> 0.96926368 | M42: =RAND() -> 0.38835122 | N42: =IF(M42<EXP(-L42),0,IF(M42<EXP(-L42)*(1+L42),1,IF(M42<EXP(-L42)*(1+L42+L42^2/2),2,IF(M42<EXP(-L42)*(1+L42+L42^2/2+L42^3/6),3,4)))) -> 1 | O42: =N42*K42 -> 44480.953 | P42: =Inputs!B14+(Inputs!D14-Inputs!B14)*BETAINV(RAND(),Model!H8,Model!I8) -> 0.30849133 | Q42: =Inputs!E14+(Inputs!G14-Inputs!E14)*BETAINV(RAND(),Model!J8,Model!K8) -> 0.49830865 | R42: =(Inputs!H14+(Inputs!J14-Inputs!H14)*BETAINV(RAND(),Model!L8,Model!M8))*Inputs!$C$6 -> 311499.5 | S42: =P42*Q42 -> 0.1537239 | T42: =RAND() -> 0.97621809 | U42: =IF(T42<EXP(-S42),0,IF(T42<EXP(-S42)*(1+S42),1,IF(T42<EXP(-S42)*(1+S42+S42^2/2),2,IF(T42<EXP(-S42)*(1+S42+S42^2/2+S42^3/6),3,4)))) -> 1 | V42: =U42*R42 -> 311499.5 | W42: =Inputs!B15+(Inputs!D15-Inputs!B15)*BETAINV(RAND(),Model!H9,Model!I9) -> 1.3816326 | X42: =Inputs!E15+(Inputs!G15-Inputs!E15)*BETAINV(RAND(),Model!J9,Model!K9) -> 0.40603996 | Y42: =(Inputs!H15+(Inputs!J15-Inputs!H15)*BETAINV(RAND(),Model!L9,Model!M9))*Inputs!$C$6 -> 42383.427 | Z42: =W42*X42 -> 0.56099803 | AA42: =RAND() -> 0.67395723 | AB42: =IF(AA42<EXP(-Z42),0,IF(AA42<EXP(-Z42)*(1+Z42),1,IF(AA42<EXP(-Z42)*(1+Z42+Z42^2/2),2,IF(AA42<EXP(-Z42)*(1+Z42+Z42^2/2+Z42^3/6),3,4)))) -> 1 | AC42: =AB42*Y42 -> 42383.427 | AD42: =Inputs!B16+(Inputs!D16-Inputs!B16)*BETAINV(RAND(),Model!H10,Model!I10) -> 0.6669259 | AE42: =Inputs!E16+(Inputs!G16-Inputs!E16)*BETAINV(RAND(),Model!J10,Model!K10) -> 0.62376499 | AF42: =(Inputs!H16+(Inputs!J16-Inputs!H16)*BETAINV(RAND(),Model!L10,Model!M10))*Inputs!$C$6 -> 169395.83 | AG42: =AD42*AE42 -> 0.41600503 | AH42: =RAND() -> 0.55053546 | AI42: =IF(AH42<EXP(-AG42),0,IF(AH42<EXP(-AG42)*(1+AG42),1,IF(AH42<EXP(-AG42)*(1+AG42+AG42^2/2),2,IF(AH42<EXP(-AG42)*(1+AG42+AG42^2/2+AG42^3/6),3,4)))) -> 0 | AJ42: =AI42*AF42 -> 0 | AK42: =H42+O42+V42+AC42+AJ42 -> 486200.91
B43: =Inputs!B12+(Inputs!D12-Inputs!B12)*BETAINV(RAND(),Model!H6,Model!I6) -> 3.5746176 | C43: =Inputs!E12+(Inputs!G12-Inputs!E12)*BETAINV(RAND(),Model!J6,Model!K6) -> 0.21506005 | D43: =(Inputs!H12+(Inputs!J12-Inputs!H12)*BETAINV(RAND(),Model!L6,Model!M6))*Inputs!$C$6 -> 23867.173 | E43: =B43*C43 -> 0.76875744 | F43: =RAND() -> 0.0011097342 | G43: =IF(F43<EXP(-E43),0,IF(F43<EXP(-E43)*(1+E43),1,IF(F43<EXP(-E43)*(1+E43+E43^2/2),2,IF(F43<EXP(-E43)*(1+E43+E43^2/2+E43^3/6),3,4)))) -> 0 | H43: =G43*D43 -> 0 | I43: =Inputs!B13+(Inputs!D13-Inputs!B13)*BETAINV(RAND(),Model!H7,Model!I7) -> 2.2574026 | J43: =Inputs!E13+(Inputs!G13-Inputs!E13)*BETAINV(RAND(),Model!J7,Model!K7) -> 0.40885331 | K43: =(Inputs!H13+(Inputs!J13-Inputs!H13)*BETAINV(RAND(),Model!L7,Model!M7))*Inputs!$C$6 -> 35948.729 | L43: =I43*J43 -> 0.92294652 | M43: =RAND() -> 0.7654899 | N43: =IF(M43<EXP(-L43),0,IF(M43<EXP(-L43)*(1+L43),1,IF(M43<EXP(-L43)*(1+L43+L43^2/2),2,IF(M43<EXP(-L43)*(1+L43+L43^2/2+L43^3/6),3,4)))) -> 2 | O43: =N43*K43 -> 71897.458 | P43: =Inputs!B14+(Inputs!D14-Inputs!B14)*BETAINV(RAND(),Model!H8,Model!I8) -> 0.33847303 | Q43: =Inputs!E14+(Inputs!G14-Inputs!E14)*BETAINV(RAND(),Model!J8,Model!K8) -> 0.48098483 | R43: =(Inputs!H14+(Inputs!J14-Inputs!H14)*BETAINV(RAND(),Model!L8,Model!M8))*Inputs!$C$6 -> 403538.02 | S43: =P43*Q43 -> 0.16280039 | T43: =RAND() -> 0.15708587 | U43: =IF(T43<EXP(-S43),0,IF(T43<EXP(-S43)*(1+S43),1,IF(T43<EXP(-S43)*(1+S43+S43^2/2),2,IF(T43<EXP(-S43)*(1+S43+S43^2/2+S43^3/6),3,4)))) -> 0 | V43: =U43*R43 -> 0 | W43: =Inputs!B15+(Inputs!D15-Inputs!B15)*BETAINV(RAND(),Model!H9,Model!I9) -> 1.0552916 | X43: =Inputs!E15+(Inputs!G15-Inputs!E15)*BETAINV(RAND(),Model!J9,Model!K9) -> 0.51026868 | Y43: =(Inputs!H15+(Inputs!J15-Inputs!H15)*BETAINV(RAND(),Model!L9,Model!M9))*Inputs!$C$6 -> 55681.295 | Z43: =W43*X43 -> 0.53848228 | AA43: =RAND() -> 0.48526046 | AB43: =IF(AA43<EXP(-Z43),0,IF(AA43<EXP(-Z43)*(1+Z43),1,IF(AA43<EXP(-Z43)*(1+Z43+Z43^2/2),2,IF(AA43<EXP(-Z43)*(1+Z43+Z43^2/2+Z43^3/6),3,4)))) -> 0 | AC43: =AB43*Y43 -> 0 | AD43: =Inputs!B16+(Inputs!D16-Inputs!B16)*BETAINV(RAND(),Model!H10,Model!I10) -> 1.0515957 | AE43: =Inputs!E16+(Inputs!G16-Inputs!E16)*BETAINV(RAND(),Model!J10,Model!K10) -> 0.78876353 | AF43: =(Inputs!H16+(Inputs!J16-Inputs!H16)*BETAINV(RAND(),Model!L10,Model!M10))*Inputs!$C$6 -> 132771.39 | AG43: =AD43*AE43 -> 0.8294603 | AH43: =RAND() -> 0.44170521 | AI43: =IF(AH43<EXP(-AG43),0,IF(AH43<EXP(-AG43)*(1+AG43),1,IF(AH43<EXP(-AG43)*(1+AG43+AG43^2/2),2,IF(AH43<EXP(-AG43)*(1+AG43+AG43^2/2+AG43^3/6),3,4)))) -> 1 | AJ43: =AI43*AF43 -> 132771.39 | AK43: =H43+O43+V43+AC43+AJ43 -> 204668.85
B44: =Inputs!B12+(Inputs!D12-Inputs!B12)*BETAINV(RAND(),Model!H6,Model!I6) -> 2.2462662 | C44: =Inputs!E12+(Inputs!G12-Inputs!E12)*BETAINV(RAND(),Model!J6,Model!K6) -> 0.32630333 | D44: =(Inputs!H12+(Inputs!J12-Inputs!H12)*BETAINV(RAND(),Model!L6,Model!M6))*Inputs!$C$6 -> 21012.547 | E44: =B44*C44 -> 0.73296413 | F44: =RAND() -> 0.71314632 | G44: =IF(F44<EXP(-E44),0,IF(F44<EXP(-E44)*(1+E44),1,IF(F44<EXP(-E44)*(1+E44+E44^2/2),2,IF(F44<EXP(-E44)*(1+E44+E44^2/2+E44^3/6),3,4)))) -> 1 | H44: =G44*D44 -> 21012.547 | I44: =Inputs!B13+(Inputs!D13-Inputs!B13)*BETAINV(RAND(),Model!H7,Model!I7) -> 2.6844072 | J44: =Inputs!E13+(Inputs!G13-Inputs!E13)*BETAINV(RAND(),Model!J7,Model!K7) -> 0.21699767 | K44: =(Inputs!H13+(Inputs!J13-Inputs!H13)*BETAINV(RAND(),Model!L7,Model!M7))*Inputs!$C$6 -> 54509.633 | L44: =I44*J44 -> 0.58251011 | M44: =RAND() -> 0.040254412 | N44: =IF(M44<EXP(-L44),0,IF(M44<EXP(-L44)*(1+L44),1,IF(M44<EXP(-L44)*(1+L44+L44^2/2),2,IF(M44<EXP(-L44)*(1+L44+L44^2/2+L44^3/6),3,4)))) -> 0 | O44: =N44*K44 -> 0 | P44: =Inputs!B14+(Inputs!D14-Inputs!B14)*BETAINV(RAND(),Model!H8,Model!I8) -> 0.47483547 | Q44: =Inputs!E14+(Inputs!G14-Inputs!E14)*BETAINV(RAND(),Model!J8,Model!K8) -> 0.7345131 | R44: =(Inputs!H14+(Inputs!J14-Inputs!H14)*BETAINV(RAND(),Model!L8,Model!M8))*Inputs!$C$6 -> 517209.96 | S44: =P44*Q44 -> 0.34877287 | T44: =RAND() -> 0.82314753 | U44: =IF(T44<EXP(-S44),0,IF(T44<EXP(-S44)*(1+S44),1,IF(T44<EXP(-S44)*(1+S44+S44^2/2),2,IF(T44<EXP(-S44)*(1+S44+S44^2/2+S44^3/6),3,4)))) -> 1 | V44: =U44*R44 -> 517209.96 | W44: =Inputs!B15+(Inputs!D15-Inputs!B15)*BETAINV(RAND(),Model!H9,Model!I9) -> 1.1040346 | X44: =Inputs!E15+(Inputs!G15-Inputs!E15)*BETAINV(RAND(),Model!J9,Model!K9) -> 0.36623989 | Y44: =(Inputs!H15+(Inputs!J15-Inputs!H15)*BETAINV(RAND(),Model!L9,Model!M9))*Inputs!$C$6 -> 33910.093 | Z44: =W44*X44 -> 0.4043415 | AA44: =RAND() -> 0.15536952 | AB44: =IF(AA44<EXP(-Z44),0,IF(AA44<EXP(-Z44)*(1+Z44),1,IF(AA44<EXP(-Z44)*(1+Z44+Z44^2/2),2,IF(AA44<EXP(-Z44)*(1+Z44+Z44^2/2+Z44^3/6),3,4)))) -> 0 | AC44: =AB44*Y44 -> 0 | AD44: =Inputs!B16+(Inputs!D16-Inputs!B16)*BETAINV(RAND(),Model!H10,Model!I10) -> 1.0123908 | AE44: =Inputs!E16+(Inputs!G16-Inputs!E16)*BETAINV(RAND(),Model!J10,Model!K10) -> 0.65251403 | AF44: =(Inputs!H16+(Inputs!J16-Inputs!H16)*BETAINV(RAND(),Model!L10,Model!M10))*Inputs!$C$6 -> 61289.901 | AG44: =AD44*AE44 -> 0.66059921 | AH44: =RAND() -> 0.0031753604 | AI44: =IF(AH44<EXP(-AG44),0,IF(AH44<EXP(-AG44)*(1+AG44),1,IF(AH44<EXP(-AG44)*(1+AG44+AG44^2/2),2,IF(AH44<EXP(-AG44)*(1+AG44+AG44^2/2+AG44^3/6),3,4)))) -> 0 | AJ44: =AI44*AF44 -> 0 | AK44: =H44+O44+V44+AC44+AJ44 -> 538222.51
B45: =Inputs!B12+(Inputs!D12-Inputs!B12)*BETAINV(RAND(),Model!H6,Model!I6) -> 3.8864169 | C45: =Inputs!E12+(Inputs!G12-Inputs!E12)*BETAINV(RAND(),Model!J6,Model!K6) -> 0.28699038 | D45: =(Inputs!H12+(Inputs!J12-Inputs!H12)*BETAINV(RAND(),Model!L6,Model!M6))*Inputs!$C$6 -> 31124.192 | E45: =B45*C45 -> 1.1153643 | F45: =RAND() -> 0.1257834 | G45: =IF(F45<EXP(-E45),0,IF(F45<EXP(-E45)*(1+E45),1,IF(F45<EXP(-E45)*(1+E45+E45^2/2),2,IF(F45<EXP(-E45)*(1+E45+E45^2/2+E45^3/6),3,4)))) -> 0 | H45: =G45*D45 -> 0 | I45: =Inputs!B13+(Inputs!D13-Inputs!B13)*BETAINV(RAND(),Model!H7,Model!I7) -> 2.5784119 | J45: =Inputs!E13+(Inputs!G13-Inputs!E13)*BETAINV(RAND(),Model!J7,Model!K7) -> 0.2114373 | K45: =(Inputs!H13+(Inputs!J13-Inputs!H13)*BETAINV(RAND(),Model!L7,Model!M7))*Inputs!$C$6 -> 17069.316 | L45: =I45*J45 -> 0.54517244 | M45: =RAND() -> 0.8397858 | N45: =IF(M45<EXP(-L45),0,IF(M45<EXP(-L45)*(1+L45),1,IF(M45<EXP(-L45)*(1+L45+L45^2/2),2,IF(M45<EXP(-L45)*(1+L45+L45^2/2+L45^3/6),3,4)))) -> 1 | O45: =N45*K45 -> 17069.316 | P45: =Inputs!B14+(Inputs!D14-Inputs!B14)*BETAINV(RAND(),Model!H8,Model!I8) -> 0.13281103 | Q45: =Inputs!E14+(Inputs!G14-Inputs!E14)*BETAINV(RAND(),Model!J8,Model!K8) -> 0.81943032 | R45: =(Inputs!H14+(Inputs!J14-Inputs!H14)*BETAINV(RAND(),Model!L8,Model!M8))*Inputs!$C$6 -> 446406.22 | S45: =P45*Q45 -> 0.10882939 | T45: =RAND() -> 0.84964528 | U45: =IF(T45<EXP(-S45),0,IF(T45<EXP(-S45)*(1+S45),1,IF(T45<EXP(-S45)*(1+S45+S45^2/2),2,IF(T45<EXP(-S45)*(1+S45+S45^2/2+S45^3/6),3,4)))) -> 0 | V45: =U45*R45 -> 0 | W45: =Inputs!B15+(Inputs!D15-Inputs!B15)*BETAINV(RAND(),Model!H9,Model!I9) -> 0.91722974 | X45: =Inputs!E15+(Inputs!G15-Inputs!E15)*BETAINV(RAND(),Model!J9,Model!K9) -> 0.35206764 | Y45: =(Inputs!H15+(Inputs!J15-Inputs!H15)*BETAINV(RAND(),Model!L9,Model!M9))*Inputs!$C$6 -> 19060.058 | Z45: =W45*X45 -> 0.32292691 | AA45: =RAND() -> 0.53178756 | AB45: =IF(AA45<EXP(-Z45),0,IF(AA45<EXP(-Z45)*(1+Z45),1,IF(AA45<EXP(-Z45)*(1+Z45+Z45^2/2),2,IF(AA45<EXP(-Z45)*(1+Z45+Z45^2/2+Z45^3/6),3,4)))) -> 0 | AC45: =AB45*Y45 -> 0 | AD45: =Inputs!B16+(Inputs!D16-Inputs!B16)*BETAINV(RAND(),Model!H10,Model!I10) -> 0.66310968 | AE45: =Inputs!E16+(Inputs!G16-Inputs!E16)*BETAINV(RAND(),Model!J10,Model!K10) -> 0.56555651 | AF45: =(Inputs!H16+(Inputs!J16-Inputs!H16)*BETAINV(RAND(),Model!L10,Model!M10))*Inputs!$C$6 -> 93284.127 | AG45: =AD45*AE45 -> 0.375026 | AH45: =RAND() -> 0.66833324 | AI45: =IF(AH45<EXP(-AG45),0,IF(AH45<EXP(-AG45)*(1+AG45),1,IF(AH45<EXP(-AG45)*(1+AG45+AG45^2/2),2,IF(AH45<EXP(-AG45)*(1+AG45+AG45^2/2+AG45^3/6),3,4)))) -> 0 | AJ45: =AI45*AF45 -> 0 | AK45: =H45+O45+V45+AC45+AJ45 -> 17069.316
B46: =Inputs!B12+(Inputs!D12-Inputs!B12)*BETAINV(RAND(),Model!H6,Model!I6) -> 3.8798639 | C46: =Inputs!E12+(Inputs!G12-Inputs!E12)*BETAINV(RAND(),Model!J6,Model!K6) -> 0.22929857 | D46: =(Inputs!H12+(Inputs!J12-Inputs!H12)*BETAINV(RAND(),Model!L6,Model!M6))*Inputs!$C$6 -> 35011.278 | E46: =B46*C46 -> 0.88964726 | F46: =RAND() -> 0.25546564 | G46: =IF(F46<EXP(-E46),0,IF(F46<EXP(-E46)*(1+E46),1,IF(F46<EXP(-E46)*(1+E46+E46^2/2),2,IF(F46<EXP(-E46)*(1+E46+E46^2/2+E46^3/6),3,4)))) -> 0 | H46: =G46*D46 -> 0 | I46: =Inputs!B13+(Inputs!D13-Inputs!B13)*BETAINV(RAND(),Model!H7,Model!I7) -> 3.1063318 | J46: =Inputs!E13+(Inputs!G13-Inputs!E13)*BETAINV(RAND(),Model!J7,Model!K7) -> 0.37667293 | K46: =(Inputs!H13+(Inputs!J13-Inputs!H13)*BETAINV(RAND(),Model!L7,Model!M7))*Inputs!$C$6 -> 52330.788 | L46: =I46*J46 -> 1.1700711 | M46: =RAND() -> 0.055700926 | N46: =IF(M46<EXP(-L46),0,IF(M46<EXP(-L46)*(1+L46),1,IF(M46<EXP(-L46)*(1+L46+L46^2/2),2,IF(M46<EXP(-L46)*(1+L46+L46^2/2+L46^3/6),3,4)))) -> 0 | O46: =N46*K46 -> 0 | P46: =Inputs!B14+(Inputs!D14-Inputs!B14)*BETAINV(RAND(),Model!H8,Model!I8) -> 0.35552446 | Q46: =Inputs!E14+(Inputs!G14-Inputs!E14)*BETAINV(RAND(),Model!J8,Model!K8) -> 0.77854766 | R46: =(Inputs!H14+(Inputs!J14-Inputs!H14)*BETAINV(RAND(),Model!L8,Model!M8))*Inputs!$C$6 -> 359820.89 | S46: =P46*Q46 -> 0.27679274 | T46: =RAND() -> 0.92875744 | U46: =IF(T46<EXP(-S46),0,IF(T46<EXP(-S46)*(1+S46),1,IF(T46<EXP(-S46)*(1+S46+S46^2/2),2,IF(T46<EXP(-S46)*(1+S46+S46^2/2+S46^3/6),3,4)))) -> 1 | V46: =U46*R46 -> 359820.89 | W46: =Inputs!B15+(Inputs!D15-Inputs!B15)*BETAINV(RAND(),Model!H9,Model!I9) -> 2.3251908 | X46: =Inputs!E15+(Inputs!G15-Inputs!E15)*BETAINV(RAND(),Model!J9,Model!K9) -> 0.34265095 | Y46: =(Inputs!H15+(Inputs!J15-Inputs!H15)*BETAINV(RAND(),Model!L9,Model!M9))*Inputs!$C$6 -> 54573.774 | Z46: =W46*X46 -> 0.79672883 | AA46: =RAND() -> 0.19186322 | AB46: =IF(AA46<EXP(-Z46),0,IF(AA46<EXP(-Z46)*(1+Z46),1,IF(AA46<EXP(-Z46)*(1+Z46+Z46^2/2),2,IF(AA46<EXP(-Z46)*(1+Z46+Z46^2/2+Z46^3/6),3,4)))) -> 0 | AC46: =AB46*Y46 -> 0 | AD46: =Inputs!B16+(Inputs!D16-Inputs!B16)*BETAINV(RAND(),Model!H10,Model!I10) -> 0.82402623 | AE46: =Inputs!E16+(Inputs!G16-Inputs!E16)*BETAINV(RAND(),Model!J10,Model!K10) -> 0.61500192 | AF46: =(Inputs!H16+(Inputs!J16-Inputs!H16)*BETAINV(RAND(),Model!L10,Model!M10))*Inputs!$C$6 -> 110179.08 | AG46: =AD46*AE46 -> 0.50677771 | AH46: =RAND() -> 0.083214141 | AI46: =IF(AH46<EXP(-AG46),0,IF(AH46<EXP(-AG46)*(1+AG46),1,IF(AH46<EXP(-AG46)*(1+AG46+AG46^2/2),2,IF(AH46<EXP(-AG46)*(1+AG46+AG46^2/2+AG46^3/6),3,4)))) -> 0 | AJ46: =AI46*AF46 -> 0 | AK46: =H46+O46+V46+AC46+AJ46 -> 359820.89
B47: =Inputs!B12+(Inputs!D12-Inputs!B12)*BETAINV(RAND(),Model!H6,Model!I6) -> 3.4014609 | C47: =Inputs!E12+(Inputs!G12-Inputs!E12)*BETAINV(RAND(),Model!J6,Model!K6) -> 0.26135259 | D47: =(Inputs!H12+(Inputs!J12-Inputs!H12)*BETAINV(RAND(),Model!L6,Model!M6))*Inputs!$C$6 -> 37539.107 | E47: =B47*C47 -> 0.88898061 | F47: =RAND() -> 0.87395046 | G47: =IF(F47<EXP(-E47),0,IF(F47<EXP(-E47)*(1+E47),1,IF(F47<EXP(-E47)*(1+E47+E47^2/2),2,IF(F47<EXP(-E47)*(1+E47+E47^2/2+E47^3/6),3,4)))) -> 2 | H47: =G47*D47 -> 75078.215 | I47: =Inputs!B13+(Inputs!D13-Inputs!B13)*BETAINV(RAND(),Model!H7,Model!I7) -> 2.1439656 | J47: =Inputs!E13+(Inputs!G13-Inputs!E13)*BETAINV(RAND(),Model!J7,Model!K7) -> 0.12942904 | K47: =(Inputs!H13+(Inputs!J13-Inputs!H13)*BETAINV(RAND(),Model!L7,Model!M7))*Inputs!$C$6 -> 73171.439 | L47: =I47*J47 -> 0.2774914 | M47: =RAND() -> 0.86506134 | N47: =IF(M47<EXP(-L47),0,IF(M47<EXP(-L47)*(1+L47),1,IF(M47<EXP(-L47)*(1+L47+L47^2/2),2,IF(M47<EXP(-L47)*(1+L47+L47^2/2+L47^3/6),3,4)))) -> 1 | O47: =N47*K47 -> 73171.439 | P47: =Inputs!B14+(Inputs!D14-Inputs!B14)*BETAINV(RAND(),Model!H8,Model!I8) -> 0.18012732 | Q47: =Inputs!E14+(Inputs!G14-Inputs!E14)*BETAINV(RAND(),Model!J8,Model!K8) -> 0.44691732 | R47: =(Inputs!H14+(Inputs!J14-Inputs!H14)*BETAINV(RAND(),Model!L8,Model!M8))*Inputs!$C$6 -> 485008.59 | S47: =P47*Q47 -> 0.080502019 | T47: =RAND() -> 0.79274885 | U47: =IF(T47<EXP(-S47),0,IF(T47<EXP(-S47)*(1+S47),1,IF(T47<EXP(-S47)*(1+S47+S47^2/2),2,IF(T47<EXP(-S47)*(1+S47+S47^2/2+S47^3/6),3,4)))) -> 0 | V47: =U47*R47 -> 0 | W47: =Inputs!B15+(Inputs!D15-Inputs!B15)*BETAINV(RAND(),Model!H9,Model!I9) -> 1.3700986 | X47: =Inputs!E15+(Inputs!G15-Inputs!E15)*BETAINV(RAND(),Model!J9,Model!K9) -> 0.46848996 | Y47: =(Inputs!H15+(Inputs!J15-Inputs!H15)*BETAINV(RAND(),Model!L9,Model!M9))*Inputs!$C$6 -> 61919.177 | Z47: =W47*X47 -> 0.64187744 | AA47: =RAND() -> 0.79539466 | AB47: =IF(AA47<EXP(-Z47),0,IF(AA47<EXP(-Z47)*(1+Z47),1,IF(AA47<EXP(-Z47)*(1+Z47+Z47^2/2),2,IF(AA47<EXP(-Z47)*(1+Z47+Z47^2/2+Z47^3/6),3,4)))) -> 1 | AC47: =AB47*Y47 -> 61919.177 | AD47: =Inputs!B16+(Inputs!D16-Inputs!B16)*BETAINV(RAND(),Model!H10,Model!I10) -> 1.0860728 | AE47: =Inputs!E16+(Inputs!G16-Inputs!E16)*BETAINV(RAND(),Model!J10,Model!K10) -> 0.64149587 | AF47: =(Inputs!H16+(Inputs!J16-Inputs!H16)*BETAINV(RAND(),Model!L10,Model!M10))*Inputs!$C$6 -> 85463.597 | AG47: =AD47*AE47 -> 0.69671123 | AH47: =RAND() -> 0.76060717 | AI47: =IF(AH47<EXP(-AG47),0,IF(AH47<EXP(-AG47)*(1+AG47),1,IF(AH47<EXP(-AG47)*(1+AG47+AG47^2/2),2,IF(AH47<EXP(-AG47)*(1+AG47+AG47^2/2+AG47^3/6),3,4)))) -> 1 | AJ47: =AI47*AF47 -> 85463.597 | AK47: =H47+O47+V47+AC47+AJ47 -> 295632.43
B48: =Inputs!B12+(Inputs!D12-Inputs!B12)*BETAINV(RAND(),Model!H6,Model!I6) -> 3.0288674 | C48: =Inputs!E12+(Inputs!G12-Inputs!E12)*BETAINV(RAND(),Model!J6,Model!K6) -> 0.33084489 | D48: =(Inputs!H12+(Inputs!J12-Inputs!H12)*BETAINV(RAND(),Model!L6,Model!M6))*Inputs!$C$6 -> 26545.858 | E48: =B48*C48 -> 1.0020853 | F48: =RAND() -> 0.0068084402 | G48: =IF(F48<EXP(-E48),0,IF(F48<EXP(-E48)*(1+E48),1,IF(F48<EXP(-E48)*(1+E48+E48^2/2),2,IF(F48<EXP(-E48)*(1+E48+E48^2/2+E48^3/6),3,4)))) -> 0 | H48: =G48*D48 -> 0 | I48: =Inputs!B13+(Inputs!D13-Inputs!B13)*BETAINV(RAND(),Model!H7,Model!I7) -> 2.6143123 | J48: =Inputs!E13+(Inputs!G13-Inputs!E13)*BETAINV(RAND(),Model!J7,Model!K7) -> 0.19114039 | K48: =(Inputs!H13+(Inputs!J13-Inputs!H13)*BETAINV(RAND(),Model!L7,Model!M7))*Inputs!$C$6 -> 22927.828 | L48: =I48*J48 -> 0.49970066 | M48: =RAND() -> 0.25037662 | N48: =IF(M48<EXP(-L48),0,IF(M48<EXP(-L48)*(1+L48),1,IF(M48<EXP(-L48)*(1+L48+L48^2/2),2,IF(M48<EXP(-L48)*(1+L48+L48^2/2+L48^3/6),3,4)))) -> 0 | O48: =N48*K48 -> 0 | P48: =Inputs!B14+(Inputs!D14-Inputs!B14)*BETAINV(RAND(),Model!H8,Model!I8) -> 0.25759729 | Q48: =Inputs!E14+(Inputs!G14-Inputs!E14)*BETAINV(RAND(),Model!J8,Model!K8) -> 0.63171525 | R48: =(Inputs!H14+(Inputs!J14-Inputs!H14)*BETAINV(RAND(),Model!L8,Model!M8))*Inputs!$C$6 -> 505894.56 | S48: =P48*Q48 -> 0.16272814 | T48: =RAND() -> 0.40769265 | U48: =IF(T48<EXP(-S48),0,IF(T48<EXP(-S48)*(1+S48),1,IF(T48<EXP(-S48)*(1+S48+S48^2/2),2,IF(T48<EXP(-S48)*(1+S48+S48^2/2+S48^3/6),3,4)))) -> 0 | V48: =U48*R48 -> 0 | W48: =Inputs!B15+(Inputs!D15-Inputs!B15)*BETAINV(RAND(),Model!H9,Model!I9) -> 1.9172997 | X48: =Inputs!E15+(Inputs!G15-Inputs!E15)*BETAINV(RAND(),Model!J9,Model!K9) -> 0.27244781 | Y48: =(Inputs!H15+(Inputs!J15-Inputs!H15)*BETAINV(RAND(),Model!L9,Model!M9))*Inputs!$C$6 -> 32800.683 | Z48: =W48*X48 -> 0.52236412 | AA48: =RAND() -> 0.046493516 | AB48: =IF(AA48<EXP(-Z48),0,IF(AA48<EXP(-Z48)*(1+Z48),1,IF(AA48<EXP(-Z48)*(1+Z48+Z48^2/2),2,IF(AA48<EXP(-Z48)*(1+Z48+Z48^2/2+Z48^3/6),3,4)))) -> 0 | AC48: =AB48*Y48 -> 0 | AD48: =Inputs!B16+(Inputs!D16-Inputs!B16)*BETAINV(RAND(),Model!H10,Model!I10) -> 0.5589632 | AE48: =Inputs!E16+(Inputs!G16-Inputs!E16)*BETAINV(RAND(),Model!J10,Model!K10) -> 0.78086256 | AF48: =(Inputs!H16+(Inputs!J16-Inputs!H16)*BETAINV(RAND(),Model!L10,Model!M10))*Inputs!$C$6 -> 177150.19 | AG48: =AD48*AE48 -> 0.43647344 | AH48: =RAND() -> 0.99878791 | AI48: =IF(AH48<EXP(-AG48),0,IF(AH48<EXP(-AG48)*(1+AG48),1,IF(AH48<EXP(-AG48)*(1+AG48+AG48^2/2),2,IF(AH48<EXP(-AG48)*(1+AG48+AG48^2/2+AG48^3/6),3,4)))) -> 3 | AJ48: =AI48*AF48 -> 531450.56 | AK48: =H48+O48+V48+AC48+AJ48 -> 531450.56
B49: =Inputs!B12+(Inputs!D12-Inputs!B12)*BETAINV(RAND(),Model!H6,Model!I6) -> 1.221775 | C49: =Inputs!E12+(Inputs!G12-Inputs!E12)*BETAINV(RAND(),Model!J6,Model!K6) -> 0.28821791 | D49: =(Inputs!H12+(Inputs!J12-Inputs!H12)*BETAINV(RAND(),Model!L6,Model!M6))*Inputs!$C$6 -> 18359.023 | E49: =B49*C49 -> 0.35213744 | F49: =RAND() -> 0.10419832 | G49: =IF(F49<EXP(-E49),0,IF(F49<EXP(-E49)*(1+E49),1,IF(F49<EXP(-E49)*(1+E49+E49^2/2),2,IF(F49<EXP(-E49)*(1+E49+E49^2/2+E49^3/6),3,4)))) -> 0 | H49: =G49*D49 -> 0 | I49: =Inputs!B13+(Inputs!D13-Inputs!B13)*BETAINV(RAND(),Model!H7,Model!I7) -> 2.6584872 | J49: =Inputs!E13+(Inputs!G13-Inputs!E13)*BETAINV(RAND(),Model!J7,Model!K7) -> 0.23057421 | K49: =(Inputs!H13+(Inputs!J13-Inputs!H13)*BETAINV(RAND(),Model!L7,Model!M7))*Inputs!$C$6 -> 35912.072 | L49: =I49*J49 -> 0.61297859 | M49: =RAND() -> 0.21572324 | N49: =IF(M49<EXP(-L49),0,IF(M49<EXP(-L49)*(1+L49),1,IF(M49<EXP(-L49)*(1+L49+L49^2/2),2,IF(M49<EXP(-L49)*(1+L49+L49^2/2+L49^3/6),3,4)))) -> 0 | O49: =N49*K49 -> 0 | P49: =Inputs!B14+(Inputs!D14-Inputs!B14)*BETAINV(RAND(),Model!H8,Model!I8) -> 0.27672221 | Q49: =Inputs!E14+(Inputs!G14-Inputs!E14)*BETAINV(RAND(),Model!J8,Model!K8) -> 0.46687027 | R49: =(Inputs!H14+(Inputs!J14-Inputs!H14)*BETAINV(RAND(),Model!L8,Model!M8))*Inputs!$C$6 -> 493382.3 | S49: =P49*Q49 -> 0.12919337 | T49: =RAND() -> 0.30488746 | U49: =IF(T49<EXP(-S49),0,IF(T49<EXP(-S49)*(1+S49),1,IF(T49<EXP(-S49)*(1+S49+S49^2/2),2,IF(T49<EXP(-S49)*(1+S49+S49^2/2+S49^3/6),3,4)))) -> 0 | V49: =U49*R49 -> 0 | W49: =Inputs!B15+(Inputs!D15-Inputs!B15)*BETAINV(RAND(),Model!H9,Model!I9) -> 0.42182185 | X49: =Inputs!E15+(Inputs!G15-Inputs!E15)*BETAINV(RAND(),Model!J9,Model!K9) -> 0.30183453 | Y49: =(Inputs!H15+(Inputs!J15-Inputs!H15)*BETAINV(RAND(),Model!L9,Model!M9))*Inputs!$C$6 -> 32051.637 | Z49: =W49*X49 -> 0.1273204 | AA49: =RAND() -> 0.86072704 | AB49: =IF(AA49<EXP(-Z49),0,IF(AA49<EXP(-Z49)*(1+Z49),1,IF(AA49<EXP(-Z49)*(1+Z49+Z49^2/2),2,IF(AA49<EXP(-Z49)*(1+Z49+Z49^2/2+Z49^3/6),3,4)))) -> 0 | AC49: =AB49*Y49 -> 0 | AD49: =Inputs!B16+(Inputs!D16-Inputs!B16)*BETAINV(RAND(),Model!H10,Model!I10) -> 0.58494149 | AE49: =Inputs!E16+(Inputs!G16-Inputs!E16)*BETAINV(RAND(),Model!J10,Model!K10) -> 0.63480374 | AF49: =(Inputs!H16+(Inputs!J16-Inputs!H16)*BETAINV(RAND(),Model!L10,Model!M10))*Inputs!$C$6 -> 68490.553 | AG49: =AD49*AE49 -> 0.37132304 | AH49: =RAND() -> 0.9760894 | AI49: =IF(AH49<EXP(-AG49),0,IF(AH49<EXP(-AG49)*(1+AG49),1,IF(AH49<EXP(-AG49)*(1+AG49+AG49^2/2),2,IF(AH49<EXP(-AG49)*(1+AG49+AG49^2/2+AG49^3/6),3,4)))) -> 2 | AJ49: =AI49*AF49 -> 136981.11 | AK49: =H49+O49+V49+AC49+AJ49 -> 136981.11
B50: =Inputs!B12+(Inputs!D12-Inputs!B12)*BETAINV(RAND(),Model!H6,Model!I6) -> 2.5785082 | C50: =Inputs!E12+(Inputs!G12-Inputs!E12)*BETAINV(RAND(),Model!J6,Model!K6) -> 0.39635804 | D50: =(Inputs!H12+(Inputs!J12-Inputs!H12)*BETAINV(RAND(),Model!L6,Model!M6))*Inputs!$C$6 -> 27756.898 | E50: =B50*C50 -> 1.0220124 | F50: =RAND() -> 0.66664254 | G50: =IF(F50<EXP(-E50),0,IF(F50<EXP(-E50)*(1+E50),1,IF(F50<EXP(-E50)*(1+E50+E50^2/2),2,IF(F50<EXP(-E50)*(1+E50+E50^2/2+E50^3/6),3,4)))) -> 1 | H50: =G50*D50 -> 27756.898 | I50: =Inputs!B13+(Inputs!D13-Inputs!B13)*BETAINV(RAND(),Model!H7,Model!I7) -> 0.9831578 | J50: =Inputs!E13+(Inputs!G13-Inputs!E13)*BETAINV(RAND(),Model!J7,Model!K7) -> 0.20693261 | K50: =(Inputs!H13+(Inputs!J13-Inputs!H13)*BETAINV(RAND(),Model!L7,Model!M7))*Inputs!$C$6 -> 31296.179 | L50: =I50*J50 -> 0.20344741 | M50: =RAND() -> 0.40422151 | N50: =IF(M50<EXP(-L50),0,IF(M50<EXP(-L50)*(1+L50),1,IF(M50<EXP(-L50)*(1+L50+L50^2/2),2,IF(M50<EXP(-L50)*(1+L50+L50^2/2+L50^3/6),3,4)))) -> 0 | O50: =N50*K50 -> 0 | P50: =Inputs!B14+(Inputs!D14-Inputs!B14)*BETAINV(RAND(),Model!H8,Model!I8) -> 0.44818419 | Q50: =Inputs!E14+(Inputs!G14-Inputs!E14)*BETAINV(RAND(),Model!J8,Model!K8) -> 0.50756112 | R50: =(Inputs!H14+(Inputs!J14-Inputs!H14)*BETAINV(RAND(),Model!L8,Model!M8))*Inputs!$C$6 -> 362433.03 | S50: =P50*Q50 -> 0.22748087 | T50: =RAND() -> 0.070118563 | U50: =IF(T50<EXP(-S50),0,IF(T50<EXP(-S50)*(1+S50),1,IF(T50<EXP(-S50)*(1+S50+S50^2/2),2,IF(T50<EXP(-S50)*(1+S50+S50^2/2+S50^3/6),3,4)))) -> 0 | V50: =U50*R50 -> 0 | W50: =Inputs!B15+(Inputs!D15-Inputs!B15)*BETAINV(RAND(),Model!H9,Model!I9) -> 1.4092668 | X50: =Inputs!E15+(Inputs!G15-Inputs!E15)*BETAINV(RAND(),Model!J9,Model!K9) -> 0.51929861 | Y50: =(Inputs!H15+(Inputs!J15-Inputs!H15)*BETAINV(RAND(),Model!L9,Model!M9))*Inputs!$C$6 -> 17065.366 | Z50: =W50*X50 -> 0.73183027 | AA50: =RAND() -> 0.097827514 | AB50: =IF(AA50<EXP(-Z50),0,IF(AA50<EXP(-Z50)*(1+Z50),1,IF(AA50<EXP(-Z50)*(1+Z50+Z50^2/2),2,IF(AA50<EXP(-Z50)*(1+Z50+Z50^2/2+Z50^3/6),3,4)))) -> 0 | AC50: =AB50*Y50 -> 0 | AD50: =Inputs!B16+(Inputs!D16-Inputs!B16)*BETAINV(RAND(),Model!H10,Model!I10) -> 0.63859772 | AE50: =Inputs!E16+(Inputs!G16-Inputs!E16)*BETAINV(RAND(),Model!J10,Model!K10) -> 0.54902358 | AF50: =(Inputs!H16+(Inputs!J16-Inputs!H16)*BETAINV(RAND(),Model!L10,Model!M10))*Inputs!$C$6 -> 98726.055 | AG50: =AD50*AE50 -> 0.35060521 | AH50: =RAND() -> 0.34317807 | AI50: =IF(AH50<EXP(-AG50),0,IF(AH50<EXP(-AG50)*(1+AG50),1,IF(AH50<EXP(-AG50)*(1+AG50+AG50^2/2),2,IF(AH50<EXP(-AG50)*(1+AG50+AG50^2/2+AG50^3/6),3,4)))) -> 0 | AJ50: =AI50*AF50 -> 0 | AK50: =H50+O50+V50+AC50+AJ50 -> 27756.898
B51: =Inputs!B12+(Inputs!D12-Inputs!B12)*BETAINV(RAND(),Model!H6,Model!I6) -> 6.0454693 | C51: =Inputs!E12+(Inputs!G12-Inputs!E12)*BETAINV(RAND(),Model!J6,Model!K6) -> 0.24538393 | D51: =(Inputs!H12+(Inputs!J12-Inputs!H12)*BETAINV(RAND(),Model!L6,Model!M6))*Inputs!$C$6 -> 17628.715 | E51: =B51*C51 -> 1.483461 | F51: =RAND() -> 0.66698307 | G51: =IF(F51<EXP(-E51),0,IF(F51<EXP(-E51)*(1+E51),1,IF(F51<EXP(-E51)*(1+E51+E51^2/2),2,IF(F51<EXP(-E51)*(1+E51+E51^2/2+E51^3/6),3,4)))) -> 2 | H51: =G51*D51 -> 35257.43 | I51: =Inputs!B13+(Inputs!D13-Inputs!B13)*BETAINV(RAND(),Model!H7,Model!I7) -> 1.9426366 | J51: =Inputs!E13+(Inputs!G13-Inputs!E13)*BETAINV(RAND(),Model!J7,Model!K7) -> 0.31034719 | K51: =(Inputs!H13+(Inputs!J13-Inputs!H13)*BETAINV(RAND(),Model!L7,Model!M7))*Inputs!$C$6 -> 19259.598 | L51: =I51*J51 -> 0.6028918 | M51: =RAND() -> 0.60557536 | N51: =IF(M51<EXP(-L51),0,IF(M51<EXP(-L51)*(1+L51),1,IF(M51<EXP(-L51)*(1+L51+L51^2/2),2,IF(M51<EXP(-L51)*(1+L51+L51^2/2+L51^3/6),3,4)))) -> 1 | O51: =N51*K51 -> 19259.598 | P51: =Inputs!B14+(Inputs!D14-Inputs!B14)*BETAINV(RAND(),Model!H8,Model!I8) -> 0.15119476 | Q51: =Inputs!E14+(Inputs!G14-Inputs!E14)*BETAINV(RAND(),Model!J8,Model!K8) -> 0.52594346 | R51: =(Inputs!H14+(Inputs!J14-Inputs!H14)*BETAINV(RAND(),Model!L8,Model!M8))*Inputs!$C$6 -> 448798.28 | S51: =P51*Q51 -> 0.079519894 | T51: =RAND() -> 0.95792827 | U51: =IF(T51<EXP(-S51),0,IF(T51<EXP(-S51)*(1+S51),1,IF(T51<EXP(-S51)*(1+S51+S51^2/2),2,IF(T51<EXP(-S51)*(1+S51+S51^2/2+S51^3/6),3,4)))) -> 1 | V51: =U51*R51 -> 448798.28 | W51: =Inputs!B15+(Inputs!D15-Inputs!B15)*BETAINV(RAND(),Model!H9,Model!I9) -> 1.1736915 | X51: =Inputs!E15+(Inputs!G15-Inputs!E15)*BETAINV(RAND(),Model!J9,Model!K9) -> 0.35455778 | Y51: =(Inputs!H15+(Inputs!J15-Inputs!H15)*BETAINV(RAND(),Model!L9,Model!M9))*Inputs!$C$6 -> 23188.415 | Z51: =W51*X51 -> 0.41614146 | AA51: =RAND() -> 0.77876941 | AB51: =IF(AA51<EXP(-Z51),0,IF(AA51<EXP(-Z51)*(1+Z51),1,IF(AA51<EXP(-Z51)*(1+Z51+Z51^2/2),2,IF(AA51<EXP(-Z51)*(1+Z51+Z51^2/2+Z51^3/6),3,4)))) -> 1 | AC51: =AB51*Y51 -> 23188.415 | AD51: =Inputs!B16+(Inputs!D16-Inputs!B16)*BETAINV(RAND(),Model!H10,Model!I10) -> 0.52870948 | AE51: =Inputs!E16+(Inputs!G16-Inputs!E16)*BETAINV(RAND(),Model!J10,Model!K10) -> 0.4649992 | AF51: =(Inputs!H16+(Inputs!J16-Inputs!H16)*BETAINV(RAND(),Model!L10,Model!M10))*Inputs!$C$6 -> 72415.317 | AG51: =AD51*AE51 -> 0.24584948 | AH51: =RAND() -> 0.65021801 | AI51: =IF(AH51<EXP(-AG51),0,IF(AH51<EXP(-AG51)*(1+AG51),1,IF(AH51<EXP(-AG51)*(1+AG51+AG51^2/2),2,IF(AH51<EXP(-AG51)*(1+AG51+AG51^2/2+AG51^3/6),3,4)))) -> 0 | AJ51: =AI51*AF51 -> 0 | AK51: =H51+O51+V51+AC51+AJ51 -> 526503.73
B52: =Inputs!B12+(Inputs!D12-Inputs!B12)*BETAINV(RAND(),Model!H6,Model!I6) -> 2.6718084 | C52: =Inputs!E12+(Inputs!G12-Inputs!E12)*BETAINV(RAND(),Model!J6,Model!K6) -> 0.30790396 | D52: =(Inputs!H12+(Inputs!J12-Inputs!H12)*BETAINV(RAND(),Model!L6,Model!M6))*Inputs!$C$6 -> 32056.036 | E52: =B52*C52 -> 0.82266038 | F52: =RAND() -> 0.034696999 | G52: =IF(F52<EXP(-E52),0,IF(F52<EXP(-E52)*(1+E52),1,IF(F52<EXP(-E52)*(1+E52+E52^2/2),2,IF(F52<EXP(-E52)*(1+E52+E52^2/2+E52^3/6),3,4)))) -> 0 | H52: =G52*D52 -> 0 | I52: =Inputs!B13+(Inputs!D13-Inputs!B13)*BETAINV(RAND(),Model!H7,Model!I7) -> 2.2167967 | J52: =Inputs!E13+(Inputs!G13-Inputs!E13)*BETAINV(RAND(),Model!J7,Model!K7) -> 0.37533435 | K52: =(Inputs!H13+(Inputs!J13-Inputs!H13)*BETAINV(RAND(),Model!L7,Model!M7))*Inputs!$C$6 -> 35349.57 | L52: =I52*J52 -> 0.83203996 | M52: =RAND() -> 0.034764176 | N52: =IF(M52<EXP(-L52),0,IF(M52<EXP(-L52)*(1+L52),1,IF(M52<EXP(-L52)*(1+L52+L52^2/2),2,IF(M52<EXP(-L52)*(1+L52+L52^2/2+L52^3/6),3,4)))) -> 0 | O52: =N52*K52 -> 0 | P52: =Inputs!B14+(Inputs!D14-Inputs!B14)*BETAINV(RAND(),Model!H8,Model!I8) -> 0.38206307 | Q52: =Inputs!E14+(Inputs!G14-Inputs!E14)*BETAINV(RAND(),Model!J8,Model!K8) -> 0.63896832 | R52: =(Inputs!H14+(Inputs!J14-Inputs!H14)*BETAINV(RAND(),Model!L8,Model!M8))*Inputs!$C$6 -> 427203.95 | S52: =P52*Q52 -> 0.2441262 | T52: =RAND() -> 0.010686282 | U52: =IF(T52<EXP(-S52),0,IF(T52<EXP(-S52)*(1+S52),1,IF(T52<EXP(-S52)*(1+S52+S52^2/2),2,IF(T52<EXP(-S52)*(1+S52+S52^2/2+S52^3/6),3,4)))) -> 0 | V52: =U52*R52 -> 0 | W52: =Inputs!B15+(Inputs!D15-Inputs!B15)*BETAINV(RAND(),Model!H9,Model!I9) -> 2.365587 | X52: =Inputs!E15+(Inputs!G15-Inputs!E15)*BETAINV(RAND(),Model!J9,Model!K9) -> 0.47937853 | Y52: =(Inputs!H15+(Inputs!J15-Inputs!H15)*BETAINV(RAND(),Model!L9,Model!M9))*Inputs!$C$6 -> 34768.644 | Z52: =W52*X52 -> 1.1340116 | AA52: =RAND() -> 0.21862884 | AB52: =IF(AA52<EXP(-Z52),0,IF(AA52<EXP(-Z52)*(1+Z52),1,IF(AA52<EXP(-Z52)*(1+Z52+Z52^2/2),2,IF(AA52<EXP(-Z52)*(1+Z52+Z52^2/2+Z52^3/6),3,4)))) -> 0 | AC52: =AB52*Y52 -> 0 | AD52: =Inputs!B16+(Inputs!D16-Inputs!B16)*BETAINV(RAND(),Model!H10,Model!I10) -> 0.88991265 | AE52: =Inputs!E16+(Inputs!G16-Inputs!E16)*BETAINV(RAND(),Model!J10,Model!K10) -> 0.71951733 | AF52: =(Inputs!H16+(Inputs!J16-Inputs!H16)*BETAINV(RAND(),Model!L10,Model!M10))*Inputs!$C$6 -> 107177.79 | AG52: =AD52*AE52 -> 0.64030757 | AH52: =RAND() -> 0.66437613 | AI52: =IF(AH52<EXP(-AG52),0,IF(AH52<EXP(-AG52)*(1+AG52),1,IF(AH52<EXP(-AG52)*(1+AG52+AG52^2/2),2,IF(AH52<EXP(-AG52)*(1+AG52+AG52^2/2+AG52^3/6),3,4)))) -> 1 | AJ52: =AI52*AF52 -> 107177.79 | AK52: =H52+O52+V52+AC52+AJ52 -> 107177.79
B53: =Inputs!B12+(Inputs!D12-Inputs!B12)*BETAINV(RAND(),Model!H6,Model!I6) -> 5.0022033 | C53: =Inputs!E12+(Inputs!G12-Inputs!E12)*BETAINV(RAND(),Model!J6,Model!K6) -> 0.26736848 | D53: =(Inputs!H12+(Inputs!J12-Inputs!H12)*BETAINV(RAND(),Model!L6,Model!M6))*Inputs!$C$6 -> 11201.712 | E53: =B53*C53 -> 1.3374315 | F53: =RAND() -> 0.050148852 | G53: =IF(F53<EXP(-E53),0,IF(F53<EXP(-E53)*(1+E53),1,IF(F53<EXP(-E53)*(1+E53+E53^2/2),2,IF(F53<EXP(-E53)*(1+E53+E53^2/2+E53^3/6),3,4)))) -> 0 | H53: =G53*D53 -> 0 | I53: =Inputs!B13+(Inputs!D13-Inputs!B13)*BETAINV(RAND(),Model!H7,Model!I7) -> 1.1484695 | J53: =Inputs!E13+(Inputs!G13-Inputs!E13)*BETAINV(RAND(),Model!J7,Model!K7) -> 0.20101757 | K53: =(Inputs!H13+(Inputs!J13-Inputs!H13)*BETAINV(RAND(),Model!L7,Model!M7))*Inputs!$C$6 -> 21918.236 | L53: =I53*J53 -> 0.23086255 | M53: =RAND() -> 0.98568751 | N53: =IF(M53<EXP(-L53),0,IF(M53<EXP(-L53)*(1+L53),1,IF(M53<EXP(-L53)*(1+L53+L53^2/2),2,IF(M53<EXP(-L53)*(1+L53+L53^2/2+L53^3/6),3,4)))) -> 2 | O53: =N53*K53 -> 43836.472 | P53: =Inputs!B14+(Inputs!D14-Inputs!B14)*BETAINV(RAND(),Model!H8,Model!I8) -> 0.23601968 | Q53: =Inputs!E14+(Inputs!G14-Inputs!E14)*BETAINV(RAND(),Model!J8,Model!K8) -> 0.76480177 | R53: =(Inputs!H14+(Inputs!J14-Inputs!H14)*BETAINV(RAND(),Model!L8,Model!M8))*Inputs!$C$6 -> 305674.59 | S53: =P53*Q53 -> 0.18050827 | T53: =RAND() -> 0.12396393 | U53: =IF(T53<EXP(-S53),0,IF(T53<EXP(-S53)*(1+S53),1,IF(T53<EXP(-S53)*(1+S53+S53^2/2),2,IF(T53<EXP(-S53)*(1+S53+S53^2/2+S53^3/6),3,4)))) -> 0 | V53: =U53*R53 -> 0 | W53: =Inputs!B15+(Inputs!D15-Inputs!B15)*BETAINV(RAND(),Model!H9,Model!I9) -> 1.5864933 | X53: =Inputs!E15+(Inputs!G15-Inputs!E15)*BETAINV(RAND(),Model!J9,Model!K9) -> 0.42305384 | Y53: =(Inputs!H15+(Inputs!J15-Inputs!H15)*BETAINV(RAND(),Model!L9,Model!M9))*Inputs!$C$6 -> 15499.388 | Z53: =W53*X53 -> 0.67117209 | AA53: =RAND() -> 0.0085593258 | AB53: =IF(AA53<EXP(-Z53),0,IF(AA53<EXP(-Z53)*(1+Z53),1,IF(AA53<EXP(-Z53)*(1+Z53+Z53^2/2),2,IF(AA53<EXP(-Z53)*(1+Z53+Z53^2/2+Z53^3/6),3,4)))) -> 0 | AC53: =AB53*Y53 -> 0 | AD53: =Inputs!B16+(Inputs!D16-Inputs!B16)*BETAINV(RAND(),Model!H10,Model!I10) -> 0.49898014 | AE53: =Inputs!E16+(Inputs!G16-Inputs!E16)*BETAINV(RAND(),Model!J10,Model!K10) -> 0.65729116 | AF53: =(Inputs!H16+(Inputs!J16-Inputs!H16)*BETAINV(RAND(),Model!L10,Model!M10))*Inputs!$C$6 -> 46419.786 | AG53: =AD53*AE53 -> 0.32797524 | AH53: =RAND() -> 0.43624031 | AI53: =IF(AH53<EXP(-AG53),0,IF(AH53<EXP(-AG53)*(1+AG53),1,IF(AH53<EXP(-AG53)*(1+AG53+AG53^2/2),2,IF(AH53<EXP(-AG53)*(1+AG53+AG53^2/2+AG53^3/6),3,4)))) -> 0 | AJ53: =AI53*AF53 -> 0 | AK53: =H53+O53+V53+AC53+AJ53 -> 43836.472
B54: =Inputs!B12+(Inputs!D12-Inputs!B12)*BETAINV(RAND(),Model!H6,Model!I6) -> 2.755941 | C54: =Inputs!E12+(Inputs!G12-Inputs!E12)*BETAINV(RAND(),Model!J6,Model!K6) -> 0.33106516 | D54: =(Inputs!H12+(Inputs!J12-Inputs!H12)*BETAINV(RAND(),Model!L6,Model!M6))*Inputs!$C$6 -> 40443.549 | E54: =B54*C54 -> 0.91239604 | F54: =RAND() -> 0.67646205 | G54: =IF(F54<EXP(-E54),0,IF(F54<EXP(-E54)*(1+E54),1,IF(F54<EXP(-E54)*(1+E54+E54^2/2),2,IF(F54<EXP(-E54)*(1+E54+E54^2/2+E54^3/6),3,4)))) -> 1 | H54: =G54*D54 -> 40443.549 | I54: =Inputs!B13+(Inputs!D13-Inputs!B13)*BETAINV(RAND(),Model!H7,Model!I7) -> 2.0148385 | J54: =Inputs!E13+(Inputs!G13-Inputs!E13)*BETAINV(RAND(),Model!J7,Model!K7) -> 0.39805046 | K54: =(Inputs!H13+(Inputs!J13-Inputs!H13)*BETAINV(RAND(),Model!L7,Model!M7))*Inputs!$C$6 -> 36316.09 | L54: =I54*J54 -> 0.80200738 | M54: =RAND() -> 0.11714508 | N54: =IF(M54<EXP(-L54),0,IF(M54<EXP(-L54)*(1+L54),1,IF(M54<EXP(-L54)*(1+L54+L54^2/2),2,IF(M54<EXP(-L54)*(1+L54+L54^2/2+L54^3/6),3,4)))) -> 0 | O54: =N54*K54 -> 0 | P54: =Inputs!B14+(Inputs!D14-Inputs!B14)*BETAINV(RAND(),Model!H8,Model!I8) -> 0.31609246 | Q54: =Inputs!E14+(Inputs!G14-Inputs!E14)*BETAINV(RAND(),Model!J8,Model!K8) -> 0.73643247 | R54: =(Inputs!H14+(Inputs!J14-Inputs!H14)*BETAINV(RAND(),Model!L8,Model!M8))*Inputs!$C$6 -> 253219.47 | S54: =P54*Q54 -> 0.23278075 | T54: =RAND() -> 0.96320442 | U54: =IF(T54<EXP(-S54),0,IF(T54<EXP(-S54)*(1+S54),1,IF(T54<EXP(-S54)*(1+S54+S54^2/2),2,IF(T54<EXP(-S54)*(1+S54+S54^2/2+S54^3/6),3,4)))) -> 1 | V54: =U54*R54 -> 253219.47 | W54: =Inputs!B15+(Inputs!D15-Inputs!B15)*BETAINV(RAND(),Model!H9,Model!I9) -> 1.3991681 | X54: =Inputs!E15+(Inputs!G15-Inputs!E15)*BETAINV(RAND(),Model!J9,Model!K9) -> 0.41179593 | Y54: =(Inputs!H15+(Inputs!J15-Inputs!H15)*BETAINV(RAND(),Model!L9,Model!M9))*Inputs!$C$6 -> 38668.772 | Z54: =W54*X54 -> 0.5761717 | AA54: =RAND() -> 0.76118751 | AB54: =IF(AA54<EXP(-Z54),0,IF(AA54<EXP(-Z54)*(1+Z54),1,IF(AA54<EXP(-Z54)*(1+Z54+Z54^2/2),2,IF(AA54<EXP(-Z54)*(1+Z54+Z54^2/2+Z54^3/6),3,4)))) -> 1 | AC54: =AB54*Y54 -> 38668.772 | AD54: =Inputs!B16+(Inputs!D16-Inputs!B16)*BETAINV(RAND(),Model!H10,Model!I10) -> 0.42333264 | AE54: =Inputs!E16+(Inputs!G16-Inputs!E16)*BETAINV(RAND(),Model!J10,Model!K10) -> 0.54512555 | AF54: =(Inputs!H16+(Inputs!J16-Inputs!H16)*BETAINV(RAND(),Model!L10,Model!M10))*Inputs!$C$6 -> 89123.283 | AG54: =AD54*AE54 -> 0.23076944 | AH54: =RAND() -> 0.75203937 | AI54: =IF(AH54<EXP(-AG54),0,IF(AH54<EXP(-AG54)*(1+AG54),1,IF(AH54<EXP(-AG54)*(1+AG54+AG54^2/2),2,IF(AH54<EXP(-AG54)*(1+AG54+AG54^2/2+AG54^3/6),3,4)))) -> 0 | AJ54: =AI54*AF54 -> 0 | AK54: =H54+O54+V54+AC54+AJ54 -> 332331.8
B55: =Inputs!B12+(Inputs!D12-Inputs!B12)*BETAINV(RAND(),Model!H6,Model!I6) -> 1.6654074 | C55: =Inputs!E12+(Inputs!G12-Inputs!E12)*BETAINV(RAND(),Model!J6,Model!K6) -> 0.38170217 | D55: =(Inputs!H12+(Inputs!J12-Inputs!H12)*BETAINV(RAND(),Model!L6,Model!M6))*Inputs!$C$6 -> 41333.981 | E55: =B55*C55 -> 0.63568963 | F55: =RAND() -> 0.65137796 | G55: =IF(F55<EXP(-E55),0,IF(F55<EXP(-E55)*(1+E55),1,IF(F55<EXP(-E55)*(1+E55+E55^2/2),2,IF(F55<EXP(-E55)*(1+E55+E55^2/2+E55^3/6),3,4)))) -> 1 | H55: =G55*D55 -> 41333.981 | I55: =Inputs!B13+(Inputs!D13-Inputs!B13)*BETAINV(RAND(),Model!H7,Model!I7) -> 1.5887967 | J55: =Inputs!E13+(Inputs!G13-Inputs!E13)*BETAINV(RAND(),Model!J7,Model!K7) -> 0.33910524 | K55: =(Inputs!H13+(Inputs!J13-Inputs!H13)*BETAINV(RAND(),Model!L7,Model!M7))*Inputs!$C$6 -> 28046.957 | L55: =I55*J55 -> 0.5387693 | M55: =RAND() -> 0.95807016 | N55: =IF(M55<EXP(-L55),0,IF(M55<EXP(-L55)*(1+L55),1,IF(M55<EXP(-L55)*(1+L55+L55^2/2),2,IF(M55<EXP(-L55)*(1+L55+L55^2/2+L55^3/6),3,4)))) -> 2 | O55: =N55*K55 -> 56093.914 | P55: =Inputs!B14+(Inputs!D14-Inputs!B14)*BETAINV(RAND(),Model!H8,Model!I8) -> 0.3458521 | Q55: =Inputs!E14+(Inputs!G14-Inputs!E14)*BETAINV(RAND(),Model!J8,Model!K8) -> 0.64478881 | R55: =(Inputs!H14+(Inputs!J14-Inputs!H14)*BETAINV(RAND(),Model!L8,Model!M8))*Inputs!$C$6 -> 354439.93 | S55: =P55*Q55 -> 0.22300156 | T55: =RAND() -> 0.47756346 | U55: =IF(T55<EXP(-S55),0,IF(T55<EXP(-S55)*(1+S55),1,IF(T55<EXP(-S55)*(1+S55+S55^2/2),2,IF(T55<EXP(-S55)*(1+S55+S55^2/2+S55^3/6),3,4)))) -> 0 | V55: =U55*R55 -> 0 | W55: =Inputs!B15+(Inputs!D15-Inputs!B15)*BETAINV(RAND(),Model!H9,Model!I9) -> 1.4587482 | X55: =Inputs!E15+(Inputs!G15-Inputs!E15)*BETAINV(RAND(),Model!J9,Model!K9) -> 0.34124187 | Y55: =(Inputs!H15+(Inputs!J15-Inputs!H15)*BETAINV(RAND(),Model!L9,Model!M9))*Inputs!$C$6 -> 15249.282 | Z55: =W55*X55 -> 0.49778597 | AA55: =RAND() -> 0.79583463 | AB55: =IF(AA55<EXP(-Z55),0,IF(AA55<EXP(-Z55)*(1+Z55),1,IF(AA55<EXP(-Z55)*(1+Z55+Z55^2/2),2,IF(AA55<EXP(-Z55)*(1+Z55+Z55^2/2+Z55^3/6),3,4)))) -> 1 | AC55: =AB55*Y55 -> 15249.282 | AD55: =Inputs!B16+(Inputs!D16-Inputs!B16)*BETAINV(RAND(),Model!H10,Model!I10) -> 1.1652503 | AE55: =Inputs!E16+(Inputs!G16-Inputs!E16)*BETAINV(RAND(),Model!J10,Model!K10) -> 0.61516526 | AF55: =(Inputs!H16+(Inputs!J16-Inputs!H16)*BETAINV(RAND(),Model!L10,Model!M10))*Inputs!$C$6 -> 59517.534 | AG55: =AD55*AE55 -> 0.71682151 | AH55: =RAND() -> 0.8546053 | AI55: =IF(AH55<EXP(-AG55),0,IF(AH55<EXP(-AG55)*(1+AG55),1,IF(AH55<EXP(-AG55)*(1+AG55+AG55^2/2),2,IF(AH55<EXP(-AG55)*(1+AG55+AG55^2/2+AG55^3/6),3,4)))) -> 2 | AJ55: =AI55*AF55 -> 119035.07 | AK55: =H55+O55+V55+AC55+AJ55 -> 231712.25
B56: =Inputs!B12+(Inputs!D12-Inputs!B12)*BETAINV(RAND(),Model!H6,Model!I6) -> 2.5408518 | C56: =Inputs!E12+(Inputs!G12-Inputs!E12)*BETAINV(RAND(),Model!J6,Model!K6) -> 0.35337927 | D56: =(Inputs!H12+(Inputs!J12-Inputs!H12)*BETAINV(RAND(),Model!L6,Model!M6))*Inputs!$C$6 -> 55160.952 | E56: =B56*C56 -> 0.89788435 | F56: =RAND() -> 0.34502758 | G56: =IF(F56<EXP(-E56),0,IF(F56<EXP(-E56)*(1+E56),1,IF(F56<EXP(-E56)*(1+E56+E56^2/2),2,IF(F56<EXP(-E56)*(1+E56+E56^2/2+E56^3/6),3,4)))) -> 0 | H56: =G56*D56 -> 0 | I56: =Inputs!B13+(Inputs!D13-Inputs!B13)*BETAINV(RAND(),Model!H7,Model!I7) -> 3.7630431 | J56: =Inputs!E13+(Inputs!G13-Inputs!E13)*BETAINV(RAND(),Model!J7,Model!K7) -> 0.35951835 | K56: =(Inputs!H13+(Inputs!J13-Inputs!H13)*BETAINV(RAND(),Model!L7,Model!M7))*Inputs!$C$6 -> 42217.28 | L56: =I56*J56 -> 1.3528831 | M56: =RAND() -> 0.68439554 | N56: =IF(M56<EXP(-L56),0,IF(M56<EXP(-L56)*(1+L56),1,IF(M56<EXP(-L56)*(1+L56+L56^2/2),2,IF(M56<EXP(-L56)*(1+L56+L56^2/2+L56^3/6),3,4)))) -> 2 | O56: =N56*K56 -> 84434.561 | P56: =Inputs!B14+(Inputs!D14-Inputs!B14)*BETAINV(RAND(),Model!H8,Model!I8) -> 0.15477108 | Q56: =Inputs!E14+(Inputs!G14-Inputs!E14)*BETAINV(RAND(),Model!J8,Model!K8) -> 0.44771734 | R56: =(Inputs!H14+(Inputs!J14-Inputs!H14)*BETAINV(RAND(),Model!L8,Model!M8))*Inputs!$C$6 -> 328352.65 | S56: =P56*Q56 -> 0.069293697 | T56: =RAND() -> 0.75818862 | U56: =IF(T56<EXP(-S56),0,IF(T56<EXP(-S56)*(1+S56),1,IF(T56<EXP(-S56)*(1+S56+S56^2/2),2,IF(T56<EXP(-S56)*(1+S56+S56^2/2+S56^3/6),3,4)))) -> 0 | V56: =U56*R56 -> 0 | W56: =Inputs!B15+(Inputs!D15-Inputs!B15)*BETAINV(RAND(),Model!H9,Model!I9) -> 0.84138022 | X56: =Inputs!E15+(Inputs!G15-Inputs!E15)*BETAINV(RAND(),Model!J9,Model!K9) -> 0.39775335 | Y56: =(Inputs!H15+(Inputs!J15-Inputs!H15)*BETAINV(RAND(),Model!L9,Model!M9))*Inputs!$C$6 -> 34243.233 | Z56: =W56*X56 -> 0.3346618 | AA56: =RAND() -> 0.29725148 | AB56: =IF(AA56<EXP(-Z56),0,IF(AA56<EXP(-Z56)*(1+Z56),1,IF(AA56<EXP(-Z56)*(1+Z56+Z56^2/2),2,IF(AA56<EXP(-Z56)*(1+Z56+Z56^2/2+Z56^3/6),3,4)))) -> 0 | AC56: =AB56*Y56 -> 0 | AD56: =Inputs!B16+(Inputs!D16-Inputs!B16)*BETAINV(RAND(),Model!H10,Model!I10) -> 0.27038542 | AE56: =Inputs!E16+(Inputs!G16-Inputs!E16)*BETAINV(RAND(),Model!J10,Model!K10) -> 0.63864132 | AF56: =(Inputs!H16+(Inputs!J16-Inputs!H16)*BETAINV(RAND(),Model!L10,Model!M10))*Inputs!$C$6 -> 73809.502 | AG56: =AD56*AE56 -> 0.1726793 | AH56: =RAND() -> 0.11898905 | AI56: =IF(AH56<EXP(-AG56),0,IF(AH56<EXP(-AG56)*(1+AG56),1,IF(AH56<EXP(-AG56)*(1+AG56+AG56^2/2),2,IF(AH56<EXP(-AG56)*(1+AG56+AG56^2/2+AG56^3/6),3,4)))) -> 0 | AJ56: =AI56*AF56 -> 0 | AK56: =H56+O56+V56+AC56+AJ56 -> 84434.561
B57: =Inputs!B12+(Inputs!D12-Inputs!B12)*BETAINV(RAND(),Model!H6,Model!I6) -> 1.9151836 | C57: =Inputs!E12+(Inputs!G12-Inputs!E12)*BETAINV(RAND(),Model!J6,Model!K6) -> 0.28918171 | D57: =(Inputs!H12+(Inputs!J12-Inputs!H12)*BETAINV(RAND(),Model!L6,Model!M6))*Inputs!$C$6 -> 60824.012 | E57: =B57*C57 -> 0.55383606 | F57: =RAND() -> 0.66717541 | G57: =IF(F57<EXP(-E57),0,IF(F57<EXP(-E57)*(1+E57),1,IF(F57<EXP(-E57)*(1+E57+E57^2/2),2,IF(F57<EXP(-E57)*(1+E57+E57^2/2+E57^3/6),3,4)))) -> 1 | H57: =G57*D57 -> 60824.012 | I57: =Inputs!B13+(Inputs!D13-Inputs!B13)*BETAINV(RAND(),Model!H7,Model!I7) -> 1.6142687 | J57: =Inputs!E13+(Inputs!G13-Inputs!E13)*BETAINV(RAND(),Model!J7,Model!K7) -> 0.3536874 | K57: =(Inputs!H13+(Inputs!J13-Inputs!H13)*BETAINV(RAND(),Model!L7,Model!M7))*Inputs!$C$6 -> 34321.777 | L57: =I57*J57 -> 0.5709465 | M57: =RAND() -> 0.48921331 | N57: =IF(M57<EXP(-L57),0,IF(M57<EXP(-L57)*(1+L57),1,IF(M57<EXP(-L57)*(1+L57+L57^2/2),2,IF(M57<EXP(-L57)*(1+L57+L57^2/2+L57^3/6),3,4)))) -> 0 | O57: =N57*K57 -> 0 | P57: =Inputs!B14+(Inputs!D14-Inputs!B14)*BETAINV(RAND(),Model!H8,Model!I8) -> 0.65516203 | Q57: =Inputs!E14+(Inputs!G14-Inputs!E14)*BETAINV(RAND(),Model!J8,Model!K8) -> 0.43508102 | R57: =(Inputs!H14+(Inputs!J14-Inputs!H14)*BETAINV(RAND(),Model!L8,Model!M8))*Inputs!$C$6 -> 382828.84 | S57: =P57*Q57 -> 0.28504856 | T57: =RAND() -> 0.7267171 | U57: =IF(T57<EXP(-S57),0,IF(T57<EXP(-S57)*(1+S57),1,IF(T57<EXP(-S57)*(1+S57+S57^2/2),2,IF(T57<EXP(-S57)*(1+S57+S57^2/2+S57^3/6),3,4)))) -> 0 | V57: =U57*R57 -> 0 | W57: =Inputs!B15+(Inputs!D15-Inputs!B15)*BETAINV(RAND(),Model!H9,Model!I9) -> 1.7358141 | X57: =Inputs!E15+(Inputs!G15-Inputs!E15)*BETAINV(RAND(),Model!J9,Model!K9) -> 0.29033913 | Y57: =(Inputs!H15+(Inputs!J15-Inputs!H15)*BETAINV(RAND(),Model!L9,Model!M9))*Inputs!$C$6 -> 22442.407 | Z57: =W57*X57 -> 0.50397476 | AA57: =RAND() -> 0.27611576 | AB57: =IF(AA57<EXP(-Z57),0,IF(AA57<EXP(-Z57)*(1+Z57),1,IF(AA57<EXP(-Z57)*(1+Z57+Z57^2/2),2,IF(AA57<EXP(-Z57)*(1+Z57+Z57^2/2+Z57^3/6),3,4)))) -> 0 | AC57: =AB57*Y57 -> 0 | AD57: =Inputs!B16+(Inputs!D16-Inputs!B16)*BETAINV(RAND(),Model!H10,Model!I10) -> 0.64798718 | AE57: =Inputs!E16+(Inputs!G16-Inputs!E16)*BETAINV(RAND(),Model!J10,Model!K10) -> 0.6223809 | AF57: =(Inputs!H16+(Inputs!J16-Inputs!H16)*BETAINV(RAND(),Model!L10,Model!M10))*Inputs!$C$6 -> 72192.86 | AG57: =AD57*AE57 -> 0.40329484 | AH57: =RAND() -> 0.29235053 | AI57: =IF(AH57<EXP(-AG57),0,IF(AH57<EXP(-AG57)*(1+AG57),1,IF(AH57<EXP(-AG57)*(1+AG57+AG57^2/2),2,IF(AH57<EXP(-AG57)*(1+AG57+AG57^2/2+AG57^3/6),3,4)))) -> 0 | AJ57: =AI57*AF57 -> 0 | AK57: =H57+O57+V57+AC57+AJ57 -> 60824.012
B58: =Inputs!B12+(Inputs!D12-Inputs!B12)*BETAINV(RAND(),Model!H6,Model!I6) -> 2.889415 | C58: =Inputs!E12+(Inputs!G12-Inputs!E12)*BETAINV(RAND(),Model!J6,Model!K6) -> 0.28546597 | D58: =(Inputs!H12+(Inputs!J12-Inputs!H12)*BETAINV(RAND(),Model!L6,Model!M6))*Inputs!$C$6 -> 28800.396 | E58: =B58*C58 -> 0.82482967 | F58: =RAND() -> 0.90766478 | G58: =IF(F58<EXP(-E58),0,IF(F58<EXP(-E58)*(1+E58),1,IF(F58<EXP(-E58)*(1+E58+E58^2/2),2,IF(F58<EXP(-E58)*(1+E58+E58^2/2+E58^3/6),3,4)))) -> 2 | H58: =G58*D58 -> 57600.792 | I58: =Inputs!B13+(Inputs!D13-Inputs!B13)*BETAINV(RAND(),Model!H7,Model!I7) -> 2.1630035 | J58: =Inputs!E13+(Inputs!G13-Inputs!E13)*BETAINV(RAND(),Model!J7,Model!K7) -> 0.32387794 | K58: =(Inputs!H13+(Inputs!J13-Inputs!H13)*BETAINV(RAND(),Model!L7,Model!M7))*Inputs!$C$6 -> 16974.584 | L58: =I58*J58 -> 0.70054912 | M58: =RAND() -> 0.29120199 | N58: =IF(M58<EXP(-L58),0,IF(M58<EXP(-L58)*(1+L58),1,IF(M58<EXP(-L58)*(1+L58+L58^2/2),2,IF(M58<EXP(-L58)*(1+L58+L58^2/2+L58^3/6),3,4)))) -> 0 | O58: =N58*K58 -> 0 | P58: =Inputs!B14+(Inputs!D14-Inputs!B14)*BETAINV(RAND(),Model!H8,Model!I8) -> 0.18608809 | Q58: =Inputs!E14+(Inputs!G14-Inputs!E14)*BETAINV(RAND(),Model!J8,Model!K8) -> 0.52895801 | R58: =(Inputs!H14+(Inputs!J14-Inputs!H14)*BETAINV(RAND(),Model!L8,Model!M8))*Inputs!$C$6 -> 233378.78 | S58: =P58*Q58 -> 0.098432785 | T58: =RAND() -> 0.38496707 | U58: =IF(T58<EXP(-S58),0,IF(T58<EXP(-S58)*(1+S58),1,IF(T58<EXP(-S58)*(1+S58+S58^2/2),2,IF(T58<EXP(-S58)*(1+S58+S58^2/2+S58^3/6),3,4)))) -> 0 | V58: =U58*R58 -> 0 | W58: =Inputs!B15+(Inputs!D15-Inputs!B15)*BETAINV(RAND(),Model!H9,Model!I9) -> 2.5685811 | X58: =Inputs!E15+(Inputs!G15-Inputs!E15)*BETAINV(RAND(),Model!J9,Model!K9) -> 0.45216222 | Y58: =(Inputs!H15+(Inputs!J15-Inputs!H15)*BETAINV(RAND(),Model!L9,Model!M9))*Inputs!$C$6 -> 27487.237 | Z58: =W58*X58 -> 1.1614153 | AA58: =RAND() -> 0.10935868 | AB58: =IF(AA58<EXP(-Z58),0,IF(AA58<EXP(-Z58)*(1+Z58),1,IF(AA58<EXP(-Z58)*(1+Z58+Z58^2/2),2,IF(AA58<EXP(-Z58)*(1+Z58+Z58^2/2+Z58^3/6),3,4)))) -> 0 | AC58: =AB58*Y58 -> 0 | AD58: =Inputs!B16+(Inputs!D16-Inputs!B16)*BETAINV(RAND(),Model!H10,Model!I10) -> 0.50030056 | AE58: =Inputs!E16+(Inputs!G16-Inputs!E16)*BETAINV(RAND(),Model!J10,Model!K10) -> 0.61527331 | AF58: =(Inputs!H16+(Inputs!J16-Inputs!H16)*BETAINV(RAND(),Model!L10,Model!M10))*Inputs!$C$6 -> 78728.837 | AG58: =AD58*AE58 -> 0.30782158 | AH58: =RAND() -> 0.029141095 | AI58: =IF(AH58<EXP(-AG58),0,IF(AH58<EXP(-AG58)*(1+AG58),1,IF(AH58<EXP(-AG58)*(1+AG58+AG58^2/2),2,IF(AH58<EXP(-AG58)*(1+AG58+AG58^2/2+AG58^3/6),3,4)))) -> 0 | AJ58: =AI58*AF58 -> 0 | AK58: =H58+O58+V58+AC58+AJ58 -> 57600.792
B59: =Inputs!B12+(Inputs!D12-Inputs!B12)*BETAINV(RAND(),Model!H6,Model!I6) -> 5.675765 | C59: =Inputs!E12+(Inputs!G12-Inputs!E12)*BETAINV(RAND(),Model!J6,Model!K6) -> 0.31281194 | D59: =(Inputs!H12+(Inputs!J12-Inputs!H12)*BETAINV(RAND(),Model!L6,Model!M6))*Inputs!$C$6 -> 42402.546 | E59: =B59*C59 -> 1.7754471 | F59: =RAND() -> 0.94842253 | G59: =IF(F59<EXP(-E59),0,IF(F59<EXP(-E59)*(1+E59),1,IF(F59<EXP(-E59)*(1+E59+E59^2/2),2,IF(F59<EXP(-E59)*(1+E59+E59^2/2+E59^3/6),3,4)))) -> 4 | H59: =G59*D59 -> 169610.18 | I59: =Inputs!B13+(Inputs!D13-Inputs!B13)*BETAINV(RAND(),Model!H7,Model!I7) -> 3.1617889 | J59: =Inputs!E13+(Inputs!G13-Inputs!E13)*BETAINV(RAND(),Model!J7,Model!K7) -> 0.29724438 | K59: =(Inputs!H13+(Inputs!J13-Inputs!H13)*BETAINV(RAND(),Model!L7,Model!M7))*Inputs!$C$6 -> 54809.026 | L59: =I59*J59 -> 0.93982398 | M59: =RAND() -> 0.40673613 | N59: =IF(M59<EXP(-L59),0,IF(M59<EXP(-L59)*(1+L59),1,IF(M59<EXP(-L59)*(1+L59+L59^2/2),2,IF(M59<EXP(-L59)*(1+L59+L59^2/2+L59^3/6),3,4)))) -> 1 | O59: =N59*K59 -> 54809.026 | P59: =Inputs!B14+(Inputs!D14-Inputs!B14)*BETAINV(RAND(),Model!H8,Model!I8) -> 0.26139272 | Q59: =Inputs!E14+(Inputs!G14-Inputs!E14)*BETAINV(RAND(),Model!J8,Model!K8) -> 0.69024709 | R59: =(Inputs!H14+(Inputs!J14-Inputs!H14)*BETAINV(RAND(),Model!L8,Model!M8))*Inputs!$C$6 -> 396456.95 | S59: =P59*Q59 -> 0.18042557 | T59: =RAND() -> 0.50534055 | U59: =IF(T59<EXP(-S59),0,IF(T59<EXP(-S59)*(1+S59),1,IF(T59<EXP(-S59)*(1+S59+S59^2/2),2,IF(T59<EXP(-S59)*(1+S59+S59^2/2+S59^3/6),3,4)))) -> 0 | V59: =U59*R59 -> 0 | W59: =Inputs!B15+(Inputs!D15-Inputs!B15)*BETAINV(RAND(),Model!H9,Model!I9) -> 1.2579025 | X59: =Inputs!E15+(Inputs!G15-Inputs!E15)*BETAINV(RAND(),Model!J9,Model!K9) -> 0.50665082 | Y59: =(Inputs!H15+(Inputs!J15-Inputs!H15)*BETAINV(RAND(),Model!L9,Model!M9))*Inputs!$C$6 -> 49547.986 | Z59: =W59*X59 -> 0.63731731 | AA59: =RAND() -> 0.85045062 | AB59: =IF(AA59<EXP(-Z59),0,IF(AA59<EXP(-Z59)*(1+Z59),1,IF(AA59<EXP(-Z59)*(1+Z59+Z59^2/2),2,IF(AA59<EXP(-Z59)*(1+Z59+Z59^2/2+Z59^3/6),3,4)))) -> 1 | AC59: =AB59*Y59 -> 49547.986 | AD59: =Inputs!B16+(Inputs!D16-Inputs!B16)*BETAINV(RAND(),Model!H10,Model!I10) -> 1.0350443 | AE59: =Inputs!E16+(Inputs!G16-Inputs!E16)*BETAINV(RAND(),Model!J10,Model!K10) -> 0.65880479 | AF59: =(Inputs!H16+(Inputs!J16-Inputs!H16)*BETAINV(RAND(),Model!L10,Model!M10))*Inputs!$C$6 -> 72397.515 | AG59: =AD59*AE59 -> 0.68189213 | AH59: =RAND() -> 0.095561731 | AI59: =IF(AH59<EXP(-AG59),0,IF(AH59<EXP(-AG59)*(1+AG59),1,IF(AH59<EXP(-AG59)*(1+AG59+AG59^2/2),2,IF(AH59<EXP(-AG59)*(1+AG59+AG59^2/2+AG59^3/6),3,4)))) -> 0 | AJ59: =AI59*AF59 -> 0 | AK59: =H59+O59+V59+AC59+AJ59 -> 273967.2
B60: =Inputs!B12+(Inputs!D12-Inputs!B12)*BETAINV(RAND(),Model!H6,Model!I6) -> 2.2801911 | C60: =Inputs!E12+(Inputs!G12-Inputs!E12)*BETAINV(RAND(),Model!J6,Model!K6) -> 0.35567027 | D60: =(Inputs!H12+(Inputs!J12-Inputs!H12)*BETAINV(RAND(),Model!L6,Model!M6))*Inputs!$C$6 -> 19581.83 | E60: =B60*C60 -> 0.81099617 | F60: =RAND() -> 0.052089552 | G60: =IF(F60<EXP(-E60),0,IF(F60<EXP(-E60)*(1+E60),1,IF(F60<EXP(-E60)*(1+E60+E60^2/2),2,IF(F60<EXP(-E60)*(1+E60+E60^2/2+E60^3/6),3,4)))) -> 0 | H60: =G60*D60 -> 0 | I60: =Inputs!B13+(Inputs!D13-Inputs!B13)*BETAINV(RAND(),Model!H7,Model!I7) -> 1.8672973 | J60: =Inputs!E13+(Inputs!G13-Inputs!E13)*BETAINV(RAND(),Model!J7,Model!K7) -> 0.17958701 | K60: =(Inputs!H13+(Inputs!J13-Inputs!H13)*BETAINV(RAND(),Model!L7,Model!M7))*Inputs!$C$6 -> 30706.861 | L60: =I60*J60 -> 0.33534234 | M60: =RAND() -> 0.9729942 | N60: =IF(M60<EXP(-L60),0,IF(M60<EXP(-L60)*(1+L60),1,IF(M60<EXP(-L60)*(1+L60+L60^2/2),2,IF(M60<EXP(-L60)*(1+L60+L60^2/2+L60^3/6),3,4)))) -> 2 | O60: =N60*K60 -> 61413.723 | P60: =Inputs!B14+(Inputs!D14-Inputs!B14)*BETAINV(RAND(),Model!H8,Model!I8) -> 0.2098291 | Q60: =Inputs!E14+(Inputs!G14-Inputs!E14)*BETAINV(RAND(),Model!J8,Model!K8) -> 0.53189792 | R60: =(Inputs!H14+(Inputs!J14-Inputs!H14)*BETAINV(RAND(),Model!L8,Model!M8))*Inputs!$C$6 -> 236470.2 | S60: =P60*Q60 -> 0.11160766 | T60: =RAND() -> 0.36165967 | U60: =IF(T60<EXP(-S60),0,IF(T60<EXP(-S60)*(1+S60),1,IF(T60<EXP(-S60)*(1+S60+S60^2/2),2,IF(T60<EXP(-S60)*(1+S60+S60^2/2+S60^3/6),3,4)))) -> 0 | V60: =U60*R60 -> 0 | W60: =Inputs!B15+(Inputs!D15-Inputs!B15)*BETAINV(RAND(),Model!H9,Model!I9) -> 1.0842595 | X60: =Inputs!E15+(Inputs!G15-Inputs!E15)*BETAINV(RAND(),Model!J9,Model!K9) -> 0.26525601 | Y60: =(Inputs!H15+(Inputs!J15-Inputs!H15)*BETAINV(RAND(),Model!L9,Model!M9))*Inputs!$C$6 -> 12113.14 | Z60: =W60*X60 -> 0.28760636 | AA60: =RAND() -> 0.67735018 | AB60: =IF(AA60<EXP(-Z60),0,IF(AA60<EXP(-Z60)*(1+Z60),1,IF(AA60<EXP(-Z60)*(1+Z60+Z60^2/2),2,IF(AA60<EXP(-Z60)*(1+Z60+Z60^2/2+Z60^3/6),3,4)))) -> 0 | AC60: =AB60*Y60 -> 0 | AD60: =Inputs!B16+(Inputs!D16-Inputs!B16)*BETAINV(RAND(),Model!H10,Model!I10) -> 0.74040915 | AE60: =Inputs!E16+(Inputs!G16-Inputs!E16)*BETAINV(RAND(),Model!J10,Model!K10) -> 0.63449757 | AF60: =(Inputs!H16+(Inputs!J16-Inputs!H16)*BETAINV(RAND(),Model!L10,Model!M10))*Inputs!$C$6 -> 105924.2 | AG60: =AD60*AE60 -> 0.4697878 | AH60: =RAND() -> 0.95348533 | AI60: =IF(AH60<EXP(-AG60),0,IF(AH60<EXP(-AG60)*(1+AG60),1,IF(AH60<EXP(-AG60)*(1+AG60+AG60^2/2),2,IF(AH60<EXP(-AG60)*(1+AG60+AG60^2/2+AG60^3/6),3,4)))) -> 2 | AJ60: =AI60*AF60 -> 211848.39 | AK60: =H60+O60+V60+AC60+AJ60 -> 273262.11
B61: =Inputs!B12+(Inputs!D12-Inputs!B12)*BETAINV(RAND(),Model!H6,Model!I6) -> 5.2835235 | C61: =Inputs!E12+(Inputs!G12-Inputs!E12)*BETAINV(RAND(),Model!J6,Model!K6) -> 0.27789961 | D61: =(Inputs!H12+(Inputs!J12-Inputs!H12)*BETAINV(RAND(),Model!L6,Model!M6))*Inputs!$C$6 -> 13267.097 | E61: =B61*C61 -> 1.4682891 | F61: =RAND() -> 0.7220597 | G61: =IF(F61<EXP(-E61),0,IF(F61<EXP(-E61)*(1+E61),1,IF(F61<EXP(-E61)*(1+E61+E61^2/2),2,IF(F61<EXP(-E61)*(1+E61+E61^2/2+E61^3/6),3,4)))) -> 2 | H61: =G61*D61 -> 26534.195 | I61: =Inputs!B13+(Inputs!D13-Inputs!B13)*BETAINV(RAND(),Model!H7,Model!I7) -> 3.6813592 | J61: =Inputs!E13+(Inputs!G13-Inputs!E13)*BETAINV(RAND(),Model!J7,Model!K7) -> 0.16952798 | K61: =(Inputs!H13+(Inputs!J13-Inputs!H13)*BETAINV(RAND(),Model!L7,Model!M7))*Inputs!$C$6 -> 38440.934 | L61: =I61*J61 -> 0.62409339 | M61: =RAND() -> 0.37888714 | N61: =IF(M61<EXP(-L61),0,IF(M61<EXP(-L61)*(1+L61),1,IF(M61<EXP(-L61)*(1+L61+L61^2/2),2,IF(M61<EXP(-L61)*(1+L61+L61^2/2+L61^3/6),3,4)))) -> 0 | O61: =N61*K61 -> 0 | P61: =Inputs!B14+(Inputs!D14-Inputs!B14)*BETAINV(RAND(),Model!H8,Model!I8) -> 0.25354075 | Q61: =Inputs!E14+(Inputs!G14-Inputs!E14)*BETAINV(RAND(),Model!J8,Model!K8) -> 0.45626316 | R61: =(Inputs!H14+(Inputs!J14-Inputs!H14)*BETAINV(RAND(),Model!L8,Model!M8))*Inputs!$C$6 -> 482934.55 | S61: =P61*Q61 -> 0.1156813 | T61: =RAND() -> 0.40447461 | U61: =IF(T61<EXP(-S61),0,IF(T61<EXP(-S61)*(1+S61),1,IF(T61<EXP(-S61)*(1+S61+S61^2/2),2,IF(T61<EXP(-S61)*(1+S61+S61^2/2+S61^3/6),3,4)))) -> 0 | V61: =U61*R61 -> 0 | W61: =Inputs!B15+(Inputs!D15-Inputs!B15)*BETAINV(RAND(),Model!H9,Model!I9) -> 1.6616309 | X61: =Inputs!E15+(Inputs!G15-Inputs!E15)*BETAINV(RAND(),Model!J9,Model!K9) -> 0.38959496 | Y61: =(Inputs!H15+(Inputs!J15-Inputs!H15)*BETAINV(RAND(),Model!L9,Model!M9))*Inputs!$C$6 -> 21036.138 | Z61: =W61*X61 -> 0.64736302 | AA61: =RAND() -> 0.87965673 | AB61: =IF(AA61<EXP(-Z61),0,IF(AA61<EXP(-Z61)*(1+Z61),1,IF(AA61<EXP(-Z61)*(1+Z61+Z61^2/2),2,IF(AA61<EXP(-Z61)*(1+Z61+Z61^2/2+Z61^3/6),3,4)))) -> 2 | AC61: =AB61*Y61 -> 42072.275 | AD61: =Inputs!B16+(Inputs!D16-Inputs!B16)*BETAINV(RAND(),Model!H10,Model!I10) -> 0.63890127 | AE61: =Inputs!E16+(Inputs!G16-Inputs!E16)*BETAINV(RAND(),Model!J10,Model!K10) -> 0.57556727 | AF61: =(Inputs!H16+(Inputs!J16-Inputs!H16)*BETAINV(RAND(),Model!L10,Model!M10))*Inputs!$C$6 -> 108336.12 | AG61: =AD61*AE61 -> 0.36773066 | AH61: =RAND() -> 0.17282114 | AI61: =IF(AH61<EXP(-AG61),0,IF(AH61<EXP(-AG61)*(1+AG61),1,IF(AH61<EXP(-AG61)*(1+AG61+AG61^2/2),2,IF(AH61<EXP(-AG61)*(1+AG61+AG61^2/2+AG61^3/6),3,4)))) -> 0 | AJ61: =AI61*AF61 -> 0 | AK61: =H61+O61+V61+AC61+AJ61 -> 68606.47
B62: =Inputs!B12+(Inputs!D12-Inputs!B12)*BETAINV(RAND(),Model!H6,Model!I6) -> 3.9218113 | C62: =Inputs!E12+(Inputs!G12-Inputs!E12)*BETAINV(RAND(),Model!J6,Model!K6) -> 0.212973 | D62: =(Inputs!H12+(Inputs!J12-Inputs!H12)*BETAINV(RAND(),Model!L6,Model!M6))*Inputs!$C$6 -> 16753.933 | E62: =B62*C62 -> 0.83523994 | F62: =RAND() -> 0.71683118 | G62: =IF(F62<EXP(-E62),0,IF(F62<EXP(-E62)*(1+E62),1,IF(F62<EXP(-E62)*(1+E62+E62^2/2),2,IF(F62<EXP(-E62)*(1+E62+E62^2/2+E62^3/6),3,4)))) -> 1 | H62: =G62*D62 -> 16753.933 | I62: =Inputs!B13+(Inputs!D13-Inputs!B13)*BETAINV(RAND(),Model!H7,Model!I7) -> 3.6296787 | J62: =Inputs!E13+(Inputs!G13-Inputs!E13)*BETAINV(RAND(),Model!J7,Model!K7) -> 0.31714312 | K62: =(Inputs!H13+(Inputs!J13-Inputs!H13)*BETAINV(RAND(),Model!L7,Model!M7))*Inputs!$C$6 -> 67519.599 | L62: =I62*J62 -> 1.1511276 | M62: =RAND() -> 0.56294328 | N62: =IF(M62<EXP(-L62),0,IF(M62<EXP(-L62)*(1+L62),1,IF(M62<EXP(-L62)*(1+L62+L62^2/2),2,IF(M62<EXP(-L62)*(1+L62+L62^2/2+L62^3/6),3,4)))) -> 1 | O62: =N62*K62 -> 67519.599 | P62: =Inputs!B14+(Inputs!D14-Inputs!B14)*BETAINV(RAND(),Model!H8,Model!I8) -> 0.40377978 | Q62: =Inputs!E14+(Inputs!G14-Inputs!E14)*BETAINV(RAND(),Model!J8,Model!K8) -> 0.54167188 | R62: =(Inputs!H14+(Inputs!J14-Inputs!H14)*BETAINV(RAND(),Model!L8,Model!M8))*Inputs!$C$6 -> 465278.78 | S62: =P62*Q62 -> 0.21871615 | T62: =RAND() -> 0.72642237 | U62: =IF(T62<EXP(-S62),0,IF(T62<EXP(-S62)*(1+S62),1,IF(T62<EXP(-S62)*(1+S62+S62^2/2),2,IF(T62<EXP(-S62)*(1+S62+S62^2/2+S62^3/6),3,4)))) -> 0 | V62: =U62*R62 -> 0 | W62: =Inputs!B15+(Inputs!D15-Inputs!B15)*BETAINV(RAND(),Model!H9,Model!I9) -> 1.0139817 | X62: =Inputs!E15+(Inputs!G15-Inputs!E15)*BETAINV(RAND(),Model!J9,Model!K9) -> 0.47681105 | Y62: =(Inputs!H15+(Inputs!J15-Inputs!H15)*BETAINV(RAND(),Model!L9,Model!M9))*Inputs!$C$6 -> 19955.791 | Z62: =W62*X62 -> 0.4834777 | AA62: =RAND() -> 0.64087925 | AB62: =IF(AA62<EXP(-Z62),0,IF(AA62<EXP(-Z62)*(1+Z62),1,IF(AA62<EXP(-Z62)*(1+Z62+Z62^2/2),2,IF(AA62<EXP(-Z62)*(1+Z62+Z62^2/2+Z62^3/6),3,4)))) -> 1 | AC62: =AB62*Y62 -> 19955.791 | AD62: =Inputs!B16+(Inputs!D16-Inputs!B16)*BETAINV(RAND(),Model!H10,Model!I10) -> 0.54172465 | AE62: =Inputs!E16+(Inputs!G16-Inputs!E16)*BETAINV(RAND(),Model!J10,Model!K10) -> 0.66091721 | AF62: =(Inputs!H16+(Inputs!J16-Inputs!H16)*BETAINV(RAND(),Model!L10,Model!M10))*Inputs!$C$6 -> 101620.84 | AG62: =AD62*AE62 -> 0.35803514 | AH62: =RAND() -> 0.79178954 | AI62: =IF(AH62<EXP(-AG62),0,IF(AH62<EXP(-AG62)*(1+AG62),1,IF(AH62<EXP(-AG62)*(1+AG62+AG62^2/2),2,IF(AH62<EXP(-AG62)*(1+AG62+AG62^2/2+AG62^3/6),3,4)))) -> 1 | AJ62: =AI62*AF62 -> 101620.84 | AK62: =H62+O62+V62+AC62+AJ62 -> 205850.16
B63: =Inputs!B12+(Inputs!D12-Inputs!B12)*BETAINV(RAND(),Model!H6,Model!I6) -> 2.3116742 | C63: =Inputs!E12+(Inputs!G12-Inputs!E12)*BETAINV(RAND(),Model!J6,Model!K6) -> 0.29480839 | D63: =(Inputs!H12+(Inputs!J12-Inputs!H12)*BETAINV(RAND(),Model!L6,Model!M6))*Inputs!$C$6 -> 30493.447 | E63: =B63*C63 -> 0.68150096 | F63: =RAND() -> 0.042057766 | G63: =IF(F63<EXP(-E63),0,IF(F63<EXP(-E63)*(1+E63),1,IF(F63<EXP(-E63)*(1+E63+E63^2/2),2,IF(F63<EXP(-E63)*(1+E63+E63^2/2+E63^3/6),3,4)))) -> 0 | H63: =G63*D63 -> 0 | I63: =Inputs!B13+(Inputs!D13-Inputs!B13)*BETAINV(RAND(),Model!H7,Model!I7) -> 2.5160811 | J63: =Inputs!E13+(Inputs!G13-Inputs!E13)*BETAINV(RAND(),Model!J7,Model!K7) -> 0.26711118 | K63: =(Inputs!H13+(Inputs!J13-Inputs!H13)*BETAINV(RAND(),Model!L7,Model!M7))*Inputs!$C$6 -> 57422.543 | L63: =I63*J63 -> 0.67207339 | M63: =RAND() -> 0.76009904 | N63: =IF(M63<EXP(-L63),0,IF(M63<EXP(-L63)*(1+L63),1,IF(M63<EXP(-L63)*(1+L63+L63^2/2),2,IF(M63<EXP(-L63)*(1+L63+L63^2/2+L63^3/6),3,4)))) -> 1 | O63: =N63*K63 -> 57422.543 | P63: =Inputs!B14+(Inputs!D14-Inputs!B14)*BETAINV(RAND(),Model!H8,Model!I8) -> 0.3004733 | Q63: =Inputs!E14+(Inputs!G14-Inputs!E14)*BETAINV(RAND(),Model!J8,Model!K8) -> 0.52784474 | R63: =(Inputs!H14+(Inputs!J14-Inputs!H14)*BETAINV(RAND(),Model!L8,Model!M8))*Inputs!$C$6 -> 399047.13 | S63: =P63*Q63 -> 0.15860325 | T63: =RAND() -> 0.70761351 | U63: =IF(T63<EXP(-S63),0,IF(T63<EXP(-S63)*(1+S63),1,IF(T63<EXP(-S63)*(1+S63+S63^2/2),2,IF(T63<EXP(-S63)*(1+S63+S63^2/2+S63^3/6),3,4)))) -> 0 | V63: =U63*R63 -> 0 | W63: =Inputs!B15+(Inputs!D15-Inputs!B15)*BETAINV(RAND(),Model!H9,Model!I9) -> 1.8936599 | X63: =Inputs!E15+(Inputs!G15-Inputs!E15)*BETAINV(RAND(),Model!J9,Model!K9) -> 0.37528244 | Y63: =(Inputs!H15+(Inputs!J15-Inputs!H15)*BETAINV(RAND(),Model!L9,Model!M9))*Inputs!$C$6 -> 19441.904 | Z63: =W63*X63 -> 0.7106573 | AA63: =RAND() -> 0.70720693 | AB63: =IF(AA63<EXP(-Z63),0,IF(AA63<EXP(-Z63)*(1+Z63),1,IF(AA63<EXP(-Z63)*(1+Z63+Z63^2/2),2,IF(AA63<EXP(-Z63)*(1+Z63+Z63^2/2+Z63^3/6),3,4)))) -> 1 | AC63: =AB63*Y63 -> 19441.904 | AD63: =Inputs!B16+(Inputs!D16-Inputs!B16)*BETAINV(RAND(),Model!H10,Model!I10) -> 0.90940788 | AE63: =Inputs!E16+(Inputs!G16-Inputs!E16)*BETAINV(RAND(),Model!J10,Model!K10) -> 0.55572623 | AF63: =(Inputs!H16+(Inputs!J16-Inputs!H16)*BETAINV(RAND(),Model!L10,Model!M10))*Inputs!$C$6 -> 65464.455 | AG63: =AD63*AE63 -> 0.50538181 | AH63: =RAND() -> 0.70777722 | AI63: =IF(AH63<EXP(-AG63),0,IF(AH63<EXP(-AG63)*(1+AG63),1,IF(AH63<EXP(-AG63)*(1+AG63+AG63^2/2),2,IF(AH63<EXP(-AG63)*(1+AG63+AG63^2/2+AG63^3/6),3,4)))) -> 1 | AJ63: =AI63*AF63 -> 65464.455 | AK63: =H63+O63+V63+AC63+AJ63 -> 142328.9
B64: =Inputs!B12+(Inputs!D12-Inputs!B12)*BETAINV(RAND(),Model!H6,Model!I6) -> 2.6531483 | C64: =Inputs!E12+(Inputs!G12-Inputs!E12)*BETAINV(RAND(),Model!J6,Model!K6) -> 0.28646315 | D64: =(Inputs!H12+(Inputs!J12-Inputs!H12)*BETAINV(RAND(),Model!L6,Model!M6))*Inputs!$C$6 -> 28379.208 | E64: =B64*C64 -> 0.76002922 | F64: =RAND() -> 0.30735568 | G64: =IF(F64<EXP(-E64),0,IF(F64<EXP(-E64)*(1+E64),1,IF(F64<EXP(-E64)*(1+E64+E64^2/2),2,IF(F64<EXP(-E64)*(1+E64+E64^2/2+E64^3/6),3,4)))) -> 0 | H64: =G64*D64 -> 0 | I64: =Inputs!B13+(Inputs!D13-Inputs!B13)*BETAINV(RAND(),Model!H7,Model!I7) -> 2.6383335 | J64: =Inputs!E13+(Inputs!G13-Inputs!E13)*BETAINV(RAND(),Model!J7,Model!K7) -> 0.27359891 | K64: =(Inputs!H13+(Inputs!J13-Inputs!H13)*BETAINV(RAND(),Model!L7,Model!M7))*Inputs!$C$6 -> 56774.199 | L64: =I64*J64 -> 0.72184517 | M64: =RAND() -> 0.43896985 | N64: =IF(M64<EXP(-L64),0,IF(M64<EXP(-L64)*(1+L64),1,IF(M64<EXP(-L64)*(1+L64+L64^2/2),2,IF(M64<EXP(-L64)*(1+L64+L64^2/2+L64^3/6),3,4)))) -> 0 | O64: =N64*K64 -> 0 | P64: =Inputs!B14+(Inputs!D14-Inputs!B14)*BETAINV(RAND(),Model!H8,Model!I8) -> 0.49567461 | Q64: =Inputs!E14+(Inputs!G14-Inputs!E14)*BETAINV(RAND(),Model!J8,Model!K8) -> 0.5369196 | R64: =(Inputs!H14+(Inputs!J14-Inputs!H14)*BETAINV(RAND(),Model!L8,Model!M8))*Inputs!$C$6 -> 525898.3 | S64: =P64*Q64 -> 0.26613741 | T64: =RAND() -> 0.75094614 | U64: =IF(T64<EXP(-S64),0,IF(T64<EXP(-S64)*(1+S64),1,IF(T64<EXP(-S64)*(1+S64+S64^2/2),2,IF(T64<EXP(-S64)*(1+S64+S64^2/2+S64^3/6),3,4)))) -> 0 | V64: =U64*R64 -> 0 | W64: =Inputs!B15+(Inputs!D15-Inputs!B15)*BETAINV(RAND(),Model!H9,Model!I9) -> 2.3149336 | X64: =Inputs!E15+(Inputs!G15-Inputs!E15)*BETAINV(RAND(),Model!J9,Model!K9) -> 0.5054445 | Y64: =(Inputs!H15+(Inputs!J15-Inputs!H15)*BETAINV(RAND(),Model!L9,Model!M9))*Inputs!$C$6 -> 18496.652 | Z64: =W64*X64 -> 1.1700705 | AA64: =RAND() -> 0.39819901 | AB64: =IF(AA64<EXP(-Z64),0,IF(AA64<EXP(-Z64)*(1+Z64),1,IF(AA64<EXP(-Z64)*(1+Z64+Z64^2/2),2,IF(AA64<EXP(-Z64)*(1+Z64+Z64^2/2+Z64^3/6),3,4)))) -> 1 | AC64: =AB64*Y64 -> 18496.652 | AD64: =Inputs!B16+(Inputs!D16-Inputs!B16)*BETAINV(RAND(),Model!H10,Model!I10) -> 1.0140318 | AE64: =Inputs!E16+(Inputs!G16-Inputs!E16)*BETAINV(RAND(),Model!J10,Model!K10) -> 0.55252573 | AF64: =(Inputs!H16+(Inputs!J16-Inputs!H16)*BETAINV(RAND(),Model!L10,Model!M10))*Inputs!$C$6 -> 56673.494 | AG64: =AD64*AE64 -> 0.56027866 | AH64: =RAND() -> 0.5461885 | AI64: =IF(AH64<EXP(-AG64),0,IF(AH64<EXP(-AG64)*(1+AG64),1,IF(AH64<EXP(-AG64)*(1+AG64+AG64^2/2),2,IF(AH64<EXP(-AG64)*(1+AG64+AG64^2/2+AG64^3/6),3,4)))) -> 0 | AJ64: =AI64*AF64 -> 0 | AK64: =H64+O64+V64+AC64+AJ64 -> 18496.652
B65: =Inputs!B12+(Inputs!D12-Inputs!B12)*BETAINV(RAND(),Model!H6,Model!I6) -> 5.0077005 | C65: =Inputs!E12+(Inputs!G12-Inputs!E12)*BETAINV(RAND(),Model!J6,Model!K6) -> 0.34922314 | D65: =(Inputs!H12+(Inputs!J12-Inputs!H12)*BETAINV(RAND(),Model!L6,Model!M6))*Inputs!$C$6 -> 34349.199 | E65: =B65*C65 -> 1.7488049 | F65: =RAND() -> 0.70439166 | G65: =IF(F65<EXP(-E65),0,IF(F65<EXP(-E65)*(1+E65),1,IF(F65<EXP(-E65)*(1+E65+E65^2/2),2,IF(F65<EXP(-E65)*(1+E65+E65^2/2+E65^3/6),3,4)))) -> 2 | H65: =G65*D65 -> 68698.397 | I65: =Inputs!B13+(Inputs!D13-Inputs!B13)*BETAINV(RAND(),Model!H7,Model!I7) -> 3.0115361 | J65: =Inputs!E13+(Inputs!G13-Inputs!E13)*BETAINV(RAND(),Model!J7,Model!K7) -> 0.22416104 | K65: =(Inputs!H13+(Inputs!J13-Inputs!H13)*BETAINV(RAND(),Model!L7,Model!M7))*Inputs!$C$6 -> 52681.731 | L65: =I65*J65 -> 0.67506907 | M65: =RAND() -> 0.196141 | N65: =IF(M65<EXP(-L65),0,IF(M65<EXP(-L65)*(1+L65),1,IF(M65<EXP(-L65)*(1+L65+L65^2/2),2,IF(M65<EXP(-L65)*(1+L65+L65^2/2+L65^3/6),3,4)))) -> 0 | O65: =N65*K65 -> 0 | P65: =Inputs!B14+(Inputs!D14-Inputs!B14)*BETAINV(RAND(),Model!H8,Model!I8) -> 0.24986711 | Q65: =Inputs!E14+(Inputs!G14-Inputs!E14)*BETAINV(RAND(),Model!J8,Model!K8) -> 0.3850966 | R65: =(Inputs!H14+(Inputs!J14-Inputs!H14)*BETAINV(RAND(),Model!L8,Model!M8))*Inputs!$C$6 -> 399891.3 | S65: =P65*Q65 -> 0.096222974 | T65: =RAND() -> 0.26916739 | U65: =IF(T65<EXP(-S65),0,IF(T65<EXP(-S65)*(1+S65),1,IF(T65<EXP(-S65)*(1+S65+S65^2/2),2,IF(T65<EXP(-S65)*(1+S65+S65^2/2+S65^3/6),3,4)))) -> 0 | V65: =U65*R65 -> 0 | W65: =Inputs!B15+(Inputs!D15-Inputs!B15)*BETAINV(RAND(),Model!H9,Model!I9) -> 1.5984506 | X65: =Inputs!E15+(Inputs!G15-Inputs!E15)*BETAINV(RAND(),Model!J9,Model!K9) -> 0.36029501 | Y65: =(Inputs!H15+(Inputs!J15-Inputs!H15)*BETAINV(RAND(),Model!L9,Model!M9))*Inputs!$C$6 -> 27210.072 | Z65: =W65*X65 -> 0.57591378 | AA65: =RAND() -> 0.48309973 | AB65: =IF(AA65<EXP(-Z65),0,IF(AA65<EXP(-Z65)*(1+Z65),1,IF(AA65<EXP(-Z65)*(1+Z65+Z65^2/2),2,IF(AA65<EXP(-Z65)*(1+Z65+Z65^2/2+Z65^3/6),3,4)))) -> 0 | AC65: =AB65*Y65 -> 0 | AD65: =Inputs!B16+(Inputs!D16-Inputs!B16)*BETAINV(RAND(),Model!H10,Model!I10) -> 0.92670902 | AE65: =Inputs!E16+(Inputs!G16-Inputs!E16)*BETAINV(RAND(),Model!J10,Model!K10) -> 0.54417255 | AF65: =(Inputs!H16+(Inputs!J16-Inputs!H16)*BETAINV(RAND(),Model!L10,Model!M10))*Inputs!$C$6 -> 61825.979 | AG65: =AD65*AE65 -> 0.5042896 | AH65: =RAND() -> 0.21318437 | AI65: =IF(AH65<EXP(-AG65),0,IF(AH65<EXP(-AG65)*(1+AG65),1,IF(AH65<EXP(-AG65)*(1+AG65+AG65^2/2),2,IF(AH65<EXP(-AG65)*(1+AG65+AG65^2/2+AG65^3/6),3,4)))) -> 0 | AJ65: =AI65*AF65 -> 0 | AK65: =H65+O65+V65+AC65+AJ65 -> 68698.397
B66: =Inputs!B12+(Inputs!D12-Inputs!B12)*BETAINV(RAND(),Model!H6,Model!I6) -> 2.5304974 | C66: =Inputs!E12+(Inputs!G12-Inputs!E12)*BETAINV(RAND(),Model!J6,Model!K6) -> 0.30127529 | D66: =(Inputs!H12+(Inputs!J12-Inputs!H12)*BETAINV(RAND(),Model!L6,Model!M6))*Inputs!$C$6 -> 23009.693 | E66: =B66*C66 -> 0.76237636 | F66: =RAND() -> 0.21064863 | G66: =IF(F66<EXP(-E66),0,IF(F66<EXP(-E66)*(1+E66),1,IF(F66<EXP(-E66)*(1+E66+E66^2/2),2,IF(F66<EXP(-E66)*(1+E66+E66^2/2+E66^3/6),3,4)))) -> 0 | H66: =G66*D66 -> 0 | I66: =Inputs!B13+(Inputs!D13-Inputs!B13)*BETAINV(RAND(),Model!H7,Model!I7) -> 3.1549073 | J66: =Inputs!E13+(Inputs!G13-Inputs!E13)*BETAINV(RAND(),Model!J7,Model!K7) -> 0.20072434 | K66: =(Inputs!H13+(Inputs!J13-Inputs!H13)*BETAINV(RAND(),Model!L7,Model!M7))*Inputs!$C$6 -> 29859.972 | L66: =I66*J66 -> 0.63326669 | M66: =RAND() -> 0.4038163 | N66: =IF(M66<EXP(-L66),0,IF(M66<EXP(-L66)*(1+L66),1,IF(M66<EXP(-L66)*(1+L66+L66^2/2),2,IF(M66<EXP(-L66)*(1+L66+L66^2/2+L66^3/6),3,4)))) -> 0 | O66: =N66*K66 -> 0 | P66: =Inputs!B14+(Inputs!D14-Inputs!B14)*BETAINV(RAND(),Model!H8,Model!I8) -> 0.43514792 | Q66: =Inputs!E14+(Inputs!G14-Inputs!E14)*BETAINV(RAND(),Model!J8,Model!K8) -> 0.62608499 | R66: =(Inputs!H14+(Inputs!J14-Inputs!H14)*BETAINV(RAND(),Model!L8,Model!M8))*Inputs!$C$6 -> 310455.38 | S66: =P66*Q66 -> 0.27243958 | T66: =RAND() -> 0.96261801 | U66: =IF(T66<EXP(-S66),0,IF(T66<EXP(-S66)*(1+S66),1,IF(T66<EXP(-S66)*(1+S66+S66^2/2),2,IF(T66<EXP(-S66)*(1+S66+S66^2/2+S66^3/6),3,4)))) -> 1 | V66: =U66*R66 -> 310455.38 | W66: =Inputs!B15+(Inputs!D15-Inputs!B15)*BETAINV(RAND(),Model!H9,Model!I9) -> 0.59141066 | X66: =Inputs!E15+(Inputs!G15-Inputs!E15)*BETAINV(RAND(),Model!J9,Model!K9) -> 0.37352937 | Y66: =(Inputs!H15+(Inputs!J15-Inputs!H15)*BETAINV(RAND(),Model!L9,Model!M9))*Inputs!$C$6 -> 44736.323 | Z66: =W66*X66 -> 0.22090925 | AA66: =RAND() -> 0.46563076 | AB66: =IF(AA66<EXP(-Z66),0,IF(AA66<EXP(-Z66)*(1+Z66),1,IF(AA66<EXP(-Z66)*(1+Z66+Z66^2/2),2,IF(AA66<EXP(-Z66)*(1+Z66+Z66^2/2+Z66^3/6),3,4)))) -> 0 | AC66: =AB66*Y66 -> 0 | AD66: =Inputs!B16+(Inputs!D16-Inputs!B16)*BETAINV(RAND(),Model!H10,Model!I10) -> 1.0426875 | AE66: =Inputs!E16+(Inputs!G16-Inputs!E16)*BETAINV(RAND(),Model!J10,Model!K10) -> 0.55220828 | AF66: =(Inputs!H16+(Inputs!J16-Inputs!H16)*BETAINV(RAND(),Model!L10,Model!M10))*Inputs!$C$6 -> 63418.921 | AG66: =AD66*AE66 -> 0.57578066 | AH66: =RAND() -> 0.55792962 | AI66: =IF(AH66<EXP(-AG66),0,IF(AH66<EXP(-AG66)*(1+AG66),1,IF(AH66<EXP(-AG66)*(1+AG66+AG66^2/2),2,IF(AH66<EXP(-AG66)*(1+AG66+AG66^2/2+AG66^3/6),3,4)))) -> 0 | AJ66: =AI66*AF66 -> 0 | AK66: =H66+O66+V66+AC66+AJ66 -> 310455.38
B67: =Inputs!B12+(Inputs!D12-Inputs!B12)*BETAINV(RAND(),Model!H6,Model!I6) -> 4.7857795 | C67: =Inputs!E12+(Inputs!G12-Inputs!E12)*BETAINV(RAND(),Model!J6,Model!K6) -> 0.26835875 | D67: =(Inputs!H12+(Inputs!J12-Inputs!H12)*BETAINV(RAND(),Model!L6,Model!M6))*Inputs!$C$6 -> 47864.056 | E67: =B67*C67 -> 1.2843058 | F67: =RAND() -> 0.62930014 | G67: =IF(F67<EXP(-E67),0,IF(F67<EXP(-E67)*(1+E67),1,IF(F67<EXP(-E67)*(1+E67+E67^2/2),2,IF(F67<EXP(-E67)*(1+E67+E67^2/2+E67^3/6),3,4)))) -> 1 | H67: =G67*D67 -> 47864.056 | I67: =Inputs!B13+(Inputs!D13-Inputs!B13)*BETAINV(RAND(),Model!H7,Model!I7) -> 3.8065409 | J67: =Inputs!E13+(Inputs!G13-Inputs!E13)*BETAINV(RAND(),Model!J7,Model!K7) -> 0.28394264 | K67: =(Inputs!H13+(Inputs!J13-Inputs!H13)*BETAINV(RAND(),Model!L7,Model!M7))*Inputs!$C$6 -> 36501.307 | L67: =I67*J67 -> 1.0808393 | M67: =RAND() -> 0.73413285 | N67: =IF(M67<EXP(-L67),0,IF(M67<EXP(-L67)*(1+L67),1,IF(M67<EXP(-L67)*(1+L67+L67^2/2),2,IF(M67<EXP(-L67)*(1+L67+L67^2/2+L67^3/6),3,4)))) -> 2 | O67: =N67*K67 -> 73002.614 | P67: =Inputs!B14+(Inputs!D14-Inputs!B14)*BETAINV(RAND(),Model!H8,Model!I8) -> 0.18342711 | Q67: =Inputs!E14+(Inputs!G14-Inputs!E14)*BETAINV(RAND(),Model!J8,Model!K8) -> 0.46495997 | R67: =(Inputs!H14+(Inputs!J14-Inputs!H14)*BETAINV(RAND(),Model!L8,Model!M8))*Inputs!$C$6 -> 340215.07 | S67: =P67*Q67 -> 0.085286264 | T67: =RAND() -> 0.084559662 | U67: =IF(T67<EXP(-S67),0,IF(T67<EXP(-S67)*(1+S67),1,IF(T67<EXP(-S67)*(1+S67+S67^2/2),2,IF(T67<EXP(-S67)*(1+S67+S67^2/2+S67^3/6),3,4)))) -> 0 | V67: =U67*R67 -> 0 | W67: =Inputs!B15+(Inputs!D15-Inputs!B15)*BETAINV(RAND(),Model!H9,Model!I9) -> 0.89435225 | X67: =Inputs!E15+(Inputs!G15-Inputs!E15)*BETAINV(RAND(),Model!J9,Model!K9) -> 0.35587681 | Y67: =(Inputs!H15+(Inputs!J15-Inputs!H15)*BETAINV(RAND(),Model!L9,Model!M9))*Inputs!$C$6 -> 52487.062 | Z67: =W67*X67 -> 0.31827923 | AA67: =RAND() -> 0.29749286 | AB67: =IF(AA67<EXP(-Z67),0,IF(AA67<EXP(-Z67)*(1+Z67),1,IF(AA67<EXP(-Z67)*(1+Z67+Z67^2/2),2,IF(AA67<EXP(-Z67)*(1+Z67+Z67^2/2+Z67^3/6),3,4)))) -> 0 | AC67: =AB67*Y67 -> 0 | AD67: =Inputs!B16+(Inputs!D16-Inputs!B16)*BETAINV(RAND(),Model!H10,Model!I10) -> 0.5675037 | AE67: =Inputs!E16+(Inputs!G16-Inputs!E16)*BETAINV(RAND(),Model!J10,Model!K10) -> 0.75051041 | AF67: =(Inputs!H16+(Inputs!J16-Inputs!H16)*BETAINV(RAND(),Model!L10,Model!M10))*Inputs!$C$6 -> 50809.052 | AG67: =AD67*AE67 -> 0.42591744 | AH67: =RAND() -> 0.64890116 | AI67: =IF(AH67<EXP(-AG67),0,IF(AH67<EXP(-AG67)*(1+AG67),1,IF(AH67<EXP(-AG67)*(1+AG67+AG67^2/2),2,IF(AH67<EXP(-AG67)*(1+AG67+AG67^2/2+AG67^3/6),3,4)))) -> 0 | AJ67: =AI67*AF67 -> 0 | AK67: =H67+O67+V67+AC67+AJ67 -> 120866.67
B68: =Inputs!B12+(Inputs!D12-Inputs!B12)*BETAINV(RAND(),Model!H6,Model!I6) -> 3.6872975 | C68: =Inputs!E12+(Inputs!G12-Inputs!E12)*BETAINV(RAND(),Model!J6,Model!K6) -> 0.39486977 | D68: =(Inputs!H12+(Inputs!J12-Inputs!H12)*BETAINV(RAND(),Model!L6,Model!M6))*Inputs!$C$6 -> 19967.672 | E68: =B68*C68 -> 1.4560023 | F68: =RAND() -> 0.10275903 | G68: =IF(F68<EXP(-E68),0,IF(F68<EXP(-E68)*(1+E68),1,IF(F68<EXP(-E68)*(1+E68+E68^2/2),2,IF(F68<EXP(-E68)*(1+E68+E68^2/2+E68^3/6),3,4)))) -> 0 | H68: =G68*D68 -> 0 | I68: =Inputs!B13+(Inputs!D13-Inputs!B13)*BETAINV(RAND(),Model!H7,Model!I7) -> 1.2505197 | J68: =Inputs!E13+(Inputs!G13-Inputs!E13)*BETAINV(RAND(),Model!J7,Model!K7) -> 0.21162119 | K68: =(Inputs!H13+(Inputs!J13-Inputs!H13)*BETAINV(RAND(),Model!L7,Model!M7))*Inputs!$C$6 -> 41168.191 | L68: =I68*J68 -> 0.26463647 | M68: =RAND() -> 0.58191626 | N68: =IF(M68<EXP(-L68),0,IF(M68<EXP(-L68)*(1+L68),1,IF(M68<EXP(-L68)*(1+L68+L68^2/2),2,IF(M68<EXP(-L68)*(1+L68+L68^2/2+L68^3/6),3,4)))) -> 0 | O68: =N68*K68 -> 0 | P68: =Inputs!B14+(Inputs!D14-Inputs!B14)*BETAINV(RAND(),Model!H8,Model!I8) -> 0.38931626 | Q68: =Inputs!E14+(Inputs!G14-Inputs!E14)*BETAINV(RAND(),Model!J8,Model!K8) -> 0.72247017 | R68: =(Inputs!H14+(Inputs!J14-Inputs!H14)*BETAINV(RAND(),Model!L8,Model!M8))*Inputs!$C$6 -> 561457.55 | S68: =P68*Q68 -> 0.28126938 | T68: =RAND() -> 0.8650766 | U68: =IF(T68<EXP(-S68),0,IF(T68<EXP(-S68)*(1+S68),1,IF(T68<EXP(-S68)*(1+S68+S68^2/2),2,IF(T68<EXP(-S68)*(1+S68+S68^2/2+S68^3/6),3,4)))) -> 1 | V68: =U68*R68 -> 561457.55 | W68: =Inputs!B15+(Inputs!D15-Inputs!B15)*BETAINV(RAND(),Model!H9,Model!I9) -> 1.1698465 | X68: =Inputs!E15+(Inputs!G15-Inputs!E15)*BETAINV(RAND(),Model!J9,Model!K9) -> 0.5596145 | Y68: =(Inputs!H15+(Inputs!J15-Inputs!H15)*BETAINV(RAND(),Model!L9,Model!M9))*Inputs!$C$6 -> 19674.426 | Z68: =W68*X68 -> 0.65466305 | AA68: =RAND() -> 0.09090304 | AB68: =IF(AA68<EXP(-Z68),0,IF(AA68<EXP(-Z68)*(1+Z68),1,IF(AA68<EXP(-Z68)*(1+Z68+Z68^2/2),2,IF(AA68<EXP(-Z68)*(1+Z68+Z68^2/2+Z68^3/6),3,4)))) -> 0 | AC68: =AB68*Y68 -> 0 | AD68: =Inputs!B16+(Inputs!D16-Inputs!B16)*BETAINV(RAND(),Model!H10,Model!I10) -> 1.0460941 | AE68: =Inputs!E16+(Inputs!G16-Inputs!E16)*BETAINV(RAND(),Model!J10,Model!K10) -> 0.47659868 | AF68: =(Inputs!H16+(Inputs!J16-Inputs!H16)*BETAINV(RAND(),Model!L10,Model!M10))*Inputs!$C$6 -> 151398.73 | AG68: =AD68*AE68 -> 0.49856709 | AH68: =RAND() -> 0.54721384 | AI68: =IF(AH68<EXP(-AG68),0,IF(AH68<EXP(-AG68)*(1+AG68),1,IF(AH68<EXP(-AG68)*(1+AG68+AG68^2/2),2,IF(AH68<EXP(-AG68)*(1+AG68+AG68^2/2+AG68^3/6),3,4)))) -> 0 | AJ68: =AI68*AF68 -> 0 | AK68: =H68+O68+V68+AC68+AJ68 -> 561457.55
B69: =Inputs!B12+(Inputs!D12-Inputs!B12)*BETAINV(RAND(),Model!H6,Model!I6) -> 2.5895737 | C69: =Inputs!E12+(Inputs!G12-Inputs!E12)*BETAINV(RAND(),Model!J6,Model!K6) -> 0.32328177 | D69: =(Inputs!H12+(Inputs!J12-Inputs!H12)*BETAINV(RAND(),Model!L6,Model!M6))*Inputs!$C$6 -> 41803.444 | E69: =B69*C69 -> 0.83716197 | F69: =RAND() -> 0.2372578 | G69: =IF(F69<EXP(-E69),0,IF(F69<EXP(-E69)*(1+E69),1,IF(F69<EXP(-E69)*(1+E69+E69^2/2),2,IF(F69<EXP(-E69)*(1+E69+E69^2/2+E69^3/6),3,4)))) -> 0 | H69: =G69*D69 -> 0 | I69: =Inputs!B13+(Inputs!D13-Inputs!B13)*BETAINV(RAND(),Model!H7,Model!I7) -> 3.8238303 | J69: =Inputs!E13+(Inputs!G13-Inputs!E13)*BETAINV(RAND(),Model!J7,Model!K7) -> 0.27966137 | K69: =(Inputs!H13+(Inputs!J13-Inputs!H13)*BETAINV(RAND(),Model!L7,Model!M7))*Inputs!$C$6 -> 19788.021 | L69: =I69*J69 -> 1.0693776 | M69: =RAND() -> 0.82259833 | N69: =IF(M69<EXP(-L69),0,IF(M69<EXP(-L69)*(1+L69),1,IF(M69<EXP(-L69)*(1+L69+L69^2/2),2,IF(M69<EXP(-L69)*(1+L69+L69^2/2+L69^3/6),3,4)))) -> 2 | O69: =N69*K69 -> 39576.042 | P69: =Inputs!B14+(Inputs!D14-Inputs!B14)*BETAINV(RAND(),Model!H8,Model!I8) -> 0.25191239 | Q69: =Inputs!E14+(Inputs!G14-Inputs!E14)*BETAINV(RAND(),Model!J8,Model!K8) -> 0.68245651 | R69: =(Inputs!H14+(Inputs!J14-Inputs!H14)*BETAINV(RAND(),Model!L8,Model!M8))*Inputs!$C$6 -> 349899.86 | S69: =P69*Q69 -> 0.17191925 | T69: =RAND() -> 0.57460296 | U69: =IF(T69<EXP(-S69),0,IF(T69<EXP(-S69)*(1+S69),1,IF(T69<EXP(-S69)*(1+S69+S69^2/2),2,IF(T69<EXP(-S69)*(1+S69+S69^2/2+S69^3/6),3,4)))) -> 0 | V69: =U69*R69 -> 0 | W69: =Inputs!B15+(Inputs!D15-Inputs!B15)*BETAINV(RAND(),Model!H9,Model!I9) -> 0.45425846 | X69: =Inputs!E15+(Inputs!G15-Inputs!E15)*BETAINV(RAND(),Model!J9,Model!K9) -> 0.4044552 | Y69: =(Inputs!H15+(Inputs!J15-Inputs!H15)*BETAINV(RAND(),Model!L9,Model!M9))*Inputs!$C$6 -> 18746.4 | Z69: =W69*X69 -> 0.1837272 | AA69: =RAND() -> 0.24411434 | AB69: =IF(AA69<EXP(-Z69),0,IF(AA69<EXP(-Z69)*(1+Z69),1,IF(AA69<EXP(-Z69)*(1+Z69+Z69^2/2),2,IF(AA69<EXP(-Z69)*(1+Z69+Z69^2/2+Z69^3/6),3,4)))) -> 0 | AC69: =AB69*Y69 -> 0 | AD69: =Inputs!B16+(Inputs!D16-Inputs!B16)*BETAINV(RAND(),Model!H10,Model!I10) -> 0.4198433 | AE69: =Inputs!E16+(Inputs!G16-Inputs!E16)*BETAINV(RAND(),Model!J10,Model!K10) -> 0.65156834 | AF69: =(Inputs!H16+(Inputs!J16-Inputs!H16)*BETAINV(RAND(),Model!L10,Model!M10))*Inputs!$C$6 -> 60906.354 | AG69: =AD69*AE69 -> 0.2735566 | AH69: =RAND() -> 0.28161959 | AI69: =IF(AH69<EXP(-AG69),0,IF(AH69<EXP(-AG69)*(1+AG69),1,IF(AH69<EXP(-AG69)*(1+AG69+AG69^2/2),2,IF(AH69<EXP(-AG69)*(1+AG69+AG69^2/2+AG69^3/6),3,4)))) -> 0 | AJ69: =AI69*AF69 -> 0 | AK69: =H69+O69+V69+AC69+AJ69 -> 39576.042
B70: =Inputs!B12+(Inputs!D12-Inputs!B12)*BETAINV(RAND(),Model!H6,Model!I6) -> 3.9091731 | C70: =Inputs!E12+(Inputs!G12-Inputs!E12)*BETAINV(RAND(),Model!J6,Model!K6) -> 0.42981244 | D70: =(Inputs!H12+(Inputs!J12-Inputs!H12)*BETAINV(RAND(),Model!L6,Model!M6))*Inputs!$C$6 -> 24227.454 | E70: =B70*C70 -> 1.6802113 | F70: =RAND() -> 0.25738803 | G70: =IF(F70<EXP(-E70),0,IF(F70<EXP(-E70)*(1+E70),1,IF(F70<EXP(-E70)*(1+E70+E70^2/2),2,IF(F70<EXP(-E70)*(1+E70+E70^2/2+E70^3/6),3,4)))) -> 1 | H70: =G70*D70 -> 24227.454 | I70: =Inputs!B13+(Inputs!D13-Inputs!B13)*BETAINV(RAND(),Model!H7,Model!I7) -> 1.6347848 | J70: =Inputs!E13+(Inputs!G13-Inputs!E13)*BETAINV(RAND(),Model!J7,Model!K7) -> 0.29386362 | K70: =(Inputs!H13+(Inputs!J13-Inputs!H13)*BETAINV(RAND(),Model!L7,Model!M7))*Inputs!$C$6 -> 25617.375 | L70: =I70*J70 -> 0.48040377 | M70: =RAND() -> 0.39010623 | N70: =IF(M70<EXP(-L70),0,IF(M70<EXP(-L70)*(1+L70),1,IF(M70<EXP(-L70)*(1+L70+L70^2/2),2,IF(M70<EXP(-L70)*(1+L70+L70^2/2+L70^3/6),3,4)))) -> 0 | O70: =N70*K70 -> 0 | P70: =Inputs!B14+(Inputs!D14-Inputs!B14)*BETAINV(RAND(),Model!H8,Model!I8) -> 0.53121012 | Q70: =Inputs!E14+(Inputs!G14-Inputs!E14)*BETAINV(RAND(),Model!J8,Model!K8) -> 0.72415722 | R70: =(Inputs!H14+(Inputs!J14-Inputs!H14)*BETAINV(RAND(),Model!L8,Model!M8))*Inputs!$C$6 -> 331342.35 | S70: =P70*Q70 -> 0.38467964 | T70: =RAND() -> 0.40401038 | U70: =IF(T70<EXP(-S70),0,IF(T70<EXP(-S70)*(1+S70),1,IF(T70<EXP(-S70)*(1+S70+S70^2/2),2,IF(T70<EXP(-S70)*(1+S70+S70^2/2+S70^3/6),3,4)))) -> 0 | V70: =U70*R70 -> 0 | W70: =Inputs!B15+(Inputs!D15-Inputs!B15)*BETAINV(RAND(),Model!H9,Model!I9) -> 1.2842492 | X70: =Inputs!E15+(Inputs!G15-Inputs!E15)*BETAINV(RAND(),Model!J9,Model!K9) -> 0.312535 | Y70: =(Inputs!H15+(Inputs!J15-Inputs!H15)*BETAINV(RAND(),Model!L9,Model!M9))*Inputs!$C$6 -> 20352.713 | Z70: =W70*X70 -> 0.40137284 | AA70: =RAND() -> 0.0090797983 | AB70: =IF(AA70<EXP(-Z70),0,IF(AA70<EXP(-Z70)*(1+Z70),1,IF(AA70<EXP(-Z70)*(1+Z70+Z70^2/2),2,IF(AA70<EXP(-Z70)*(1+Z70+Z70^2/2+Z70^3/6),3,4)))) -> 0 | AC70: =AB70*Y70 -> 0 | AD70: =Inputs!B16+(Inputs!D16-Inputs!B16)*BETAINV(RAND(),Model!H10,Model!I10) -> 0.42915781 | AE70: =Inputs!E16+(Inputs!G16-Inputs!E16)*BETAINV(RAND(),Model!J10,Model!K10) -> 0.72535355 | AF70: =(Inputs!H16+(Inputs!J16-Inputs!H16)*BETAINV(RAND(),Model!L10,Model!M10))*Inputs!$C$6 -> 71517.987 | AG70: =AD70*AE70 -> 0.31129114 | AH70: =RAND() -> 0.88466199 | AI70: =IF(AH70<EXP(-AG70),0,IF(AH70<EXP(-AG70)*(1+AG70),1,IF(AH70<EXP(-AG70)*(1+AG70+AG70^2/2),2,IF(AH70<EXP(-AG70)*(1+AG70+AG70^2/2+AG70^3/6),3,4)))) -> 1 | AJ70: =AI70*AF70 -> 71517.987 | AK70: =H70+O70+V70+AC70+AJ70 -> 95745.441
B71: =Inputs!B12+(Inputs!D12-Inputs!B12)*BETAINV(RAND(),Model!H6,Model!I6) -> 4.3703547 | C71: =Inputs!E12+(Inputs!G12-Inputs!E12)*BETAINV(RAND(),Model!J6,Model!K6) -> 0.25895069 | D71: =(Inputs!H12+(Inputs!J12-Inputs!H12)*BETAINV(RAND(),Model!L6,Model!M6))*Inputs!$C$6 -> 14799.253 | E71: =B71*C71 -> 1.1317064 | F71: =RAND() -> 0.44841426 | G71: =IF(F71<EXP(-E71),0,IF(F71<EXP(-E71)*(1+E71),1,IF(F71<EXP(-E71)*(1+E71+E71^2/2),2,IF(F71<EXP(-E71)*(1+E71+E71^2/2+E71^3/6),3,4)))) -> 1 | H71: =G71*D71 -> 14799.253 | I71: =Inputs!B13+(Inputs!D13-Inputs!B13)*BETAINV(RAND(),Model!H7,Model!I7) -> 0.93229313 | J71: =Inputs!E13+(Inputs!G13-Inputs!E13)*BETAINV(RAND(),Model!J7,Model!K7) -> 0.3467712 | K71: =(Inputs!H13+(Inputs!J13-Inputs!H13)*BETAINV(RAND(),Model!L7,Model!M7))*Inputs!$C$6 -> 19257.477 | L71: =I71*J71 -> 0.32329241 | M71: =RAND() -> 0.076471971 | N71: =IF(M71<EXP(-L71),0,IF(M71<EXP(-L71)*(1+L71),1,IF(M71<EXP(-L71)*(1+L71+L71^2/2),2,IF(M71<EXP(-L71)*(1+L71+L71^2/2+L71^3/6),3,4)))) -> 0 | O71: =N71*K71 -> 0 | P71: =Inputs!B14+(Inputs!D14-Inputs!B14)*BETAINV(RAND(),Model!H8,Model!I8) -> 0.3694161 | Q71: =Inputs!E14+(Inputs!G14-Inputs!E14)*BETAINV(RAND(),Model!J8,Model!K8) -> 0.43285064 | R71: =(Inputs!H14+(Inputs!J14-Inputs!H14)*BETAINV(RAND(),Model!L8,Model!M8))*Inputs!$C$6 -> 317068.78 | S71: =P71*Q71 -> 0.159902 | T71: =RAND() -> 0.73692513 | U71: =IF(T71<EXP(-S71),0,IF(T71<EXP(-S71)*(1+S71),1,IF(T71<EXP(-S71)*(1+S71+S71^2/2),2,IF(T71<EXP(-S71)*(1+S71+S71^2/2+S71^3/6),3,4)))) -> 0 | V71: =U71*R71 -> 0 | W71: =Inputs!B15+(Inputs!D15-Inputs!B15)*BETAINV(RAND(),Model!H9,Model!I9) -> 0.9452435 | X71: =Inputs!E15+(Inputs!G15-Inputs!E15)*BETAINV(RAND(),Model!J9,Model!K9) -> 0.33448292 | Y71: =(Inputs!H15+(Inputs!J15-Inputs!H15)*BETAINV(RAND(),Model!L9,Model!M9))*Inputs!$C$6 -> 8927.0239 | Z71: =W71*X71 -> 0.31616781 | AA71: =RAND() -> 0.56994276 | AB71: =IF(AA71<EXP(-Z71),0,IF(AA71<EXP(-Z71)*(1+Z71),1,IF(AA71<EXP(-Z71)*(1+Z71+Z71^2/2),2,IF(AA71<EXP(-Z71)*(1+Z71+Z71^2/2+Z71^3/6),3,4)))) -> 0 | AC71: =AB71*Y71 -> 0 | AD71: =Inputs!B16+(Inputs!D16-Inputs!B16)*BETAINV(RAND(),Model!H10,Model!I10) -> 0.54517331 | AE71: =Inputs!E16+(Inputs!G16-Inputs!E16)*BETAINV(RAND(),Model!J10,Model!K10) -> 0.6107702 | AF71: =(Inputs!H16+(Inputs!J16-Inputs!H16)*BETAINV(RAND(),Model!L10,Model!M10))*Inputs!$C$6 -> 91330.336 | AG71: =AD71*AE71 -> 0.33297561 | AH71: =RAND() -> 0.81489932 | AI71: =IF(AH71<EXP(-AG71),0,IF(AH71<EXP(-AG71)*(1+AG71),1,IF(AH71<EXP(-AG71)*(1+AG71+AG71^2/2),2,IF(AH71<EXP(-AG71)*(1+AG71+AG71^2/2+AG71^3/6),3,4)))) -> 1 | AJ71: =AI71*AF71 -> 91330.336 | AK71: =H71+O71+V71+AC71+AJ71 -> 106129.59
B72: =Inputs!B12+(Inputs!D12-Inputs!B12)*BETAINV(RAND(),Model!H6,Model!I6) -> 5.9553126 | C72: =Inputs!E12+(Inputs!G12-Inputs!E12)*BETAINV(RAND(),Model!J6,Model!K6) -> 0.40630984 | D72: =(Inputs!H12+(Inputs!J12-Inputs!H12)*BETAINV(RAND(),Model!L6,Model!M6))*Inputs!$C$6 -> 30545.306 | E72: =B72*C72 -> 2.4197021 | F72: =RAND() -> 0.38375762 | G72: =IF(F72<EXP(-E72),0,IF(F72<EXP(-E72)*(1+E72),1,IF(F72<EXP(-E72)*(1+E72+E72^2/2),2,IF(F72<EXP(-E72)*(1+E72+E72^2/2+E72^3/6),3,4)))) -> 2 | H72: =G72*D72 -> 61090.612 | I72: =Inputs!B13+(Inputs!D13-Inputs!B13)*BETAINV(RAND(),Model!H7,Model!I7) -> 1.5220264 | J72: =Inputs!E13+(Inputs!G13-Inputs!E13)*BETAINV(RAND(),Model!J7,Model!K7) -> 0.19477436 | K72: =(Inputs!H13+(Inputs!J13-Inputs!H13)*BETAINV(RAND(),Model!L7,Model!M7))*Inputs!$C$6 -> 27050.419 | L72: =I72*J72 -> 0.29645172 | M72: =RAND() -> 0.4399924 | N72: =IF(M72<EXP(-L72),0,IF(M72<EXP(-L72)*(1+L72),1,IF(M72<EXP(-L72)*(1+L72+L72^2/2),2,IF(M72<EXP(-L72)*(1+L72+L72^2/2+L72^3/6),3,4)))) -> 0 | O72: =N72*K72 -> 0 | P72: =Inputs!B14+(Inputs!D14-Inputs!B14)*BETAINV(RAND(),Model!H8,Model!I8) -> 0.3317268 | Q72: =Inputs!E14+(Inputs!G14-Inputs!E14)*BETAINV(RAND(),Model!J8,Model!K8) -> 0.38513766 | R72: =(Inputs!H14+(Inputs!J14-Inputs!H14)*BETAINV(RAND(),Model!L8,Model!M8))*Inputs!$C$6 -> 343124.88 | S72: =P72*Q72 -> 0.12776048 | T72: =RAND() -> 0.35720705 | U72: =IF(T72<EXP(-S72),0,IF(T72<EXP(-S72)*(1+S72),1,IF(T72<EXP(-S72)*(1+S72+S72^2/2),2,IF(T72<EXP(-S72)*(1+S72+S72^2/2+S72^3/6),3,4)))) -> 0 | V72: =U72*R72 -> 0 | W72: =Inputs!B15+(Inputs!D15-Inputs!B15)*BETAINV(RAND(),Model!H9,Model!I9) -> 2.1666331 | X72: =Inputs!E15+(Inputs!G15-Inputs!E15)*BETAINV(RAND(),Model!J9,Model!K9) -> 0.53018504 | Y72: =(Inputs!H15+(Inputs!J15-Inputs!H15)*BETAINV(RAND(),Model!L9,Model!M9))*Inputs!$C$6 -> 21107.12 | Z72: =W72*X72 -> 1.1487164 | AA72: =RAND() -> 0.71927117 | AB72: =IF(AA72<EXP(-Z72),0,IF(AA72<EXP(-Z72)*(1+Z72),1,IF(AA72<EXP(-Z72)*(1+Z72+Z72^2/2),2,IF(AA72<EXP(-Z72)*(1+Z72+Z72^2/2+Z72^3/6),3,4)))) -> 2 | AC72: =AB72*Y72 -> 42214.241 | AD72: =Inputs!B16+(Inputs!D16-Inputs!B16)*BETAINV(RAND(),Model!H10,Model!I10) -> 0.46825003 | AE72: =Inputs!E16+(Inputs!G16-Inputs!E16)*BETAINV(RAND(),Model!J10,Model!K10) -> 0.57692444 | AF72: =(Inputs!H16+(Inputs!J16-Inputs!H16)*BETAINV(RAND(),Model!L10,Model!M10))*Inputs!$C$6 -> 56217.587 | AG72: =AD72*AE72 -> 0.27014488 | AH72: =RAND() -> 0.82451889 | AI72: =IF(AH72<EXP(-AG72),0,IF(AH72<EXP(-AG72)*(1+AG72),1,IF(AH72<EXP(-AG72)*(1+AG72+AG72^2/2),2,IF(AH72<EXP(-AG72)*(1+AG72+AG72^2/2+AG72^3/6),3,4)))) -> 1 | AJ72: =AI72*AF72 -> 56217.587 | AK72: =H72+O72+V72+AC72+AJ72 -> 159522.44
B73: =Inputs!B12+(Inputs!D12-Inputs!B12)*BETAINV(RAND(),Model!H6,Model!I6) -> 3.2160675 | C73: =Inputs!E12+(Inputs!G12-Inputs!E12)*BETAINV(RAND(),Model!J6,Model!K6) -> 0.24705164 | D73: =(Inputs!H12+(Inputs!J12-Inputs!H12)*BETAINV(RAND(),Model!L6,Model!M6))*Inputs!$C$6 -> 18633.317 | E73: =B73*C73 -> 0.79453476 | F73: =RAND() -> 0.49680457 | G73: =IF(F73<EXP(-E73),0,IF(F73<EXP(-E73)*(1+E73),1,IF(F73<EXP(-E73)*(1+E73+E73^2/2),2,IF(F73<EXP(-E73)*(1+E73+E73^2/2+E73^3/6),3,4)))) -> 1 | H73: =G73*D73 -> 18633.317 | I73: =Inputs!B13+(Inputs!D13-Inputs!B13)*BETAINV(RAND(),Model!H7,Model!I7) -> 1.3054731 | J73: =Inputs!E13+(Inputs!G13-Inputs!E13)*BETAINV(RAND(),Model!J7,Model!K7) -> 0.289702 | K73: =(Inputs!H13+(Inputs!J13-Inputs!H13)*BETAINV(RAND(),Model!L7,Model!M7))*Inputs!$C$6 -> 51328.279 | L73: =I73*J73 -> 0.37819818 | M73: =RAND() -> 0.45501955 | N73: =IF(M73<EXP(-L73),0,IF(M73<EXP(-L73)*(1+L73),1,IF(M73<EXP(-L73)*(1+L73+L73^2/2),2,IF(M73<EXP(-L73)*(1+L73+L73^2/2+L73^3/6),3,4)))) -> 0 | O73: =N73*K73 -> 0 | P73: =Inputs!B14+(Inputs!D14-Inputs!B14)*BETAINV(RAND(),Model!H8,Model!I8) -> 0.67432673 | Q73: =Inputs!E14+(Inputs!G14-Inputs!E14)*BETAINV(RAND(),Model!J8,Model!K8) -> 0.54222299 | R73: =(Inputs!H14+(Inputs!J14-Inputs!H14)*BETAINV(RAND(),Model!L8,Model!M8))*Inputs!$C$6 -> 286457.9 | S73: =P73*Q73 -> 0.36563546 | T73: =RAND() -> 0.27120259 | U73: =IF(T73<EXP(-S73),0,IF(T73<EXP(-S73)*(1+S73),1,IF(T73<EXP(-S73)*(1+S73+S73^2/2),2,IF(T73<EXP(-S73)*(1+S73+S73^2/2+S73^3/6),3,4)))) -> 0 | V73: =U73*R73 -> 0 | W73: =Inputs!B15+(Inputs!D15-Inputs!B15)*BETAINV(RAND(),Model!H9,Model!I9) -> 1.1640254 | X73: =Inputs!E15+(Inputs!G15-Inputs!E15)*BETAINV(RAND(),Model!J9,Model!K9) -> 0.33708812 | Y73: =(Inputs!H15+(Inputs!J15-Inputs!H15)*BETAINV(RAND(),Model!L9,Model!M9))*Inputs!$C$6 -> 29488.569 | Z73: =W73*X73 -> 0.39237915 | AA73: =RAND() -> 0.23596486 | AB73: =IF(AA73<EXP(-Z73),0,IF(AA73<EXP(-Z73)*(1+Z73),1,IF(AA73<EXP(-Z73)*(1+Z73+Z73^2/2),2,IF(AA73<EXP(-Z73)*(1+Z73+Z73^2/2+Z73^3/6),3,4)))) -> 0 | AC73: =AB73*Y73 -> 0 | AD73: =Inputs!B16+(Inputs!D16-Inputs!B16)*BETAINV(RAND(),Model!H10,Model!I10) -> 0.31630575 | AE73: =Inputs!E16+(Inputs!G16-Inputs!E16)*BETAINV(RAND(),Model!J10,Model!K10) -> 0.73676474 | AF73: =(Inputs!H16+(Inputs!J16-Inputs!H16)*BETAINV(RAND(),Model!L10,Model!M10))*Inputs!$C$6 -> 152559.06 | AG73: =AD73*AE73 -> 0.23304292 | AH73: =RAND() -> 0.050585048 | AI73: =IF(AH73<EXP(-AG73),0,IF(AH73<EXP(-AG73)*(1+AG73),1,IF(AH73<EXP(-AG73)*(1+AG73+AG73^2/2),2,IF(AH73<EXP(-AG73)*(1+AG73+AG73^2/2+AG73^3/6),3,4)))) -> 0 | AJ73: =AI73*AF73 -> 0 | AK73: =H73+O73+V73+AC73+AJ73 -> 18633.317
B74: =Inputs!B12+(Inputs!D12-Inputs!B12)*BETAINV(RAND(),Model!H6,Model!I6) -> 5.1523627 | C74: =Inputs!E12+(Inputs!G12-Inputs!E12)*BETAINV(RAND(),Model!J6,Model!K6) -> 0.3695801 | D74: =(Inputs!H12+(Inputs!J12-Inputs!H12)*BETAINV(RAND(),Model!L6,Model!M6))*Inputs!$C$6 -> 11259.636 | E74: =B74*C74 -> 1.9042107 | F74: =RAND() -> 0.14220854 | G74: =IF(F74<EXP(-E74),0,IF(F74<EXP(-E74)*(1+E74),1,IF(F74<EXP(-E74)*(1+E74+E74^2/2),2,IF(F74<EXP(-E74)*(1+E74+E74^2/2+E74^3/6),3,4)))) -> 0 | H74: =G74*D74 -> 0 | I74: =Inputs!B13+(Inputs!D13-Inputs!B13)*BETAINV(RAND(),Model!H7,Model!I7) -> 2.8817145 | J74: =Inputs!E13+(Inputs!G13-Inputs!E13)*BETAINV(RAND(),Model!J7,Model!K7) -> 0.21843816 | K74: =(Inputs!H13+(Inputs!J13-Inputs!H13)*BETAINV(RAND(),Model!L7,Model!M7))*Inputs!$C$6 -> 29984.723 | L74: =I74*J74 -> 0.62947641 | M74: =RAND() -> 0.99955256 | N74: =IF(M74<EXP(-L74),0,IF(M74<EXP(-L74)*(1+L74),1,IF(M74<EXP(-L74)*(1+L74+L74^2/2),2,IF(M74<EXP(-L74)*(1+L74+L74^2/2+L74^3/6),3,4)))) -> 4 | O74: =N74*K74 -> 119938.89 | P74: =Inputs!B14+(Inputs!D14-Inputs!B14)*BETAINV(RAND(),Model!H8,Model!I8) -> 0.16872036 | Q74: =Inputs!E14+(Inputs!G14-Inputs!E14)*BETAINV(RAND(),Model!J8,Model!K8) -> 0.51695513 | R74: =(Inputs!H14+(Inputs!J14-Inputs!H14)*BETAINV(RAND(),Model!L8,Model!M8))*Inputs!$C$6 -> 250599.73 | S74: =P74*Q74 -> 0.087220854 | T74: =RAND() -> 0.28657727 | U74: =IF(T74<EXP(-S74),0,IF(T74<EXP(-S74)*(1+S74),1,IF(T74<EXP(-S74)*(1+S74+S74^2/2),2,IF(T74<EXP(-S74)*(1+S74+S74^2/2+S74^3/6),3,4)))) -> 0 | V74: =U74*R74 -> 0 | W74: =Inputs!B15+(Inputs!D15-Inputs!B15)*BETAINV(RAND(),Model!H9,Model!I9) -> 0.4134057 | X74: =Inputs!E15+(Inputs!G15-Inputs!E15)*BETAINV(RAND(),Model!J9,Model!K9) -> 0.45829034 | Y74: =(Inputs!H15+(Inputs!J15-Inputs!H15)*BETAINV(RAND(),Model!L9,Model!M9))*Inputs!$C$6 -> 17696.094 | Z74: =W74*X74 -> 0.18945984 | AA74: =RAND() -> 0.072237915 | AB74: =IF(AA74<EXP(-Z74),0,IF(AA74<EXP(-Z74)*(1+Z74),1,IF(AA74<EXP(-Z74)*(1+Z74+Z74^2/2),2,IF(AA74<EXP(-Z74)*(1+Z74+Z74^2/2+Z74^3/6),3,4)))) -> 0 | AC74: =AB74*Y74 -> 0 | AD74: =Inputs!B16+(Inputs!D16-Inputs!B16)*BETAINV(RAND(),Model!H10,Model!I10) -> 1.0030828 | AE74: =Inputs!E16+(Inputs!G16-Inputs!E16)*BETAINV(RAND(),Model!J10,Model!K10) -> 0.71858863 | AF74: =(Inputs!H16+(Inputs!J16-Inputs!H16)*BETAINV(RAND(),Model!L10,Model!M10))*Inputs!$C$6 -> 88096.254 | AG74: =AD74*AE74 -> 0.72080393 | AH74: =RAND() -> 0.78943751 | AI74: =IF(AH74<EXP(-AG74),0,IF(AH74<EXP(-AG74)*(1+AG74),1,IF(AH74<EXP(-AG74)*(1+AG74+AG74^2/2),2,IF(AH74<EXP(-AG74)*(1+AG74+AG74^2/2+AG74^3/6),3,4)))) -> 1 | AJ74: =AI74*AF74 -> 88096.254 | AK74: =H74+O74+V74+AC74+AJ74 -> 208035.14
B75: =Inputs!B12+(Inputs!D12-Inputs!B12)*BETAINV(RAND(),Model!H6,Model!I6) -> 4.8830605 | C75: =Inputs!E12+(Inputs!G12-Inputs!E12)*BETAINV(RAND(),Model!J6,Model!K6) -> 0.40033833 | D75: =(Inputs!H12+(Inputs!J12-Inputs!H12)*BETAINV(RAND(),Model!L6,Model!M6))*Inputs!$C$6 -> 12284.552 | E75: =B75*C75 -> 1.9548763 | F75: =RAND() -> 0.15527557 | G75: =IF(F75<EXP(-E75),0,IF(F75<EXP(-E75)*(1+E75),1,IF(F75<EXP(-E75)*(1+E75+E75^2/2),2,IF(F75<EXP(-E75)*(1+E75+E75^2/2+E75^3/6),3,4)))) -> 1 | H75: =G75*D75 -> 12284.552 | I75: =Inputs!B13+(Inputs!D13-Inputs!B13)*BETAINV(RAND(),Model!H7,Model!I7) -> 1.885098 | J75: =Inputs!E13+(Inputs!G13-Inputs!E13)*BETAINV(RAND(),Model!J7,Model!K7) -> 0.21096504 | K75: =(Inputs!H13+(Inputs!J13-Inputs!H13)*BETAINV(RAND(),Model!L7,Model!M7))*Inputs!$C$6 -> 20053.146 | L75: =I75*J75 -> 0.39768976 | M75: =RAND() -> 0.58557021 | N75: =IF(M75<EXP(-L75),0,IF(M75<EXP(-L75)*(1+L75),1,IF(M75<EXP(-L75)*(1+L75+L75^2/2),2,IF(M75<EXP(-L75)*(1+L75+L75^2/2+L75^3/6),3,4)))) -> 0 | O75: =N75*K75 -> 0 | P75: =Inputs!B14+(Inputs!D14-Inputs!B14)*BETAINV(RAND(),Model!H8,Model!I8) -> 0.25348142 | Q75: =Inputs!E14+(Inputs!G14-Inputs!E14)*BETAINV(RAND(),Model!J8,Model!K8) -> 0.7886272 | R75: =(Inputs!H14+(Inputs!J14-Inputs!H14)*BETAINV(RAND(),Model!L8,Model!M8))*Inputs!$C$6 -> 191593.9 | S75: =P75*Q75 -> 0.19990234 | T75: =RAND() -> 0.016769672 | U75: =IF(T75<EXP(-S75),0,IF(T75<EXP(-S75)*(1+S75),1,IF(T75<EXP(-S75)*(1+S75+S75^2/2),2,IF(T75<EXP(-S75)*(1+S75+S75^2/2+S75^3/6),3,4)))) -> 0 | V75: =U75*R75 -> 0 | W75: =Inputs!B15+(Inputs!D15-Inputs!B15)*BETAINV(RAND(),Model!H9,Model!I9) -> 0.94517716 | X75: =Inputs!E15+(Inputs!G15-Inputs!E15)*BETAINV(RAND(),Model!J9,Model!K9) -> 0.42408821 | Y75: =(Inputs!H15+(Inputs!J15-Inputs!H15)*BETAINV(RAND(),Model!L9,Model!M9))*Inputs!$C$6 -> 48309.154 | Z75: =W75*X75 -> 0.40083849 | AA75: =RAND() -> 0.72454739 | AB75: =IF(AA75<EXP(-Z75),0,IF(AA75<EXP(-Z75)*(1+Z75),1,IF(AA75<EXP(-Z75)*(1+Z75+Z75^2/2),2,IF(AA75<EXP(-Z75)*(1+Z75+Z75^2/2+Z75^3/6),3,4)))) -> 1 | AC75: =AB75*Y75 -> 48309.154 | AD75: =Inputs!B16+(Inputs!D16-Inputs!B16)*BETAINV(RAND(),Model!H10,Model!I10) -> 0.34051499 | AE75: =Inputs!E16+(Inputs!G16-Inputs!E16)*BETAINV(RAND(),Model!J10,Model!K10) -> 0.44090803 | AF75: =(Inputs!H16+(Inputs!J16-Inputs!H16)*BETAINV(RAND(),Model!L10,Model!M10))*Inputs!$C$6 -> 38023.93 | AG75: =AD75*AE75 -> 0.15013579 | AH75: =RAND() -> 0.30233286 | AI75: =IF(AH75<EXP(-AG75),0,IF(AH75<EXP(-AG75)*(1+AG75),1,IF(AH75<EXP(-AG75)*(1+AG75+AG75^2/2),2,IF(AH75<EXP(-AG75)*(1+AG75+AG75^2/2+AG75^3/6),3,4)))) -> 0 | AJ75: =AI75*AF75 -> 0 | AK75: =H75+O75+V75+AC75+AJ75 -> 60593.706
B76: =Inputs!B12+(Inputs!D12-Inputs!B12)*BETAINV(RAND(),Model!H6,Model!I6) -> 2.3433015 | C76: =Inputs!E12+(Inputs!G12-Inputs!E12)*BETAINV(RAND(),Model!J6,Model!K6) -> 0.41744695 | D76: =(Inputs!H12+(Inputs!J12-Inputs!H12)*BETAINV(RAND(),Model!L6,Model!M6))*Inputs!$C$6 -> 26969.988 | E76: =B76*C76 -> 0.97820404 | F76: =RAND() -> 0.5567243 | G76: =IF(F76<EXP(-E76),0,IF(F76<EXP(-E76)*(1+E76),1,IF(F76<EXP(-E76)*(1+E76+E76^2/2),2,IF(F76<EXP(-E76)*(1+E76+E76^2/2+E76^3/6),3,4)))) -> 1 | H76: =G76*D76 -> 26969.988 | I76: =Inputs!B13+(Inputs!D13-Inputs!B13)*BETAINV(RAND(),Model!H7,Model!I7) -> 1.0468561 | J76: =Inputs!E13+(Inputs!G13-Inputs!E13)*BETAINV(RAND(),Model!J7,Model!K7) -> 0.22755019 | K76: =(Inputs!H13+(Inputs!J13-Inputs!H13)*BETAINV(RAND(),Model!L7,Model!M7))*Inputs!$C$6 -> 23222.86 | L76: =I76*J76 -> 0.23821229 | M76: =RAND() -> 0.99512785 | N76: =IF(M76<EXP(-L76),0,IF(M76<EXP(-L76)*(1+L76),1,IF(M76<EXP(-L76)*(1+L76+L76^2/2),2,IF(M76<EXP(-L76)*(1+L76+L76^2/2+L76^3/6),3,4)))) -> 2 | O76: =N76*K76 -> 46445.72 | P76: =Inputs!B14+(Inputs!D14-Inputs!B14)*BETAINV(RAND(),Model!H8,Model!I8) -> 0.13393053 | Q76: =Inputs!E14+(Inputs!G14-Inputs!E14)*BETAINV(RAND(),Model!J8,Model!K8) -> 0.43796681 | R76: =(Inputs!H14+(Inputs!J14-Inputs!H14)*BETAINV(RAND(),Model!L8,Model!M8))*Inputs!$C$6 -> 383973.99 | S76: =P76*Q76 -> 0.058657128 | T76: =RAND() -> 0.40437032 | U76: =IF(T76<EXP(-S76),0,IF(T76<EXP(-S76)*(1+S76),1,IF(T76<EXP(-S76)*(1+S76+S76^2/2),2,IF(T76<EXP(-S76)*(1+S76+S76^2/2+S76^3/6),3,4)))) -> 0 | V76: =U76*R76 -> 0 | W76: =Inputs!B15+(Inputs!D15-Inputs!B15)*BETAINV(RAND(),Model!H9,Model!I9) -> 0.50636702 | X76: =Inputs!E15+(Inputs!G15-Inputs!E15)*BETAINV(RAND(),Model!J9,Model!K9) -> 0.37483907 | Y76: =(Inputs!H15+(Inputs!J15-Inputs!H15)*BETAINV(RAND(),Model!L9,Model!M9))*Inputs!$C$6 -> 52706.14 | Z76: =W76*X76 -> 0.18980614 | AA76: =RAND() -> 0.94615092 | AB76: =IF(AA76<EXP(-Z76),0,IF(AA76<EXP(-Z76)*(1+Z76),1,IF(AA76<EXP(-Z76)*(1+Z76+Z76^2/2),2,IF(AA76<EXP(-Z76)*(1+Z76+Z76^2/2+Z76^3/6),3,4)))) -> 1 | AC76: =AB76*Y76 -> 52706.14 | AD76: =Inputs!B16+(Inputs!D16-Inputs!B16)*BETAINV(RAND(),Model!H10,Model!I10) -> 0.83774061 | AE76: =Inputs!E16+(Inputs!G16-Inputs!E16)*BETAINV(RAND(),Model!J10,Model!K10) -> 0.58853073 | AF76: =(Inputs!H16+(Inputs!J16-Inputs!H16)*BETAINV(RAND(),Model!L10,Model!M10))*Inputs!$C$6 -> 44790.561 | AG76: =AD76*AE76 -> 0.49303609 | AH76: =RAND() -> 0.084359687 | AI76: =IF(AH76<EXP(-AG76),0,IF(AH76<EXP(-AG76)*(1+AG76),1,IF(AH76<EXP(-AG76)*(1+AG76+AG76^2/2),2,IF(AH76<EXP(-AG76)*(1+AG76+AG76^2/2+AG76^3/6),3,4)))) -> 0 | AJ76: =AI76*AF76 -> 0 | AK76: =H76+O76+V76+AC76+AJ76 -> 126121.85
B77: =Inputs!B12+(Inputs!D12-Inputs!B12)*BETAINV(RAND(),Model!H6,Model!I6) -> 5.7015193 | C77: =Inputs!E12+(Inputs!G12-Inputs!E12)*BETAINV(RAND(),Model!J6,Model!K6) -> 0.27918409 | D77: =(Inputs!H12+(Inputs!J12-Inputs!H12)*BETAINV(RAND(),Model!L6,Model!M6))*Inputs!$C$6 -> 34631.852 | E77: =B77*C77 -> 1.5917735 | F77: =RAND() -> 0.9717463 | G77: =IF(F77<EXP(-E77),0,IF(F77<EXP(-E77)*(1+E77),1,IF(F77<EXP(-E77)*(1+E77+E77^2/2),2,IF(F77<EXP(-E77)*(1+E77+E77^2/2+E77^3/6),3,4)))) -> 4 | H77: =G77*D77 -> 138527.41 | I77: =Inputs!B13+(Inputs!D13-Inputs!B13)*BETAINV(RAND(),Model!H7,Model!I7) -> 2.4652995 | J77: =Inputs!E13+(Inputs!G13-Inputs!E13)*BETAINV(RAND(),Model!J7,Model!K7) -> 0.33074787 | K77: =(Inputs!H13+(Inputs!J13-Inputs!H13)*BETAINV(RAND(),Model!L7,Model!M7))*Inputs!$C$6 -> 54566.718 | L77: =I77*J77 -> 0.81539255 | M77: =RAND() -> 0.59557569 | N77: =IF(M77<EXP(-L77),0,IF(M77<EXP(-L77)*(1+L77),1,IF(M77<EXP(-L77)*(1+L77+L77^2/2),2,IF(M77<EXP(-L77)*(1+L77+L77^2/2+L77^3/6),3,4)))) -> 1 | O77: =N77*K77 -> 54566.718 | P77: =Inputs!B14+(Inputs!D14-Inputs!B14)*BETAINV(RAND(),Model!H8,Model!I8) -> 0.32949544 | Q77: =Inputs!E14+(Inputs!G14-Inputs!E14)*BETAINV(RAND(),Model!J8,Model!K8) -> 0.68414256 | R77: =(Inputs!H14+(Inputs!J14-Inputs!H14)*BETAINV(RAND(),Model!L8,Model!M8))*Inputs!$C$6 -> 201945.56 | S77: =P77*Q77 -> 0.22542186 | T77: =RAND() -> 0.63042869 | U77: =IF(T77<EXP(-S77),0,IF(T77<EXP(-S77)*(1+S77),1,IF(T77<EXP(-S77)*(1+S77+S77^2/2),2,IF(T77<EXP(-S77)*(1+S77+S77^2/2+S77^3/6),3,4)))) -> 0 | V77: =U77*R77 -> 0 | W77: =Inputs!B15+(Inputs!D15-Inputs!B15)*BETAINV(RAND(),Model!H9,Model!I9) -> 1.801701 | X77: =Inputs!E15+(Inputs!G15-Inputs!E15)*BETAINV(RAND(),Model!J9,Model!K9) -> 0.33326618 | Y77: =(Inputs!H15+(Inputs!J15-Inputs!H15)*BETAINV(RAND(),Model!L9,Model!M9))*Inputs!$C$6 -> 22457.607 | Z77: =W77*X77 -> 0.600446 | AA77: =RAND() -> 0.9941197 | AB77: =IF(AA77<EXP(-Z77),0,IF(AA77<EXP(-Z77)*(1+Z77),1,IF(AA77<EXP(-Z77)*(1+Z77+Z77^2/2),2,IF(AA77<EXP(-Z77)*(1+Z77+Z77^2/2+Z77^3/6),3,4)))) -> 3 | AC77: =AB77*Y77 -> 67372.82 | AD77: =Inputs!B16+(Inputs!D16-Inputs!B16)*BETAINV(RAND(),Model!H10,Model!I10) -> 0.99569303 | AE77: =Inputs!E16+(Inputs!G16-Inputs!E16)*BETAINV(RAND(),Model!J10,Model!K10) -> 0.65143965 | AF77: =(Inputs!H16+(Inputs!J16-Inputs!H16)*BETAINV(RAND(),Model!L10,Model!M10))*Inputs!$C$6 -> 77473.751 | AG77: =AD77*AE77 -> 0.64863392 | AH77: =RAND() -> 0.19805787 | AI77: =IF(AH77<EXP(-AG77),0,IF(AH77<EXP(-AG77)*(1+AG77),1,IF(AH77<EXP(-AG77)*(1+AG77+AG77^2/2),2,IF(AH77<EXP(-AG77)*(1+AG77+AG77^2/2+AG77^3/6),3,4)))) -> 0 | AJ77: =AI77*AF77 -> 0 | AK77: =H77+O77+V77+AC77+AJ77 -> 260466.95
B78: =Inputs!B12+(Inputs!D12-Inputs!B12)*BETAINV(RAND(),Model!H6,Model!I6) -> 4.1088348 | C78: =Inputs!E12+(Inputs!G12-Inputs!E12)*BETAINV(RAND(),Model!J6,Model!K6) -> 0.30939417 | D78: =(Inputs!H12+(Inputs!J12-Inputs!H12)*BETAINV(RAND(),Model!L6,Model!M6))*Inputs!$C$6 -> 35561.011 | E78: =B78*C78 -> 1.2712496 | F78: =RAND() -> 0.039876587 | G78: =IF(F78<EXP(-E78),0,IF(F78<EXP(-E78)*(1+E78),1,IF(F78<EXP(-E78)*(1+E78+E78^2/2),2,IF(F78<EXP(-E78)*(1+E78+E78^2/2+E78^3/6),3,4)))) -> 0 | H78: =G78*D78 -> 0 | I78: =Inputs!B13+(Inputs!D13-Inputs!B13)*BETAINV(RAND(),Model!H7,Model!I7) -> 3.9659431 | J78: =Inputs!E13+(Inputs!G13-Inputs!E13)*BETAINV(RAND(),Model!J7,Model!K7) -> 0.24950553 | K78: =(Inputs!H13+(Inputs!J13-Inputs!H13)*BETAINV(RAND(),Model!L7,Model!M7))*Inputs!$C$6 -> 13762.391 | L78: =I78*J78 -> 0.98952474 | M78: =RAND() -> 0.53830432 | N78: =IF(M78<EXP(-L78),0,IF(M78<EXP(-L78)*(1+L78),1,IF(M78<EXP(-L78)*(1+L78+L78^2/2),2,IF(M78<EXP(-L78)*(1+L78+L78^2/2+L78^3/6),3,4)))) -> 1 | O78: =N78*K78 -> 13762.391 | P78: =Inputs!B14+(Inputs!D14-Inputs!B14)*BETAINV(RAND(),Model!H8,Model!I8) -> 0.38624627 | Q78: =Inputs!E14+(Inputs!G14-Inputs!E14)*BETAINV(RAND(),Model!J8,Model!K8) -> 0.49717688 | R78: =(Inputs!H14+(Inputs!J14-Inputs!H14)*BETAINV(RAND(),Model!L8,Model!M8))*Inputs!$C$6 -> 492008.31 | S78: =P78*Q78 -> 0.19203271 | T78: =RAND() -> 0.1323448 | U78: =IF(T78<EXP(-S78),0,IF(T78<EXP(-S78)*(1+S78),1,IF(T78<EXP(-S78)*(1+S78+S78^2/2),2,IF(T78<EXP(-S78)*(1+S78+S78^2/2+S78^3/6),3,4)))) -> 0 | V78: =U78*R78 -> 0 | W78: =Inputs!B15+(Inputs!D15-Inputs!B15)*BETAINV(RAND(),Model!H9,Model!I9) -> 0.47731261 | X78: =Inputs!E15+(Inputs!G15-Inputs!E15)*BETAINV(RAND(),Model!J9,Model!K9) -> 0.48460352 | Y78: =(Inputs!H15+(Inputs!J15-Inputs!H15)*BETAINV(RAND(),Model!L9,Model!M9))*Inputs!$C$6 -> 24934.673 | Z78: =W78*X78 -> 0.23130737 | AA78: =RAND() -> 0.27894657 | AB78: =IF(AA78<EXP(-Z78),0,IF(AA78<EXP(-Z78)*(1+Z78),1,IF(AA78<EXP(-Z78)*(1+Z78+Z78^2/2),2,IF(AA78<EXP(-Z78)*(1+Z78+Z78^2/2+Z78^3/6),3,4)))) -> 0 | AC78: =AB78*Y78 -> 0 | AD78: =Inputs!B16+(Inputs!D16-Inputs!B16)*BETAINV(RAND(),Model!H10,Model!I10) -> 0.43737658 | AE78: =Inputs!E16+(Inputs!G16-Inputs!E16)*BETAINV(RAND(),Model!J10,Model!K10) -> 0.55934328 | AF78: =(Inputs!H16+(Inputs!J16-Inputs!H16)*BETAINV(RAND(),Model!L10,Model!M10))*Inputs!$C$6 -> 61528.339 | AG78: =AD78*AE78 -> 0.24464365 | AH78: =RAND() -> 0.11279398 | AI78: =IF(AH78<EXP(-AG78),0,IF(AH78<EXP(-AG78)*(1+AG78),1,IF(AH78<EXP(-AG78)*(1+AG78+AG78^2/2),2,IF(AH78<EXP(-AG78)*(1+AG78+AG78^2/2+AG78^3/6),3,4)))) -> 0 | AJ78: =AI78*AF78 -> 0 | AK78: =H78+O78+V78+AC78+AJ78 -> 13762.391
B79: =Inputs!B12+(Inputs!D12-Inputs!B12)*BETAINV(RAND(),Model!H6,Model!I6) -> 5.1030781 | C79: =Inputs!E12+(Inputs!G12-Inputs!E12)*BETAINV(RAND(),Model!J6,Model!K6) -> 0.25346089 | D79: =(Inputs!H12+(Inputs!J12-Inputs!H12)*BETAINV(RAND(),Model!L6,Model!M6))*Inputs!$C$6 -> 46574.323 | E79: =B79*C79 -> 1.2934307 | F79: =RAND() -> 0.5948688 | G79: =IF(F79<EXP(-E79),0,IF(F79<EXP(-E79)*(1+E79),1,IF(F79<EXP(-E79)*(1+E79+E79^2/2),2,IF(F79<EXP(-E79)*(1+E79+E79^2/2+E79^3/6),3,4)))) -> 1 | H79: =G79*D79 -> 46574.323 | I79: =Inputs!B13+(Inputs!D13-Inputs!B13)*BETAINV(RAND(),Model!H7,Model!I7) -> 1.5315449 | J79: =Inputs!E13+(Inputs!G13-Inputs!E13)*BETAINV(RAND(),Model!J7,Model!K7) -> 0.14694426 | K79: =(Inputs!H13+(Inputs!J13-Inputs!H13)*BETAINV(RAND(),Model!L7,Model!M7))*Inputs!$C$6 -> 28743.874 | L79: =I79*J79 -> 0.22505174 | M79: =RAND() -> 0.59212788 | N79: =IF(M79<EXP(-L79),0,IF(M79<EXP(-L79)*(1+L79),1,IF(M79<EXP(-L79)*(1+L79+L79^2/2),2,IF(M79<EXP(-L79)*(1+L79+L79^2/2+L79^3/6),3,4)))) -> 0 | O79: =N79*K79 -> 0 | P79: =Inputs!B14+(Inputs!D14-Inputs!B14)*BETAINV(RAND(),Model!H8,Model!I8) -> 0.45142165 | Q79: =Inputs!E14+(Inputs!G14-Inputs!E14)*BETAINV(RAND(),Model!J8,Model!K8) -> 0.7987362 | R79: =(Inputs!H14+(Inputs!J14-Inputs!H14)*BETAINV(RAND(),Model!L8,Model!M8))*Inputs!$C$6 -> 205370.21 | S79: =P79*Q79 -> 0.36056681 | T79: =RAND() -> 0.8796009 | U79: =IF(T79<EXP(-S79),0,IF(T79<EXP(-S79)*(1+S79),1,IF(T79<EXP(-S79)*(1+S79+S79^2/2),2,IF(T79<EXP(-S79)*(1+S79+S79^2/2+S79^3/6),3,4)))) -> 1 | V79: =U79*R79 -> 205370.21 | W79: =Inputs!B15+(Inputs!D15-Inputs!B15)*BETAINV(RAND(),Model!H9,Model!I9) -> 1.9262795 | X79: =Inputs!E15+(Inputs!G15-Inputs!E15)*BETAINV(RAND(),Model!J9,Model!K9) -> 0.3733824 | Y79: =(Inputs!H15+(Inputs!J15-Inputs!H15)*BETAINV(RAND(),Model!L9,Model!M9))*Inputs!$C$6 -> 43530.583 | Z79: =W79*X79 -> 0.71923887 | AA79: =RAND() -> 0.90565462 | AB79: =IF(AA79<EXP(-Z79),0,IF(AA79<EXP(-Z79)*(1+Z79),1,IF(AA79<EXP(-Z79)*(1+Z79+Z79^2/2),2,IF(AA79<EXP(-Z79)*(1+Z79+Z79^2/2+Z79^3/6),3,4)))) -> 2 | AC79: =AB79*Y79 -> 87061.167 | AD79: =Inputs!B16+(Inputs!D16-Inputs!B16)*BETAINV(RAND(),Model!H10,Model!I10) -> 1.0156205 | AE79: =Inputs!E16+(Inputs!G16-Inputs!E16)*BETAINV(RAND(),Model!J10,Model!K10) -> 0.65809075 | AF79: =(Inputs!H16+(Inputs!J16-Inputs!H16)*BETAINV(RAND(),Model!L10,Model!M10))*Inputs!$C$6 -> 156342.47 | AG79: =AD79*AE79 -> 0.66837044 | AH79: =RAND() -> 0.73020535 | AI79: =IF(AH79<EXP(-AG79),0,IF(AH79<EXP(-AG79)*(1+AG79),1,IF(AH79<EXP(-AG79)*(1+AG79+AG79^2/2),2,IF(AH79<EXP(-AG79)*(1+AG79+AG79^2/2+AG79^3/6),3,4)))) -> 1 | AJ79: =AI79*AF79 -> 156342.47 | AK79: =H79+O79+V79+AC79+AJ79 -> 495348.17
B80: =Inputs!B12+(Inputs!D12-Inputs!B12)*BETAINV(RAND(),Model!H6,Model!I6) -> 4.458867 | C80: =Inputs!E12+(Inputs!G12-Inputs!E12)*BETAINV(RAND(),Model!J6,Model!K6) -> 0.19007728 | D80: =(Inputs!H12+(Inputs!J12-Inputs!H12)*BETAINV(RAND(),Model!L6,Model!M6))*Inputs!$C$6 -> 37639.252 | E80: =B80*C80 -> 0.8475293 | F80: =RAND() -> 0.39635804 | G80: =IF(F80<EXP(-E80),0,IF(F80<EXP(-E80)*(1+E80),1,IF(F80<EXP(-E80)*(1+E80+E80^2/2),2,IF(F80<EXP(-E80)*(1+E80+E80^2/2+E80^3/6),3,4)))) -> 0 | H80: =G80*D80 -> 0 | I80: =Inputs!B13+(Inputs!D13-Inputs!B13)*BETAINV(RAND(),Model!H7,Model!I7) -> 1.1860294 | J80: =Inputs!E13+(Inputs!G13-Inputs!E13)*BETAINV(RAND(),Model!J7,Model!K7) -> 0.26509028 | K80: =(Inputs!H13+(Inputs!J13-Inputs!H13)*BETAINV(RAND(),Model!L7,Model!M7))*Inputs!$C$6 -> 27001.174 | L80: =I80*J80 -> 0.31440488 | M80: =RAND() -> 0.40624775 | N80: =IF(M80<EXP(-L80),0,IF(M80<EXP(-L80)*(1+L80),1,IF(M80<EXP(-L80)*(1+L80+L80^2/2),2,IF(M80<EXP(-L80)*(1+L80+L80^2/2+L80^3/6),3,4)))) -> 0 | O80: =N80*K80 -> 0 | P80: =Inputs!B14+(Inputs!D14-Inputs!B14)*BETAINV(RAND(),Model!H8,Model!I8) -> 0.49071576 | Q80: =Inputs!E14+(Inputs!G14-Inputs!E14)*BETAINV(RAND(),Model!J8,Model!K8) -> 0.54602847 | R80: =(Inputs!H14+(Inputs!J14-Inputs!H14)*BETAINV(RAND(),Model!L8,Model!M8))*Inputs!$C$6 -> 403703.85 | S80: =P80*Q80 -> 0.26794477 | T80: =RAND() -> 0.91979124 | U80: =IF(T80<EXP(-S80),0,IF(T80<EXP(-S80)*(1+S80),1,IF(T80<EXP(-S80)*(1+S80+S80^2/2),2,IF(T80<EXP(-S80)*(1+S80+S80^2/2+S80^3/6),3,4)))) -> 1 | V80: =U80*R80 -> 403703.85 | W80: =Inputs!B15+(Inputs!D15-Inputs!B15)*BETAINV(RAND(),Model!H9,Model!I9) -> 1.9420686 | X80: =Inputs!E15+(Inputs!G15-Inputs!E15)*BETAINV(RAND(),Model!J9,Model!K9) -> 0.55795316 | Y80: =(Inputs!H15+(Inputs!J15-Inputs!H15)*BETAINV(RAND(),Model!L9,Model!M9))*Inputs!$C$6 -> 13005.72 | Z80: =W80*X80 -> 1.0835833 | AA80: =RAND() -> 0.30134064 | AB80: =IF(AA80<EXP(-Z80),0,IF(AA80<EXP(-Z80)*(1+Z80),1,IF(AA80<EXP(-Z80)*(1+Z80+Z80^2/2),2,IF(AA80<EXP(-Z80)*(1+Z80+Z80^2/2+Z80^3/6),3,4)))) -> 0 | AC80: =AB80*Y80 -> 0 | AD80: =Inputs!B16+(Inputs!D16-Inputs!B16)*BETAINV(RAND(),Model!H10,Model!I10) -> 0.68779507 | AE80: =Inputs!E16+(Inputs!G16-Inputs!E16)*BETAINV(RAND(),Model!J10,Model!K10) -> 0.65210255 | AF80: =(Inputs!H16+(Inputs!J16-Inputs!H16)*BETAINV(RAND(),Model!L10,Model!M10))*Inputs!$C$6 -> 70612.8 | AG80: =AD80*AE80 -> 0.44851292 | AH80: =RAND() -> 0.37485819 | AI80: =IF(AH80<EXP(-AG80),0,IF(AH80<EXP(-AG80)*(1+AG80),1,IF(AH80<EXP(-AG80)*(1+AG80+AG80^2/2),2,IF(AH80<EXP(-AG80)*(1+AG80+AG80^2/2+AG80^3/6),3,4)))) -> 0 | AJ80: =AI80*AF80 -> 0 | AK80: =H80+O80+V80+AC80+AJ80 -> 403703.85
B81: =Inputs!B12+(Inputs!D12-Inputs!B12)*BETAINV(RAND(),Model!H6,Model!I6) -> 4.8178957 | C81: =Inputs!E12+(Inputs!G12-Inputs!E12)*BETAINV(RAND(),Model!J6,Model!K6) -> 0.41125125 | D81: =(Inputs!H12+(Inputs!J12-Inputs!H12)*BETAINV(RAND(),Model!L6,Model!M6))*Inputs!$C$6 -> 27976.026 | E81: =B81*C81 -> 1.9813656 | F81: =RAND() -> 0.77406433 | G81: =IF(F81<EXP(-E81),0,IF(F81<EXP(-E81)*(1+E81),1,IF(F81<EXP(-E81)*(1+E81+E81^2/2),2,IF(F81<EXP(-E81)*(1+E81+E81^2/2+E81^3/6),3,4)))) -> 3 | H81: =G81*D81 -> 83928.079 | I81: =Inputs!B13+(Inputs!D13-Inputs!B13)*BETAINV(RAND(),Model!H7,Model!I7) -> 1.2298379 | J81: =Inputs!E13+(Inputs!G13-Inputs!E13)*BETAINV(RAND(),Model!J7,Model!K7) -> 0.32697868 | K81: =(Inputs!H13+(Inputs!J13-Inputs!H13)*BETAINV(RAND(),Model!L7,Model!M7))*Inputs!$C$6 -> 62378.897 | L81: =I81*J81 -> 0.40213076 | M81: =RAND() -> 0.87391579 | N81: =IF(M81<EXP(-L81),0,IF(M81<EXP(-L81)*(1+L81),1,IF(M81<EXP(-L81)*(1+L81+L81^2/2),2,IF(M81<EXP(-L81)*(1+L81+L81^2/2+L81^3/6),3,4)))) -> 1 | O81: =N81*K81 -> 62378.897 | P81: =Inputs!B14+(Inputs!D14-Inputs!B14)*BETAINV(RAND(),Model!H8,Model!I8) -> 0.52844232 | Q81: =Inputs!E14+(Inputs!G14-Inputs!E14)*BETAINV(RAND(),Model!J8,Model!K8) -> 0.49867055 | R81: =(Inputs!H14+(Inputs!J14-Inputs!H14)*BETAINV(RAND(),Model!L8,Model!M8))*Inputs!$C$6 -> 498549.9 | S81: =P81*Q81 -> 0.26351862 | T81: =RAND() -> 0.45561298 | U81: =IF(T81<EXP(-S81),0,IF(T81<EXP(-S81)*(1+S81),1,IF(T81<EXP(-S81)*(1+S81+S81^2/2),2,IF(T81<EXP(-S81)*(1+S81+S81^2/2+S81^3/6),3,4)))) -> 0 | V81: =U81*R81 -> 0 | W81: =Inputs!B15+(Inputs!D15-Inputs!B15)*BETAINV(RAND(),Model!H9,Model!I9) -> 1.2845109 | X81: =Inputs!E15+(Inputs!G15-Inputs!E15)*BETAINV(RAND(),Model!J9,Model!K9) -> 0.45519397 | Y81: =(Inputs!H15+(Inputs!J15-Inputs!H15)*BETAINV(RAND(),Model!L9,Model!M9))*Inputs!$C$6 -> 39749.707 | Z81: =W81*X81 -> 0.58470164 | AA81: =RAND() -> 0.44557364 | AB81: =IF(AA81<EXP(-Z81),0,IF(AA81<EXP(-Z81)*(1+Z81),1,IF(AA81<EXP(-Z81)*(1+Z81+Z81^2/2),2,IF(AA81<EXP(-Z81)*(1+Z81+Z81^2/2+Z81^3/6),3,4)))) -> 0 | AC81: =AB81*Y81 -> 0 | AD81: =Inputs!B16+(Inputs!D16-Inputs!B16)*BETAINV(RAND(),Model!H10,Model!I10) -> 0.5495311 | AE81: =Inputs!E16+(Inputs!G16-Inputs!E16)*BETAINV(RAND(),Model!J10,Model!K10) -> 0.74928344 | AF81: =(Inputs!H16+(Inputs!J16-Inputs!H16)*BETAINV(RAND(),Model!L10,Model!M10))*Inputs!$C$6 -> 44677.282 | AG81: =AD81*AE81 -> 0.41175456 | AH81: =RAND() -> 0.22805142 | AI81: =IF(AH81<EXP(-AG81),0,IF(AH81<EXP(-AG81)*(1+AG81),1,IF(AH81<EXP(-AG81)*(1+AG81+AG81^2/2),2,IF(AH81<EXP(-AG81)*(1+AG81+AG81^2/2+AG81^3/6),3,4)))) -> 0 | AJ81: =AI81*AF81 -> 0 | AK81: =H81+O81+V81+AC81+AJ81 -> 146306.98
B82: =Inputs!B12+(Inputs!D12-Inputs!B12)*BETAINV(RAND(),Model!H6,Model!I6) -> 1.6801264 | C82: =Inputs!E12+(Inputs!G12-Inputs!E12)*BETAINV(RAND(),Model!J6,Model!K6) -> 0.23564362 | D82: =(Inputs!H12+(Inputs!J12-Inputs!H12)*BETAINV(RAND(),Model!L6,Model!M6))*Inputs!$C$6 -> 20091.988 | E82: =B82*C82 -> 0.39591108 | F82: =RAND() -> 0.51053479 | G82: =IF(F82<EXP(-E82),0,IF(F82<EXP(-E82)*(1+E82),1,IF(F82<EXP(-E82)*(1+E82+E82^2/2),2,IF(F82<EXP(-E82)*(1+E82+E82^2/2+E82^3/6),3,4)))) -> 0 | H82: =G82*D82 -> 0 | I82: =Inputs!B13+(Inputs!D13-Inputs!B13)*BETAINV(RAND(),Model!H7,Model!I7) -> 2.064222 | J82: =Inputs!E13+(Inputs!G13-Inputs!E13)*BETAINV(RAND(),Model!J7,Model!K7) -> 0.24179692 | K82: =(Inputs!H13+(Inputs!J13-Inputs!H13)*BETAINV(RAND(),Model!L7,Model!M7))*Inputs!$C$6 -> 77769.068 | L82: =I82*J82 -> 0.49912253 | M82: =RAND() -> 0.59704745 | N82: =IF(M82<EXP(-L82),0,IF(M82<EXP(-L82)*(1+L82),1,IF(M82<EXP(-L82)*(1+L82+L82^2/2),2,IF(M82<EXP(-L82)*(1+L82+L82^2/2+L82^3/6),3,4)))) -> 0 | O82: =N82*K82 -> 0 | P82: =Inputs!B14+(Inputs!D14-Inputs!B14)*BETAINV(RAND(),Model!H8,Model!I8) -> 0.12373902 | Q82: =Inputs!E14+(Inputs!G14-Inputs!E14)*BETAINV(RAND(),Model!J8,Model!K8) -> 0.52735705 | R82: =(Inputs!H14+(Inputs!J14-Inputs!H14)*BETAINV(RAND(),Model!L8,Model!M8))*Inputs!$C$6 -> 491561.8 | S82: =P82*Q82 -> 0.065254646 | T82: =RAND() -> 0.94078811 | U82: =IF(T82<EXP(-S82),0,IF(T82<EXP(-S82)*(1+S82),1,IF(T82<EXP(-S82)*(1+S82+S82^2/2),2,IF(T82<EXP(-S82)*(1+S82+S82^2/2+S82^3/6),3,4)))) -> 1 | V82: =U82*R82 -> 491561.8 | W82: =Inputs!B15+(Inputs!D15-Inputs!B15)*BETAINV(RAND(),Model!H9,Model!I9) -> 0.66674072 | X82: =Inputs!E15+(Inputs!G15-Inputs!E15)*BETAINV(RAND(),Model!J9,Model!K9) -> 0.39684333 | Y82: =(Inputs!H15+(Inputs!J15-Inputs!H15)*BETAINV(RAND(),Model!L9,Model!M9))*Inputs!$C$6 -> 36378.216 | Z82: =W82*X82 -> 0.26459161 | AA82: =RAND() -> 0.97454358 | AB82: =IF(AA82<EXP(-Z82),0,IF(AA82<EXP(-Z82)*(1+Z82),1,IF(AA82<EXP(-Z82)*(1+Z82+Z82^2/2),2,IF(AA82<EXP(-Z82)*(1+Z82+Z82^2/2+Z82^3/6),3,4)))) -> 2 | AC82: =AB82*Y82 -> 72756.432 | AD82: =Inputs!B16+(Inputs!D16-Inputs!B16)*BETAINV(RAND(),Model!H10,Model!I10) -> 1.3282289 | AE82: =Inputs!E16+(Inputs!G16-Inputs!E16)*BETAINV(RAND(),Model!J10,Model!K10) -> 0.49147048 | AF82: =(Inputs!H16+(Inputs!J16-Inputs!H16)*BETAINV(RAND(),Model!L10,Model!M10))*Inputs!$C$6 -> 111620.92 | AG82: =AD82*AE82 -> 0.65278529 | AH82: =RAND() -> 0.76679452 | AI82: =IF(AH82<EXP(-AG82),0,IF(AH82<EXP(-AG82)*(1+AG82),1,IF(AH82<EXP(-AG82)*(1+AG82+AG82^2/2),2,IF(AH82<EXP(-AG82)*(1+AG82+AG82^2/2+AG82^3/6),3,4)))) -> 1 | AJ82: =AI82*AF82 -> 111620.92 | AK82: =H82+O82+V82+AC82+AJ82 -> 675939.15
